Workbook

Sheet indice
A1: Capacitação em Direitos Humanos, Gênero, Raça e Etnia; e em Depoimento Especial" - 0148945-13.2024.8.16.6000 | B1: Capacitação de Facilitadores 0148959-94.2024.8.16.6000 | C1: Acessibilidade e Inclusão - 0148938-21.2024.8.16.6000 | D1: Política de Prevenção e Enfrentamento do Assédio Moral, do Assédio Sexual e da Discriminação.0148908-83.2024.8.16.6000 | E1: SUSTENTABILIDADE https://portal.tjpr.jus.br/portletforms/frm.do?idFormulario=7430 0017859-16.2024.8.16.6000
A2: cursos de formação inicial e de formação continuada para capacitação magistrados(as) ativos(as), de primeiro e segundo graus de jurisdição | B2: violência doméstica e familiar contra a mulher | C2: Acessibilidade comunicacional | D2: assédio moral | E2: equidade e diversidade
A3: direitos humanos, gênero, raça e etnia | C3: Acessibilidade tecnológica | D3: assédio sexual | E3: sustentabilidade
A4: depoimento especial | D4: discriminação | E4: elaborar inventários
E5: Emissões de GEE (gases de efeito estufa) e incentivos a práticas sustentáveis
B11: INDICADORES | C11: Tipo de evento | D11: MODALIDADE | E11: DECLARAÇÃO/ CERTIFICADO/ SEM CERTIFICAÇÃO | F11: ON LINE OU PRESENCIAL | G11: PUBLICO ALVO | H11: CATEGORIA DO Curso | I11: STATUS | J11: LIVRO DE REGISTRO
B12: ADMINISTRATIVO | C12: 1. CONGRESSO | D12: AUTOINSTRUCIONAL | E12: Certificado | F12: EAD | G12: LIVRE | H12: APOIO | I12: ARQUIVADO | J12: 1 - LISTA GERAL_2020 A ...
B13: ADOÇÃO | C13: 2. SIMPÓSIO | D13: EVENTO EXTERNO | E13: Declaração | F13: HÍBRIDO (presencial e EAD) | G13: MAGISTRADOS | H13: CONTRATAÇÃO | I13: CURSO FECHADO | J13: 2 - IN COMPANY
B14: BRIGADISTA | C14: 3. SEMINÁRIO | D14: IN COMPANY | E14: Sem certificação | F14: PRESENCIAL | G14: PÚBLICO EXTERNO | H14: CONVITE | I14: PRONTO PARA REGISTRO | J14: 3 - CONCILIAJUD
B15: DTOS HUMANOS E CIDADANIA | C15: 4. PAINEL ACADÊMICO | D15: REPOSITÓRIO | F15: PRESENCIAL COM TRANSMISSÃO AO VIVO | G15: QUADRO INTERNO | H15: DIVULGAÇÃO | I15: NÃO REALIZADO | J15: 3 - EVENTO EXTERNO
B16: ECA | C16: 5. FÓRUM | D16: CERTIFICAÇÃO | F16: TRANSMISSÃO AO VIVO | G16: RESTRITOS | H16: ELABORAÇÃO | I16: SOBRESTADO
B17: GESTÃO | C17: 6. COLÓQUIO | D17: DIVULGAÇÃO | F17: WEBCONFERÊNCIA (teams/zoom) | G17: SERVIDORES | H17: REPLICAÇÃO | I17: SUSPENSO
B18: INOVAÇÃO | C18: 7. CONFERÊNCIA | I18: AUTORIZADO
B19: MEDIAÇÃO | C19: 8. MESA REDONDA
B20: RISCO E COMPLIENCE | C20: 9. JORNADA ACADÊMICA
B21: SAÚDE | C21: 10. SEMANA ACADÊMICA
B22: TECNOLOGIA | C22: 11. WORKSHOP
C23: 12. CURSOS
C24: 13. LIVES
C25: Magistrados - Cred. Enfam
C26: Magistrados - Não Cred
B27: JUSTIÇA RESTAURATIVA
B28: MAGISTRADO
B29: MEIO AMBIENTE
B30: SUSTENTABILIDADE
B31: DEPOIMENTO ESPECIAL
B32: assédio moral, sexual e discriminação.
B33: ACESSIBILIDADE E INCLUSÃO
B34: VIOLÊNCIA DOMESTICA
B35: Reflexão e sensibilização de autores de violência doméstica e familiar

Sheet Cursos antigos
B1: ANO DO CURSO2 | C1: BLOCO | D1: SEI | E1: NOME DO Curso | F1: CATEGORIA DO Curso | G1: RESPONSÁVEL PELA CERTIFICAÇÃO | H1: INSTITUIÇÃO DE ENSINO | I1: EMPRESA CONTRATADA | J1: CNPJ | K1: SEI DOC INSTRUTORES | L1: Intrutor (andamento do SEI) | M1: TERMO DE USO DE IMAGEM | N1: ATESTO | O1: PRE ANOTAÇÃO ATESTO | P1: REG DE INSTRUTORES | Q1: DESPESAS | R1: VALOR DAS DESPESAS | S1: PRODUÇÃO/UNIDADE SOLICITANTE | T1: Eixo de Capacitação - Itinerários Formativos | U1: PAE | V1: INDICADORES | W1: PORTARIA ENFAM | X1: Tipo de evento | Y1: TURMA | Z1: nº de vagas | AA1: INTÉRPRETES DE LIBRAS | AB1: MODALIDADE | AC1: PLANO DE CURSO/SEI | AD1: LOCAL | AE1: ANO DO CURSO2 | AF1: DATA INÍCIO | AG1: DATA TERMINO | AH1: DECLARAÇÃO/ CERTIFICADO/ SEM CERTIFICAÇÃO | AI1: ON LINE OU PRESENCIAL | AJ1: PUBLICO ALVO | AK1: RELATORIO_CARGA HORÁRIA | AL1: CARGA HORARIA | AM1: ID | AN1: LINK AVA/ANDAMENTO DO CERTIFICADO | AO1: lista de presença | AP1: SEI DOS INSCRITOS | AQ1: STATUS | AR1: pronto para registro | AS1: DATA DA ULTIMA VERIFICAÇÃO | AT1: obs 2: | AU1: LIVRO DE REGISTRO | AV1: DATA DO ULTIMO REGISTRO | AW1: 2021 | AX1: 2022 | AY1: 1º trim/2023 | AZ1: 2º trim/2023 | BA1: 3º trim/2023 | BB1: 4º trim/2023 | BC1: 2023 | BD1: TOTAL CERTIFICADOS EMITIDOS/2024 | BE1: 1º trim/2024 | BF1: 2º trim/2024 | BG1: 3º trim/2024 | BH1: 4º trim/2024 | BI1: TOTAL CERTIFICADOS EMITIDOS/2025 | BJ1: 1º trim/2025 | BK1: 2º trim/2025 | BL1: 3º trim/2025 | BM1: 4º trim/2025
B2: 0 | E2: Escola Judicial do Paraná | Tribunal de Justiça do Paraná | AD2: Paraná | AM2: 1 | AQ2: Curso fechado
B3: 0 | E3: Mediação Judicial _ padrão | V3: MEDIAÇÃO | AM3: 2 | AQ3: Curso fechado
B4: 0 | E4: Instrutor EAD em mediação judicial | V4: MEDIAÇÃO | AM4: 4 | AQ4: Curso fechado
B5: 0 | E5: Mediação Judicial - turma 1 | V5: MEDIAÇÃO | Y5: turma 1 | AM5: 5 | AQ5: Curso fechado
B6: 0 | E6: Mediação Judicial - turma 2 | V6: MEDIAÇÃO | Y6: turma 2 | AM6: 6 | AQ6: Curso fechado
B7: 0 | E7: Mediação Judicial - turma 3 | V7: MEDIAÇÃO | Y7: turma 3 | AM7: 7 | AQ7: Curso fechado
B8: 0 | E8: Mediação Judicial - turma 4 | V8: MEDIAÇÃO | Y8: turma 4 | AM8: 8 | AQ8: Curso fechado
B9: 0 | E9: Mediação Judicial - turma 5 | V9: MEDIAÇÃO | Y9: turma 5 | AM9: 9 | AQ9: Curso fechado
B10: 0 | E10: Mediação Judicial - turma 6 | V10: MEDIAÇÃO | Y10: turma 6 | AM10: 10 | AQ10: Curso fechado
B11: 0 | E11: Mediação Judicial - teste | V11: MEDIAÇÃO | AM11: 11 | AQ11: Curso fechado
B12: 0 | E12: Mediação Judicial - Turma Recuperação | V12: MEDIAÇÃO | Y12: Turma Recuperação | AM12: 12 | AQ12: Curso fechado
B13: 0 | E13: Mediação Judicial_002/2014 | V13: MEDIAÇÃO | Y13: Judicial_002/2014 | AM13: 13 | AQ13: Curso fechado
B14: 0 | E14: Mediação Judicial 003/2014 | V14: MEDIAÇÃO | Y14: Judicial 003/2014 | AM14: 14 | AQ14: Curso fechado
B15: 0 | E15: Palestras Públicas | AM15: 15 | AQ15: Curso fechado
B16: 0 | E16: Instrutores em mediação e conciliação | V16: MEDIAÇÃO | AM16: 16 | AQ16: Curso fechado
B17: 0 | E17: Mediação para representantes de empresas | V17: MEDIAÇÃO | AM17: 17 | AQ17: Curso fechado
B18: 0 | E18: Relações Interpessoais e Administração de Conflitos | AM18: 18 | AQ18: Curso fechado
B19: 0 | E19: Mediação Judicial 004/2014 | V19: MEDIAÇÃO | Y19: Judicial 004/2014 | AM19: 21 | AQ19: Curso fechado
B20: 0 | E20: Mediação Judicial - presencial - Ponta Grossa | V20: MEDIAÇÃO | AD20: Ponta Grossa | AM20: 22 | AQ20: Curso fechado
B21: 0 | E21: Mediação Judicial 005/2014 | V21: MEDIAÇÃO | Y21: Judicial 005/2014 | AM21: 25 | AQ21: Curso fechado
B22: 0 | E22: Educação Ambiental e Sustentabilidade | AD22: Sustentabilidade | AM22: 26 | AQ22: Curso fechado
B23: 0 | E23: Desenvolvimento de Competências Gerenciais | AD23: Gerenciais | AM23: 30 | AQ23: Curso fechado
B24: 2015 | E24: Oficial de Justiça - 2015 | AE24: 2015 | AM24: 31 | AQ24: Curso fechado
B25: 0 | E25: Noções Básicas de Administração | AM25: 33 | AQ25: Curso fechado
B26: 0 | E26: Fundamentos de Ensino a Distância | AM26: 34 | AQ26: Curso fechado
B27: 0 | E27: Introdução à Capacitação Gerencial Turma I - Zona 21 a 57 | AM27: 35 | AQ27: Curso fechado
B28: 0 | E28: Atendimento ao público para CNJ | AM28: 36 | AQ28: Curso fechado
B29: 0 | E29: Atualização em Gramática da Língua Portuguesa turma teste | AM29: 37 | AQ29: Curso fechado
B30: 0 | E30: Introdução ao Orçamento Público | AM30: 38 | AQ30: Curso fechado
B31: 0 | E31: Noções Básicas de Administração | AM31: 39 | AQ31: Curso fechado
B32: 0 | E32: Tutoria no Ensino a Distância | AM32: 40 | AQ32: Curso fechado
B33: 0 | E33: Introdução à Lei de Responsabilidade Fiscal | AM33: 41 | AQ33: Curso fechado
B34: 0 | E34: Licitações e Contratos | AM34: 42 | AQ34: Curso fechado
B35: 0 | E35: Formação de Tutores para o curso Desenvolvimento de Competências Gerenciais | AM35: 43 | AQ35: Curso fechado
B36: 0 | E36: Administração Judiciária | AM36: 44 | AQ36: Curso fechado
B37: 0 | E37: Curso de Mediação Judicial | V37: MEDIAÇÃO | AM37: 51 | AQ37: Curso fechado
B38: 0 | E38: Curso de Mediação Judicial NUPEMEC/CNJ/2016 | V38: MEDIAÇÃO | AM38: 53 | AQ38: Curso fechado
B39: 0 | E39: Depoimento Especial e a Escuta de Crianças no Sistema de Justiça | V39: Depoimento Especial | AM39: 56 | AQ39: Curso fechado
B40: 2016 | D40: 0028066-55.2016.8.16.6000 | E40: Protesto das Custas Processuais | V40: - | AM40: 57 | AQ40: Curso fechado
B41: 2016 | D41: 0028066-55.2016.8.16.6000 | E41: Protesto das Custas Processuais | V41: - | AM41: 59 | AQ41: Curso fechado
B42: 2017 | E42: Curso Práticas de Restaurativas - Curitiba - março de 2017 | V42: JUSTIÇA RESTAURATIVA | AD42: curitibA | AE42: 2017 | AF42: março de 2017 | AM42: 60 | AQ42: Curso fechado
B43: 0 | E43: Depoimento Especial | V43: Depoimento Especial | AM43: 62 | AQ43: Curso fechado
B44: 0 | E44: Processo Judicial Eletrônico - Advogado | AM44: 64 | AQ44: Curso fechado
B45: 2017 | E45: Curso Práticas Restaurativas - Curitiba - abril de 2017 | V45: JUSTIÇA RESTAURATIVA | AD45: CURITIBA | AE45: 2017 | AF45: abril de 2017 | AM45: 65 | AQ45: Curso fechado
B46: 0 | E46: Depoimento Especial | V46: Depoimento Especial | AM46: 66 | AQ46: Curso fechado
B47: 0 | E47: Processo Judicial Eletrônico -Teste | AM47: 67 | AQ47: Curso fechado
B48: 2017 | E48: CURSO DE FORMAÇÃO BÁSICA PARA TERCEIROS FACILITADORES 0001/2017 | V48: JUSTIÇA RESTAURATIVA | Y48: 0001/2017 | AD48: FACILITADORES 0001/2017 | AE48: 2017 | AM48: 68 | AQ48: Curso fechado
B49: 2017 | E49: Curso Justiça Restaurativa CTBA - junho 2017 | V49: JUSTIÇA RESTAURATIVA | AD49: curitiba | AE49: 2017 | AF49: junho | AM49: 69 | AQ49: Curso fechado
B50: 2017 | E50: Curso Justiça Restaurativa MGA - junho 2017 | V50: JUSTIÇA RESTAURATIVA | AD50: MARINGÁ | AE50: 2017 | AF50: junho | AM50: 70 | AQ50: Curso fechado
B51: 0 | E51: Módulo prático do Curso de Terceiro Facilitador (Mediação e Conciliação) | V51: JUSTIÇA RESTAURATIVA | AM51: 71 | AQ51: Curso fechado
B52: 0 | D52: 0110889-86.2016.8.16.6000 | E52: Sensibilização em Gestão Socioambiental | V52: - | AM52: 72 | AQ52: Curso fechado
B53: 0 | E53: Módulo prático do curso de Terceiro Facilitador (Mediação e Conciliação) - Módulo prático (Estágio Supervisionado) 001/2017 | V53: JUSTIÇA RESTAURATIVA | Y53: 001/2017 | AM53: 73 | AQ53: Curso fechado
B54: 0 | E54: Terceiro Facilitador (mediação e conciliação judicial) | AM54: 74 | AQ54: Curso fechado
B55: 0 | E55: 1A/16MC - CURITIBA | V55: MEDIAÇÃO | Y55: 1A/16MC - CURITIBA | AD55: CURITIBA | AM55: 75 | AQ55: Curso fechado
B56: 2017 | E56: Curso Justiça Restaurativa CTBA - agosto 2017 | V56: JUSTIÇA RESTAURATIVA | AD56: CURITIBA | AE56: 2017 | AF56: agosto | AM56: 76 | AQ56: Curso fechado
B57: 0 | E57: 2A/17CM - CURITIBA | V57: MEDIAÇÃO | Y57: 2A/17CM - CURITIBA | AD57: CURITIBA | AM57: 77 | AQ57: Curso fechado
B58: 0 | D58: 0072948-34.2018.8.16.6000 | E58: Formação de Brigadista - Fórum Cível I | V58: - | AM58: 78 | AQ58: Curso fechado
B59: 2017 | E59: Curso Justiça Restaurativa - LON - Agosto 2017 | V59: JUSTIÇA RESTAURATIVA | AD59: Londrina | AE59: 2017 | AF59: 42948 | AM59: 80 | AQ59: Curso fechado
B60: 0 | E60: 2B/17CM - CURITIBA | V60: MEDIAÇÃO | Y60: 2B/17CM - CURITIBA | AD60: CURITIBA | AM60: 81 | AQ60: Curso fechado
B61: 0 | E61: 2C/17CM - CURITIBA | V61: MEDIAÇÃO | Y61: 2C/17CM - CURITIBA | AD61: CURITIBA | AM61: 82 | AQ61: Curso fechado
B62: 2017 | E62: Curso Justiça Restaurativa - Campo Mourão - 12 a 15 SET de 2017 | V62: JUSTIÇA RESTAURATIVA | AD62: CAMPO MOURÃO | AE62: 2017 | AF62: 12 a 15 SET de 2017 | AM62: 84 | AQ62: Curso fechado
B63: 2017 | E63: CURSO DE INSTRUTORES EM JUSTIÇA RESTAURATIVA 28 e 29 SET de 2017 | V63: JUSTIÇA RESTAURATIVA | AE63: 2017 | AF63: 42996 | AG63: 43007 | AM63: 85 | AQ63: Curso fechado
B64: 0 | E64: 3A/17CM - CURITIBA | V64: MEDIAÇÃO | Y64: 3A/17CM - CURITIBA | AD64: CURITIBA | AM64: 86 | AQ64: Curso fechado
B65: 0 | E65: 3B/17CM - CURITIBA | V65: MEDIAÇÃO | Y65: 3B/17CM - CURITIBA | AD65: CURITIBA | AM65: 87 | AQ65: Curso fechado
B66: 0 | E66: 3C/17CM - CURITIBA | V66: MEDIAÇÃO | Y66: 3C/17CM - CURITIBA | AD66: CURITIBA | AM66: 88 | AQ66: Curso fechado
B67: 0 | E67: 4A/17CM | V67: MEDIAÇÃO | Y67: 4A/17CM | AD67: CM | AM67: 89 | AQ67: Curso fechado
B68: 0 | E68: Panorama Jurídico 27/08 a 01/09/2017 | AG68: a 01/09/2017 | AM68: 90 | AQ68: Curso fechado
B69: 0 | E69: 4B/17CM | V69: MEDIAÇÃO | Y69: 4B/17CM | AD69: CM | AM69: 91 | AQ69: Curso fechado
B70: 0 | E70: 4C/17CM | V70: MEDIAÇÃO | Y70: 4C/17CM | AD70: CM | AM70: 92 | AQ70: Curso fechado
B71: 0 | E71: 4D/17CM | V71: MEDIAÇÃO | Y71: 4D/17CM | AD71: CM | AM71: 93 | AQ71: Curso fechado
B72: 0 | E72: 5A/17CM - PONTA GROSSA | V72: MEDIAÇÃO | Y72: 5A/17CM - PONTA GROSSA | AD72: PONTA GROSSA | AM72: 94 | AQ72: Curso fechado
B73: 0 | E73: 6A/17CM - CURITIBA | V73: MEDIAÇÃO | Y73: 6A/17CM - CURITIBA | AD73: CURITIBA | AM73: 95 | AQ73: Curso fechado
B74: 0 | E74: 6B/17CM - CURITIBA | V74: MEDIAÇÃO | Y74: 6B/17CM - CURITIBA | AD74: CURITIBA | AM74: 96 | AQ74: Curso fechado
B75: 0 | E75: 6C/17CM - CURITIBA | V75: MEDIAÇÃO | Y75: 6C/17CM - CURITIBA | AD75: CURITIBA | AM75: 97 | AQ75: Curso fechado
B76: 2017 | E76: Curso Justiça Restaurativa PG - 02 a 05 OUT de 2017 | V76: JUSTIÇA RESTAURATIVA | AD76: PONTA GROSSA | AE76: 2017 | AF76: 02 a 05 OUT de 2017 | AM76: 98 | AQ76: Curso fechado
B77: 0 | E77: 7A/17CM - CURITIBA | V77: MEDIAÇÃO | Y77: 7A/17CM - CURITIBA | AD77: CURITIBA | AM77: 99 | AQ77: Curso fechado
B78: 0 | E78: 7B/17CM - CURITIBA | V78: MEDIAÇÃO | Y78: 7B/17CM - CURITIBA | AD78: CURITIBA | AM78: 100 | AQ78: Curso fechado
B79: 0 | E79: 7C/17CM - CURITIBA | V79: MEDIAÇÃO | Y79: 7C/17CM - CURITIBA | AD79: CURITIBA | AM79: 101 | AQ79: Curso fechado
B80: 0 | E80: 8A/17CM - CURITIBA | V80: MEDIAÇÃO | Y80: 8A/17CM - CURITIBA | AD80: CURITIBA | AM80: 102 | AQ80: Curso fechado
B81: 0 | E81: 8B/17CM - CURITIBA | V81: MEDIAÇÃO | Y81: 8B/17CM - CURITIBA | AD81: CURITIBA | AM81: 103 | AQ81: Curso fechado
B82: 0 | E82: 11A/17CM - PONTA GROSSA | V82: MEDIAÇÃO | Y82: 11A/17CM - PONTA GROSSA | AD82: PONTA GROSSA | AM82: 104 | AQ82: Curso fechado
B83: 0 | E83: 9A/17CM - COLORADO | V83: MEDIAÇÃO | Y83: 9A/17CM - COLORADO | AD83: COLORADO | AM83: 105 | AQ83: Curso fechado
B84: 0 | E84: 9B/17CM - COLORADO | V84: MEDIAÇÃO | Y84: 9B/17CM - COLORADO | AD84: COLORADO | AM84: 106 | AQ84: Curso fechado
B85: 0 | E85: 12A/17CM - CIANORTE | V85: MEDIAÇÃO | Y85: 12A/17CM - CIANORTE | AD85: CIANORTE | AM85: 107 | AQ85: Curso fechado
B86: 0 | E86: 12B/17CM - CIANORTE | V86: MEDIAÇÃO | Y86: 12B/17CM - CIANORTE | AD86: CIANORTE | AM86: 108 | AQ86: Curso fechado
B87: 0 | E87: 14A/17CM - CURITIBA | V87: MEDIAÇÃO | Y87: 14A/17CM - CURITIBA | AD87: CURITIBA | AM87: 109 | AQ87: Curso fechado
B88: 0 | E88: 13A/17CM - CURITIBA | V88: MEDIAÇÃO | Y88: 13A/17CM - CURITIBA | AD88: CURITIBA | AM88: 110 | AQ88: Curso fechado
... B90: 0 | E90: 10B/17CM - CURITIBA | V90: MEDIAÇÃO | Y90: 10B/17CM - CURITIBA | AD90: CURITIBA | AM90: 112 | AQ90: Curso fechado
B91: 2017 | E91: Curso Justiça Restaurativa - Londrina 24 a 27 Out de 2017 | V91: JUSTIÇA RESTAURATIVA | AD91: Londrina | AE91: 2017 | AF91: 24 a 27 Out de 2017 | AM91: 113 | AQ91: Curso fechado
B92: 2017 | E92: Curso Justiça Restaurativa - DEASE Toledo - 26 a 27 de Out de 2017 | V92: JUSTIÇA RESTAURATIVA | AD92: TOLEDO | AE92: 2017 | AF92: 26 a 27 de Out de 2017 | AM92: 114 | AQ92: Curso fechado
B93: 2017 | E93: Curso Justiça Restaurativa - DEASE Londrina - 31 de Out e 01 de Nov de 2017 | V93: JUSTIÇA RESTAURATIVA | AD93: Londrina | AE93: 2017 | AF93: 31 de Out e 01 de Nov de 2017 | AM93: 115 | AQ93: Curso fechado
B94: 2017 | E94: Curso Justiça Restaurativa - DEASE Curitiba - 16 e 17 Nov de 2017 | V94: JUSTIÇA RESTAURATIVA | AD94: Curitiba | AE94: 2017 | AF94: 16 e 17 Nov de 2017 | AM94: 116 | AQ94: Curso fechado
B95: 2017 | E95: 16A/17CM - CURITIBA | V95: MEDIAÇÃO | Y95: 16A/17CM - CURITIBA | AD95: CURITIBA | AM95: 117 | AQ95: Curso fechado
B96: 2017 | E96: 16B/17CM - CURITIBA | V96: MEDIAÇÃO | Y96: 16B/17CM - CURITIBA | AD96: CURITIBA | AM96: 118 | AQ96: Curso fechado
B97: 2017 | E97: 17A/17CM - CURITIBA | V97: MEDIAÇÃO | Y97: 17A/17CM - CURITIBA | AD97: CURITIBA | AM97: 119 | AQ97: Curso fechado
B98: 2017 | E98: 17B/17CM - CURITIBA | V98: MEDIAÇÃO | Y98: 17B/17CM - CURITIBA | AD98: CURITIBA | AM98: 120 | AQ98: Curso fechado
B99: 2017 | E99: 15A/17CM - CURITIBA | V99: MEDIAÇÃO | Y99: 15A/17CM - CURITIBA | AD99: CURITIBA | AM99: 121 | AQ99: Curso fechado
B100: 2017 | E100: 15B/17CM - CURITIBA | V100: MEDIAÇÃO | Y100: 15B/17CM - CURITIBA | AD100: CURITIBA | AM100: 122 | AQ100: Curso fechado
B101: 2017 | E101: 15C/17CM - CURITIBA | V101: MEDIAÇÃO | Y101: 15C/17CM - CURITIBA | AD101: CURITIBA | AM101: 123 | AQ101: Curso fechado
...

Sheet controle de cursos
A1: CNJ - Capacitação em Direitos Humanos, Gênero, Raça e Etnia; e em Depoimento Especial" - 0148945-13.2024.8.16.6000 | B1: Prêmio CNJ de Qualidade - 2025 - Justiça Restaurativa - 0148919-15.2024.8.16.6000 | C1: Prêmio CNJ de Qualidade - 2025 - Capacitação de Facilitadores 0148959-94.2024.8.16.6000 | D1: Prêmio CNJ de Qualidade - 2025 - Acessibilidade e Inclusão - 0148938-21.2024.8.16.6000 | E1: Prêmio CNJ de Qualidade - 2025 Política de Prevenção e Enfrentamento do Assédio Moral, do Assédio Sexual e da Discriminação.0148908-83.2024.8.16.6000 | F1: sustentabilidade https://portal.tjpr.jus.br/portletforms/frm.do?idFormulario=7430 | G1: Coluna2 | H1: ANO DO CURSO2 | I1: SEI | J1: NOME DO Curso | K1: CATEGORIA DO Curso=modalidade | L1: RESPONSÁVEL PELA CERTIFICAÇÃO | M1: INSTITUIÇÃO DE ENSINO | N1: EMPRESA CONTRATADA | O1: CNPJ | P1: SEI DOC INSTRUTORES | Q1: Intrutor (andamento do SEI) | R1: TERMO DE USO DE IMAGEM | S1: ATESTO | T1: PRE ANOTAÇÃO ATESTO | U1: DESPESAS | V1: VALOR DAS DESPESAS | W1: PRODUÇÃO/UNIDADE SOLICITANTE | X1: Eixo de Capacitação - Itinerários Formativos | Y1: PAE | Z1: INDICADORES | AA1: PORTARIA ENFAM | AB1: Tipo de evento | AC1: TURMA | AD1: nº de vagas | AE1: INTÉRPRETES DE LIBRAS | AF1: MODALIDADE | AG1: PLANO DE CURSO/SEI | AH1: LOCAL | AI1: ANO DO CURSO22 | AJ1: DATA INÍCIO | AK1: DATA TERMINO | AL1: DECLARAÇÃO/ CERTIFICADO/ SEM CERTIFICAÇÃO | AM1: ON LINE OU PRESENCIAL | AN1: PUBLICO ALVO | AO1: RELATORIO_CARGA HORÁRIA | AP1: CARGA HORARIA | AQ1: ID | AR1: LINK AVA/ANDAMENTO DO CERTIFICADO | AS1: lista de presença | AT1: SEI DOS INSCRITOS | AU1: STATUS | AV1: pronto para registro | AW1: DATA DA ULTIMA VERIFICAÇÃO | AX1: obs 2: | AY1: REG DE INSTRUTORES | AZ1: REGISTRO DE INSTRUTORES NO SEI | BA1: LIVRO DE REGISTRO | BB1: REGISTRO NO SEI | BC1: DATA DO ULTIMO REGISTRO | BD1: REGISTRO NO SEI/2021 | BE1: TOTAL CERTIFICADOS EMITIDOS/2021 | BF1: REGISTRO NO SEI/20222 | BG1: TOTAL CERTIFICADOS EMITIDOS/2022 | BH1: REGISTRO NO SEI/2023 | BI1: TOTAL CERTIFICADOS EMITIDOS/2023 | BJ1: 1º trim/2023 | BK1: 2º trim/2023 | BL1: 3º trim/2023 | BM1: 4º trim/2023 | BN1: REGISTRO NO SEI/2024 | BO1: TOTAL CERTIFICADOS EMITIDOS/2024 | BP1: 1º trim/2024 | BQ1: 2º trim/2024 | BR1: 3º trim/2024 | BS1: 4º trim/2024 | BT1: REGISTRO NO SEI/2025 | BU1: TOTAL CERTIFICADOS EMITIDOS/2025 | BV1: 1º trim/2025 | BW1: 2º trim/2025 | BX1: 3º trim/2025 | BY1: 4º trim/2025
H2: 2021 | I2: 0051257-56.2021.8.16.6000 | J2: 1ª Oficina de Ideação da Magistratura Paranaense | VALORIZAÇÃO Valorização - Jornada de Valorização da Magistratura Paranaense | AB2: Oficina | AI2: 2021 | AJ2: 44355 | AK2: 44388 | AL2: Certificado | AN2: MAGISTRATURA | AQ2: 675 | AR2: https://ead.tjpr.jus.br/course/view.php?id=675 | AU2: Curso fechado | AX2: registrado_65 pessoas_sem informar o sei
H3: 2022 | I3: 0060212-42.2022.8.16.6000 | J3: Curso de Justiça Restaurativa: Formação Prática I - Processos Circulares não Conflitivos | W3: NUPEMEC | Z3: JUSTIÇA RESTAURATIVA | AB3: Curso | AC3: 1 Ed | AD3: 20 | AI3: 2022 | AJ3: 44714 | AK3: 44742 | AQ3: 702 | AR3: https://ead.tjpr.jus.br/course/view.php?id=702 | AU3: Curso fechado | BC3: 44791 | BG3: 2022 | BI3: #VALUE!
B4: sim | H4: 2022 | I4: 0060247-02.2022.8.16.6000 | J4: Curso Formação Prática I em Justiça Restaurativa - JR - 2022 - 2ª Edição - Turma 2 | W4: NUPEMEC | Z4: JUSTIÇA RESTAURATIVA | AB4: Curso | AC4: 2 ed | AD4: 20 | AI4: 2022 | AJ4: 44718 | AK4: 44748 | AQ4: 736 | AR4: https://ead.tjpr.jus.br/course/view.php?id=736 | AU4: Curso fechado | BG4: 2022 | BI4: #VALUE!
B5: sim | H5: 2022 | I5: 0060391-73.2022.8.16.6000 | J5: Curso Formação Prática I em Justiça Restaurativa - JR - 2022 - 4ª Edição - Turma 4 - Ponta Grossa - 2022 | W5: NUPEMEC | Z5: JUSTIÇA RESTAURATIVA | AB5: Curso | AC5: 4 ED | AI5: 2022 | AJ5: 44730 | AK5: 44750 | AQ5: 755 | AR5: https://ead.tjpr.jus.br/course/view.php?id=755 | AU5: Curso fechado | BG5: 2022 | BI5: #VALUE!
B6: sim | H6: 2022 | I6: 0060331-03.2022.8.16.6000 | J6: Curso Formação Prática I em Justiça Restaurativa - JR - 2022 - 3ª Edição - Turma 3 | W6: NUPEMEC | Z6: JUSTIÇA RESTAURATIVA | AB6: Curso | AC6: 3 ED | AD6: 20 | AI6: 2022 | AJ6: 44733 | AK6: 44757 | AQ6: 738 | AR6: https://ead.tjpr.jus.br/course/view.php?id=738 | AU6: Curso fechado | BG6: 2022 | BI6: #VALUE!
H7: 2022 | I7: 0072539-19.2022.8.16.6000 | J7: III Semana de Integração e Aperfeiçoamento | AG7: Projeto Semana de Integração e Aperfeiçoamento – Jul./2022 (7784471) | AI7: 2022 | AJ7: 44743 | AK7: 44750 | AR7: https://ead.tjpr.jus.br/course/view.php?id=1033 | AU7: Curso fechado | AX7: autorizada a emissáo do certificado | BC7: 45600 | BQ7: 29
B8: sim | H8: 2022 | I8: 0060474-89.2022.8.16.6000 | J8: Curso Formação Prática I em Justiça Restaurativa - JR - 2022 - 5ª Edição - Turma 5 - presencial Toledo | W8: NUPEMEC | Z8: JUSTIÇA RESTAURATIVA | AB8: Curso | AC8: 5 ED | AI8: 2022 | AJ8: 44768 | AK8: 44771 | AQ8: 756 | AR8: https://ead.tjpr.jus.br/course/view.php?id=756 | AU8: Curso fechado | BG8: ? | BI8: #VALUE!
B9: sim | H9: 2022 | I9: 0130331-28.2022.8.16.6000 | J9: Curso de Justiça Restaurativa: Formação Prática I - Processos Circulares não Conflitivos - 6ª Edição | W9: NUPEMEC | Z9: JUSTIÇA RESTAURATIVA | AB9: Curso | AI9: 2022 | AJ9: 44866 | AK9: 44910 | AQ9: 796 | AR9: https://ead.tjpr.jus.br/course/view.php?id=796 | AU9: curso fechado | BC9: 44959 | BI9: #VALUE! | BJ9: 17 | BO9: 17
B10: sim | H10: 2022 | I10: 0130369-40.2022.8.16.6000 | J10: Curso de Justiça Restaurativa - Formação Prática I - 7ª Edição | W10: NUPEMEC | Z10: JUSTIÇA RESTAURATIVA | AB10: Curso | AI10: 2022 | AJ10: 44868 | AK10: 44896 | AQ10: 797 | AR10: https://ead.tjpr.jus.br/course/view.php?id=797 | AU10: Curso fechado | BC10: 44959 | BI10: #VALUE! | BJ10: 16 | BO10: 16
B11: sim | H11: 2023 | I11: 0130372-92.2022.8.16.6000. | J11: 8a Edição do Curso de Justiça Restaurativa - Formação Prática I (Círculos não conflitivos) | L11: EJUD | W11: NUPEMEC | Z11: JUSTIÇA RESTAURATIVA | AB11: Curso | AI11: 2023 | AJ11: 45005 | AK11: 45028 | AQ11: 798 | AR11: https://ead.tjpr.jus.br/course/view.php?id=798 | AU11: Curso fechado | AY11: sim em 2024 | BA11: 1 - LISTA GERAL_2020 A ... | BC11: 45049 | BI11: #VALUE! | BJ11: 19 | BO11: 19
H12: 2023 | I12: 0049503-11.2023.8.16.6000 | J12: CURSO OFICIAL DE FORMAÇÃO INICIAL PARA JUIZ SUBSTITUTO | L12: EJUD | W12: EJUD | AA12: 088/2022 | AB12: curso | AD12: 20 | AH12: Curitiba | AI12: 2023 | AJ12: 45048 | AK12: 45134 | AL12: Certificado | AM12: presencial | AN12: MAGISTRATURA | AO12: 20 | AP12: 480 h | AQ12: 843 | AR12: https://ead.tjpr.jus.br/course/view.php?id=843 | AU12: Curso fechado | AX12: registrado alguns instrutores - certificado 2023 | AY12: 470-548/2023 | BA12: 1 - LISTA GERAL_2020 A ... | BC12: 45174 | BI12: #VALUE! | BL12: 15
H13: 2023 | I13: 0058337-03.2023.8.16.6000 | J13: CURSOS DE FORMAÇÃO DE CONCILIADORES E MEDIADORES JUDICIAL | Z13: MEDIAÇÃO | AH13: Maringá | AI13: 2023 | AJ13: 45062 | AK13: 45083 | AL13: Declaração | AM13: presencial | AP13: 40 h | AU13: curso fechado | BC13: 45672 | BO13: 11
E14: sim | H14: 2023 | I14: 0050268-79.2023.8.16.6000 | J14: Entre o ideal e o Possível: a importância da rede na aplicação das medidas de proteção (dia 24/05/2023 | Q14: 9035156 | X14: Formação Inicial e Continuada | AA14: não | AB14: Palestra | AH14: Paraná | AI14: 2023 | AJ14: 45070 | AK14: 45070 | AL14: Certificado | AM14: webconferência | AO14: 0.33333333 | AP14: 8 h | AQ14: 860 | AR14: https://ead.tjpr.jus.br/course/view.php?id=860 | AU14: Curso fechado | BA14: 1 - LISTA GERAL_2020 A ... | BC14: 45146 | BI14: #VALUE! | BK14: 82
E15: sim | H15: 2023 | I15: 0050268-79.2023.8.16.6000 | J15: Entre o ideal e o Possível: a importância da rede na aplicação das medidas de proteção (dia 25/05/2023 | Q15: 9035156 | X15: Formação Inicial e Continuada | AA15: não | AB15: Palestra | AH15: Paraná | AI15: 2023 | AJ15: 45071 | AK15: 45071 | AL15: Certificado | AM15: webconferência | AO15: 0.20833333 | AP15: 5 h | AQ15: 860 | AR15: https://ead.tjpr.jus.br/course/view.php?id=860 | AU15: Curso fechado | BA15: 1 - LISTA GERAL_2020 A ... | BC15: 45146 | BI15: #VALUE! | BK15: 83
F16: sim | H16: 2023 | I16: 0070561-70.2023.8.16.6000 | J16: 5º Ciclo de Treinamento e Reciclagem | L16: EJUD | Q16: 9137444 | W16: DGP-Departamento de Gestão de Precatórios | X16: Formação Inicial e Continuada | AA16: não | AD16: 70 | AH16: Curitiba | AI16: 2023 | AJ16: 45075 | AK16: 45091 | AM16: presencial | AN16: servidores(as) e estagiários(as) | AO16: 0.33333333 | AP16: 8 h | AQ16: 857 | AR16: https://ead.tjpr.jus.br/course/view.php?id=857 | AU16: Curso fechado | AY16: 419-426 | BA16: 1 - LISTA GERAL_2020 A ... | BC16: 45146 | BI16: #VALUE! | BL16: 60
E17: sim | H17: 2023 | I17: 0052563-89.2023.8.16.6000 | J17: II Fórum Paranaense de Violência Doméstica e Familiar contra a Mulher (FOVID/PR) | Q17: 9018411 | W17: CEVID | AA17: não | AB17: Fórum | AD17: 280 | AH17: Paraná | AI17: 2023 | AJ17: 45077 | AK17: 45079 | AL17: Certificado | AM17: webconferência | AO17: 0.95833333 | AP17: 23 h | AQ17: 858 | AR17: https://ead.tjpr.jus.br/course/view.php?id=858 | AU17: Curso fechado | AX17: 15/08 - ag. lista de presença no ava - 20/09juntada da lista de presença | AY17: 459-469 | BA17: 1 - LISTA GERAL_2020 A ... | BC17: 45404 | BI17: #VALUE! | BK17: 400 | BP17: 3
H18: 2023 | I18: 0054248-34.2023.8.16.6000 | J18: Instruções BNMP | Q18: 9094414 | W18: CGJ | Z18: Gestão | AB18: Curso | AH18: Paraná | AI18: 2023 | AJ18: 45082 | AK18: 45082 | AL18: certificado | AM18: transmissão ao vivo | AN18: magistrados(as) e servidores(as) da esfera criminal do TJPR | AO18: 0.16666667 | AP18: 4 h | AQ18: 863 | AR18: https://ead.tjpr.jus.br/course/view.php?id=863 | AU18: Curso fechado | AY18: 417-418 | BA18: 1 - LISTA GERAL_2020 A ... | BC18: 45146 | BI18: #VALUE! | BL18: 758
A19: sim | H19: 2023 | I19: 0049473-73.2023.8.16.6000 | J19: Seminário Internacional de Saúde Mental: Possibilidades para a efetivação da Política Antimanicomial na interface com o Poder Judiciário | Q19: espalhado | W19: CNJ | AA19: não | AB19: Seminário | AD19: 400 | AH19: Curitiba | AI19: 2023 | AJ19: 45092 | AK19: 45093 | AL19: Certificado | AM19: presencial com transmissão ao vivo | AO19: 0.70833333 | AP19: 17 h | AQ19: 862 | AR19: https://ead.tjpr.jus.br/course/view.php?id=862 | AU19: Curso fechado | AY19: 430-444/803-814/2024 | BA19: 1 - LISTA GERAL_2020 A ... | BC19: 45153 | BI19: #VALUE! | BK19: 586
H20: 2023 | I20: 0062706-40.2023.8.16.6000 | J20: Curso de Aperfeiçoamento para Magistrados e Magistradas – Medidas Protetivas de Urgência no Âmbito da Lei 11340/2006. Fundamentos, questões controvertidas e efetividade | Q20: 9086742 | AA20: 126/2023 | AB20: Curso | AD20: 80 | AI20: 2023 | AJ20: 45092 | AK20: 45131 | AL20: certificado | AM20: transmissão ao vivo | AN20: MAGISTRATURA | AO20: 0.83333333 | AP20: 20 h | AQ20: 859 | AR20: https://ead.tjpr.jus.br/course/view.php?id=859 | AU20: Curso fechado | AY20: 448-452 | BA20: 1 - LISTA GERAL_2020 A ... | BC20: 45155 | BI20: #VALUE! | BL20: 68
F21: sim | H21: 2023 | I21: 0070644-86.2023.8.16.6000 | J21: curso “Sustentabilidade Ambiental e Populações Tradicionais: direito ao Meio Ambiente Ecologicamente Equilibrado” | L21: EJUD | Q21: José Ricardo Alvarez Vianna | W21: EJUD | AA21: 039/2023 | AB21: curso | AD21: 40 | AH21: Paraná | AI21: 2023 | AJ21: 45099 | AK21: 45131 | AL21: Certificado | AM21: EAD | AN21: MAGISTRATURA | AO21: 1.25 | AP21: 30 h | AQ21: 846 | AR21: https://ead.tjpr.jus.br/course/view.php?id=846 | AU21: Curso fechado | AY21: 470 | BA21: 1 - LISTA GERAL_2020 A ... | BC21: 45160 | BI21: #VALUE! | BL21: 20
A22: sim | E22: sim | H22: 2023 | I22: 0078947-89.2023.8.16.6000 | J22: O Protocolo para Julgamento com a Perspectiva de Gênero - Edição 2024 | Z22: MAGISTRADO | AG22: Plano de curso (9174100) | AI22: 2023 | AJ22: 45101 | AK22: 45131 | AN22: MAGISTRADO | AQ22: 999 | AU22: Curso fechado | BC22: 45520 | BQ22: 33
A23: sim | E23: sim | H23: 2023 | I23: 0078947-89.2023.8.16.6000 | J23: Protocolo para julgamento com perspectiva de gênero - 3ed | L23: EJUD | Q23: 9176202 | AA23: 157/2022 | AB23: Curso | AD23: 40 | AI23: 2023 | AJ23: 45101 | AK23: 45131 | AL23: Certificado | AM23: transmissão ao vivo | AN23: MAGISTRATURA | AO23: 1.0833333 | AP23: 26 h | AQ23: 861 | AR23: https://ead.tjpr.jus.br/course/view.php?id=861 | AU23: Curso fechado | AY23: 445/446 | BA23: 1 - LISTA GERAL_2020 A ... | BC23: 45154 | BI23: #VALUE! | BL23: 33
H24: 2023 | I24: 0078648-15.2023.8.16.6000 | J24: Cooperação Judiciária e o CPC/15: Perspectivas e Desafios | L24: EJUD | Q24: 9309073 | W24: Núcleo de Cooperação Judiciária | X24: Formação Inicial e Continuada | AA24: não | AB24: Live | AH24: Paraná | AI24: 2023 | AJ24: 45132 | AK24: 45132 | AM24: transmissão ao vivo | AN24: MAGISTRATURA | AO24: 0.083333333 | AP24: 2 h | AQ24: 874 | AR24: https://ead.tjpr.jus.br/course/view.php?id=874 | AU24: Curso fechado | AY24: 427-429 | BA24: 1 - LISTA GERAL_2020 A ... | BC24: 45146 | BI24: #VALUE! | BL24: 128
H25: 2023 | I25: 0059165-67.2021.8.16.6000 | J25: Adequação da numeração única dos Recursos no Projudi | W25: DPLAN-DE - Divisão de Estatística do Departamento de Planejamento | AA25: não | AB25: live | AI25: 2023 | AJ25: 45135 | AK25: 45135 | AL25: Certificado | AM25: transmissão ao vivo | AN25: Livre | AO25: 0.055555556 | AP25: 1h 20min | AQ25: 875 | AR25: https://ead.tjpr.jus.br/course/view.php?id=875 | AU25: Curso fechado | AY25: 453-458 | BA25: 1 - LISTA GERAL_2020 A ... | BC25: 45160 | BI25: #VALUE! | BL25: 104
E26: sim | H26: 2023 | I26: 0013489-28.2023.8.16.6000 | J26: Curso de violência doméstica e familiar contra a mulher para Magistrados(as) | Q26: 9556723 | Z26: violencia domestica | AA26: 074/2023 | AB26: Curso | AD26: 80 | AH26: Paraná | AI26: 2023 | AJ26: 45141 | AK26: 45180 | AL26: Certificado | AM26: EAD | AN26: MAGISTRATURA | AO26: 1.6666667 | AP26: 40 h | AQ26: 869 | AR26: https://ead.tjpr.jus.br/course/view.php?id=869 | AU26: Curso fechado | AX26: 18/10- forcei a certificação | AY26: 599-602/2023 | BA26: 1 - LISTA GERAL_2020 A ... | BC26: 45217 | BI26: #VALUE! | BL26: 48
H27: 2023 | I27: 0058310-20.2023.8.16.6000 | J27: Programa de Consultoria sobre o Sistema de Controle Interno do Poder Judiciário | W27: DAUDI-D - Diretoria do Departamento de Auditoria Interna | AB27: Curso | AI27: 2023 | AJ27: 45141 | AK27: 45147 | AL27: Certificado | AM27: presencial | AO27: 0.125 | AP27: 3 h | AQ27: 876 | AR27: https://ead.tjpr.jus.br/course/view.php?id=876 | AU27: Curso fechado | AX27: 26/09 - forcei a expedição dos certificados | AY27: 588-590/2023 | BA27: 1 - LISTA GERAL_2020 A ... | BC27: 45195 | BI27: #VALUE! | BL27: 128
B28: sim | H28: 2023 | I28: 0079751-57.2023.8.16.6000 | J28: Curso Formação de Formadores - Desenvolvimento Docente N1M1 | L28: EJUD | Q28: 9180806 | AA28: 302/2021 | AB28: curso | AC28: 2 ED | AD28: 40 | AH28: Paraná | AI28: 2023 | AJ28: 45141 | AK28: 45166 | AL28: Certificado | AM28: EAD | AN28: MAGISTRATURA | AO28: 1.0833333 | AP28: 26h | AQ28: 865 | AR28: https://ead.tjpr.jus.br/course/view.php?id=865 | AU28: Curso fechado | AY28: 576 -580/2023_expedido em 16/02/2024 | BA28: 1 - LISTA GERAL_2020 A ... | BC28: 45181 | BI28: #VALUE! | BL28: 37
H29: 2023 | I29: 0073414-52.2023.8.16.6000 | J29: Curso de Justiça Restaurativa: Formação Prática I - Processos Circulares não Conflitivos 9ª Edição | L29: EJUD | AD29: 20 | AH29: Paraná | AI29: 2023 | AJ29: 45145 | AK29: 45168 | AL29: Declaração | AM29: webconferência | AO29: 1.6666667 | AP29: 40 h | AQ29: 872 | AR29: https://ead.tjpr.jus.br/course/view.php?id=872 | AU29: Curso fechado | AX29: 25/09 - declaração no ava | AY29: 591-592/2023 | BA29: 1 - LISTA GERAL_2020 A ... | BC29: 45195 | BI29: #VALUE! | BL29: 20 | BO29: 20
H30: 2023 | I30: 0098485-56.2023.8.16.6000 | J30: V Semana de Integração e Aperfeiçoamento | L30: EJUD | W30: Unidade Especial de Atuação no Primeiro Grau de Jurisdição (UEA) | AH30: Paraná | AI30: 2023 | AJ30: 45145 | AK30: 45149 | AM30: webconferência | AN30: Servidores e estagiários da UEA | AO30: 0.45833333 | AP30: 11 h | AQ30: 877 | AR30: https://ead.tjpr.jus.br/course/view.php?id=877 | AU30: Curso fechado | BA30: 1 - LISTA GERAL_2020 A ... | BC30: 45168 | BI30: #VALUE! | BL30: 25
H31: 2023 | I31: 0099050-20.2023.8.16.6000 | J31: Nova Lei de Licitações com ênfase na prática do sistema COMPRAS.GOV | L31: EJUD | W31: DP-DL - Divisão de Licitações do Departamento do Patrimônio | AB31: CURSO | AC31: 1 | AD31: 40 | AF31: IN COMPANY | AI31: 2023 | AJ31: 45145 | AK31: 45148 | AL31: CERTIFICADO | AN31: Compradores, Pregoeiros e membros de Equipes de Apoio, assessores jurídicos, agentes de controle interno, além de servidores e profissionais atuantes no cenário das compras públicas em geral | AO31: 0.66666667 | AP31: 16 h | AU31: Curso fechado | BA31: IN COMPANY | BC31: 45166 | BI31: #VALUE! | BL31: 41
B32: sim | H32: 2023 | I32: 0078697-56.2023.8.16.6000 | J32: 10ª Edição do Curso Formação Prática I em Justiça Restaurativa. | L32: EJUD | W32: NUPEMEC | Z32: JUSTIÇA RESTAURATIVA | AB32: Curso | AC32: 10 Edição | AD32: 20 | AH32: Paraná | AI32: 2023 | AJ32: 45147 | AK32: 45170 | AL32: Declaração | AM32: EAD | AO32: 1.6666667 | AP32: 40 h | AQ32: 873 | AR32: https://ead.tjpr.jus.br/course/view.php?id=873 | AU32: Curso fechado | AY32: 593-594/2023 | BA32: 1 - LISTA GERAL_2020 A ... | BC32: 45195 | BI32: #VALUE! | BL32: 18 | BO32: 18
F33: sim | H33: 2023 | I33: 0083639-34.2023.8.16.6000 | J33: Webinar de Sustentabilidade - 2 live | L33: EJUD | Q33: 9275525 | W33: GCJ-GJACJ-AC - Assessoria Correicional do Gabinete dos Juizes Auxiliares do Corregedor-geral da Justiça | X33: Formação Inicial e Continuada | Z33: Sustentabilidade | AA33: não | AB33: live | AI33: 2023 | AJ33: 45147 | AK33: 45147 | AL33: Certificado | AM33: transmissão ao vivo | AN33: Livre | AO33: 0.041666667 | AP33: 1 h | AQ33: 870 | AR33: https://ead.tjpr.jus.br/course/view.php?id=870 | AU33: Curso fechado | AY33: 447 | BA33: 1 - LISTA GERAL_2020 A ... | BC33: 45154 | BI33: #VALUE! | BL33: 140
H34: 2023 | I34: 0078413-48.2023.8.16.6000 | J34: O testamento vital como instrumento para autodeterminação no fim de vida | L34: EJUD | Q34: Luciana Dadalto | W34: CPER-CPASMS - Comissão Permanente de Apoio à Saúde dos Magistrados e Servidores das Comissões Permanentes | X34: Formação Inicial e Continuada | AA34: não | AB34: live | AI34: 2023 | AJ34: 45149 | AK34: 45149 | AL34: SEM CERTIFICAÇÃO | AM34: transmissão ao vivo | AN34: Livre | AO34: 0.041666667 | AP34: 1 h | AR34: não | AU34: Curso fechado | AX34: sem certificação - 9270321 | BI34: #VALUE!
H35: 2023 | I35: 0061423-79.2023.8.16.6000 | J35: CAPACITAÇÃO Espaço de Fala MULHERES TRANSEXUAIS E TRAVESTIS DEBATEM: VIOLÊNCIA E ACESSO À JUSTIÇA | W35: CEVID | AH35: Paraná | AI35: 2023 | AJ35: 45152 | AK35: 45152 | AL35: Certificado | AM35: transmissão ao vivo | AN35: Livre | AO35: 0.083333333 | AP35: 2 h | AQ35: 879 | AR35: https://ead.tjpr.jus.br/course/view.php?id=879 | AU35: Curso fechado | AX35: 20/09 - falei com o Jonatas q expediu os certificados | AY35: 581 - 586/2023 | BA35: 1 - LISTA GERAL_2020 A ... | BC35: 45189 | BI35: #VALUE! | BL35: 77
H36: 2023 | I36: 0102956-18.2023.8.16.6000 | J36: Masterclass de BIM para administração Publica | L36: EJUD | W36: Departamento de Engenharia e Arquitetura | AB36: CURSO | AF36: IN COMPANY | AI36: 2023 | AJ36: 45154 | AK36: 45156 | AU36: arquivado | AX36: 15/08/2023 - não contratado falta de tempo hábil | BA36: IN COMPANY | BI36: #VALUE!
H37: 2023 | I37: 0109501-07.2023.8.16.6000 | J37: Congresso 20 anos do Código Civil: avanços e novos desafios - Homenagem ao Ministro Paulo de Tarso Sanseverino | K37: DIVULGAÇÃO | L37: EJUD | Z37: administrativo | AI37: 2023 | AJ37: 45155 | AK37: 45156 | AU37: arquivado | BI37: #VALUE!
H38: 2023 | I38: 0079748-05.2023.8.16.6000 | J38: Fórum de Integridade do Judiciário Paranaense | L38: EJUD | AH38: Paraná | AI38: 2023 | AJ38: 45163 | AK38: 45163 | AL38: Certificado | AM38: webconferência | AO38: 0.29166667 | AP38: 7 h | AQ38: 871 | AR38: https://ead.tjpr.jus.br/course/view.php?id=871 | AU38: Curso fechado | AY38: 549-566/2023 | BA38: 1 - LISTA GERAL_2020 A ... | BC38: 45314 | BI38: #VALUE! | BL38: 336 | BP38: 1
H39: 2023 | I39: 0075436-83.2023.8.16.6000 | J39: Novas Fronteiras do Direito da Criança e do Adolescente | L39: EJUD | W39: CONSIJ | AH39: Paraná | AI39: 2023 | AJ39: 45168 | AK39: 45168 | AL39: Certificado | AM39: webconferência | AO39: 0.125 | AP39: 3 h | AQ39: 883 | AR39: https://ead.tjpr.jus.br/course/view.php?id=883 | AU39: Curso fechado | AX39: presencial e remoto | AY39: 567- 571/2023 | BA39: 1 - LISTA GERAL_2020 A ... | BC39: 45180 | BI39: #VALUE! | BL39: 124
H40: 2023 | I40: 0110053-69.2023.8.16.6000 | J40: Varas Especializadas em Direito Empresarial, Falências e Recuperação Judicial: Desempenho e Perspectivas | L40: EJUD | W40: P-GP-DG - Diretoria do Gabinete do Presidente | AH40: Paraná | AI40: 2023 | AJ40: 45168 | AK40: 45168 | AL40: Certificado | AM40: webconferência | AN40: Livre | AO40: 0.041666667 | AP40: 1 h | AQ40: 889 | AR40: https://ead.tjpr.jus.br/course/view.php?id=889 | AU40: Curso fechado | AY40: 572//2023 | BA40: 1 - LISTA GERAL_2020 A ... | BC40: 45180 | BI40: #VALUE! | BL40: 95
H41: 2023 | I41: 0101943-81.2023.8.16.6000 | J41: Curso de Aperfeiçoamento para magistrados e magistradas Gestão e Produtividade no 1º Grau de Jurisdição: Projudi e outras ferramentas | L41: EJUD | AA41: 197/2023 | AB41: Curso | AD41: 30 | AH41: Paraná | AI41: 2023 | AJ41: 45169 | AK41: 45208 | AL41: Certificado | AM41: EAD | AN41: MAGISTRATURA | AO41: 1.6666667 | AP41: 40 h | AQ41: 880 | AR41: https://ead.tjpr.jus.br/course/view.php?id=880 | AU41: Curso fechado | AX41: 10/05/24 - não temcertificado docentes emitido (2emiridos) | AY41: 596-602/2023 | BA41: 1 - LISTA GERAL_2020 A ... | BC41: 45243 | BI41: #VALUE! | BL41: 23
H42: 2023 | I42: 0108073-87.2023.8.16.6000 | J42: Como manter o equilíbrio saudável com seus pets | L42: EJUD | W42: CPER-CPASMS - Comissão Permanente de Apoio à Saúde dos Magistrados e Servidores das Comissões Permanentes | AI42: 2023 | AJ42: 45169 | AK42: 45169 | AL42: SEM CERTIFICAÇÃO | AM42: presencial | AN42: Livre | AO42: 0.041666667 | AP42: 1 h | AU42: Curso fechado | AX42: sem certificação - segundo o projeto | BI42: #VALUE!
H43: 2023 | I43: 0110845-23.2023.8.16.6000 | J43: Curso de Formação de Formadores Nível 2 (FOFO N2) - Avaliação da Prática Jurisdicional e o uso de Portfólio | L43: EJUD | AB43: Curso | AD43: 30 | AI43: 2023 | AJ43: 45173 | AK43: 45175 | AM43: presencial | AN43: MAGISTRATURA | AO43: 0.83333333 | AP43: 20 h | AU43: Curso fechado | AX43: 20/09 ofertado pela Escola Nacional de Formação e Aperfeiçoamento de Magistrados – ENFAM e a Rede Nacional de Escolas Judiciais e da Magistratura – Renejum | BI43: #VALUE!
H44: 2023 | I44: 0104966-35.2023.8.16.6000 | J44: Saúde Mental no Ambiente de Trabalho | L44: EJUD | W44: CAMS | AB44: live | AH44: Paraná | AI44: 2023 | AJ44: 45181 | AK44: 45181 | AN44: Chefes de Divisão, Supervisores de unidades e centros, Secretários de Desembargador, Chefes de Secretaria e Chefes de Gabinete | AP44: 1 h | AQ44: 893 | AR44: https://ead.tjpr.jus.br/course/view.php?id=893 | AU44: Curso fechado | AY44: 587/2023 | BA44: 1 - LISTA GERAL_2020 A ... | BC44: 45191 | BI44: #VALUE! | BL44: 427
H45: 2023 | I45: 0108211-54.2023.8.16.6000 | J45: Curso de Aperfeiçoamento para magistrados e magistradas - Equidade de Gênero e Diversidade: desafios e impactos no âmbito do Poder Judiciário | L45: EJUD | Q45: 9433829 | X45: Formação Continuada para efeito de vitaliciamento e válido para a promoção na carreira. | AA45: 217/2023 | AB45: curso | AC45: 2 turmas | AD45: 80 | AH45: Paraná | AI45: 2023 | AJ45: 45182 | AK45: 45209 | AL45: Certificado | AM45: híbrido | AN45: MAGISTRATURA | AO45: 0.91666667 | AP45: 22 h | AQ45: 882 | AR45: https://ead.tjpr.jus.br/course/view.php?id=882 | AU45: Curso fechado | AY45: 602-618/2023 | BA45: 1 - LISTA GERAL_2020 A ... | BC45: 45243 | BI45: #VALUE! | BL45: 26
H46: 2023 | I46: 0086764-10.2023.8.16.6000 | J46: 13º Encontro Nacional de Preparação Online para Pretendentes à Adoção. | L46: EJUD | W46: CONSIJ | AB46: Curso | AH46: Paraná | AI46: 2023 | AJ46: 45185 | AK46: 45239 | AL46: Certificado | AM46: transmissão ao vivo | AP46: 30 H | AQ46: 898 | AR46: https://ead.tjpr.jus.br/course/view.php?id=898 | AU46: curso fechado | BA46: 1 - LISTA GERAL_2020 A ... | BC46: 45609 | BI46: #VALUE! | BM46: 818 | BP46: 28 | BQ46: 15 | BS46: 11
H47: 2023 | I47: 0103348-55.2023.8.16.6000 | J47: CURSO DE CAPACITAÇÃO EM CONCILIAÇÃO E MEDIAÇÃO JUDICIAL e CONCILIAÇÃO JUDICIAL | L47: EJUD | Q47: ANDRESSA THIEMY BALBINO FUJIKI, BRUNO FERNANDO GASPAROTTO, MARISA KREMER e SAMUEL AUGUSTO RAMPON | W47: NUPEMEC | AD47: 30 | AF47: Evento externo | AH47: Cascavel | AI47: 2023 | AJ47: 45187 | AK47: 45191 | AM47: PRESENCIAL | AO47: 1.6666667 | AP47: 40 h | AR47: CONCILIAJUD | AU47: Curso fechado | AX47: CONCILIAJUD/2023 | BA47: CONCILIAJUD | BC47: 45210 | BI47: #VALUE! | BO47: 43
H48: 2023 | I48: 0086764-10.2023.8.16.6000 | J48: 13º Encontro Nacional de Preparação Online para Pretendentes à Adoção - 1 pré-encontro | L48: EJUD | W48: CONSIJ | AB48: Curso | AH48: Paraná | AI48: 2023 | AJ48: 45188 | AK48: 45188 | AL48: Certificado | AM48: transmissão ao vivo | AP48: 1 H | AQ48: 894 | AR48: https://ead.tjpr.jus.br/course/view.php?id=894 | AU48: Curso fechado | BA48: 1 - LISTA GERAL_2020 A ... | BC48: 45264 | BI48: #VALUE! | BM48: 293
H49: 2023 | I49: 0064647-25.2023.8.16.6000 | J49: 1º Encontro Regional sobre Justiça Restaurativa na Educação: “Formando cidadãos por meio do diálogo e da convivência participativa | W49: NUPEMEC | Z49: JUSTIÇA RESTAURATIVA | AD49: 360 | AH49: Âmpere | AI49: 2023 | AJ49: 45189 | AK49: 45189 | AL49: Certificado | AM49: presencial | AN49: Livre | AO49: 0.125 | AP49: 3 h | AQ49: 888 | AR49: https://ead.tjpr.jus.br/course/view.php?id=888 | AU49: Curso fechado | AY49: 603-609/2023 | BA49: 1 - LISTA GERAL_2020 A ... | BC49: 45518 | BI49: #VALUE! | BM49: 290 | BO49: 290
A50: sim | H50: 2023 | I50: 0115131-44.2023.8.16.6000 | J50: Dia Nacional de Luta da Pessoa com Deficiência | L50: EJUD | W50: CPER-CPAI - Comissão Permanente de Acessibilidade e Inclusão das Comissões Permanentes | Z50: Acessibilidade e Inclusão | AI50: 2023 | AJ50: 45190 | AK50: 45190 | AL50: CERTIFICADO | AM50: transmissão ao vivo | AN50: Livre | AO50: 0.0625 | AP50: 1 h30 min | AQ50: 897 | AR50: https://ead.tjpr.jus.br/course/view.php?id=897 | AU50: Curso fechado | AY50: não tem | BA50: 1 - LISTA GERAL_2020 A ... | BC50: 45217 | BI50: #VALUE! | BL50: 92
H51: 2023 | I51: 0116573-45.2023.8.16.6000 | J51: Atualização da ferramenta Balcão Virtual | L51: EJUD | W51: DTIC | AF51: REPOSITÓRIO | AI51: 2023 | AJ51: 45190 | AK51: 45190 | AL51: SEM CERTIFICAÇÃO | AO51: 0.54166667 | AP51: 13 h | AQ51: 896 | AR51: https://ead.tjpr.jus.br/course/view.php?id=896 | AU51: arquivado | AX51: sem expedição de certificado | BI51: #VALUE!
H52: 2023 | I52: 0039706-11.2023.8.16.6000 | J52: Programa "JUSTIÇA E CIDADANIA TAMBÉM SE APRENDEM NA ESCOLA | AI52: 2023 | AJ52: 45191 | AK52: 45210 | AL52: SEM CERTIFICAÇÃO | AU52: Curso fechado | AX52: sem certificação | BI52: #VALUE!
H53: 2023 | I53: 0086764-10.2023.8.16.6000 | J53: 13º Encontro Nacional de Preparação Online para Pretendentes à Adoção - 2 pré-encontro | L53: EJUD | W53: CONSIJ | AB53: Curso | AH53: Paraná | AI53: 2023 | AJ53: 45195 | AK53: 45195 | AL53: Certificado | AM53: transmissão ao vivo | AP53: 1 H | AQ53: 894 | AR53: https://ead.tjpr.jus.br/course/view.php?id=894 | AU53: Curso fechado | BA53: 1 - LISTA GERAL_2020 A ... | BC53: 45369 | BG53: 293 | BI53: #VALUE! | BM53: 349 | BO53: 293 | BP53: 1
H54: 2023 | I54: 0122915-72.2023.8.16.6000 | J54: 1º Simpósio do Departamento do Patrimônio | L54: EJUD | W54: Departamento do Patrimônio | AI54: 2023 | AJ54: 45195 | AK54: 45196 | AL54: SEM CERTIFICAÇÃO | AU54: Curso fechado | AX54: 03/10 - não parece ter certificação | BI54: #VALUE!
H55: 2023 | I55: 0109507-14.2023.8.16.6000 | J55: LVI Encontro do Colégio Permanente de Diretores de Escolas Estaduais da Magistratura (COPEDEM) | K55: CONVITE | Z55: administrativo | AI55: 2023 | AJ55: 45197 | AK55: 45198 | AU55: arquivado | BI55: #VALUE!
H56: 2023 | I56: 0117297-49.2023.8.16.6000 | J56: Curso de atualização e aperfeiçoamento para Instrutores de Mediação e Conciliação Judiciais. | L56: EJUD | Q56: 9558104 | W56: COMISSÃO DA MEDIAÇÃO E DA JUSTIÇA RESTAURATIVA – TJPR | AD56: 25 | AI56: 2023 | AJ56: 45197 | AK56: 45198 | AL56: CERTIFICADO | AM56: presencial | AO56: 0.66666667 | AP56: 16 h | AQ56: 910 | AR56: https://ead.tjpr.jus.br/course/view.php?id=910 | AU56: Curso fechado | AY56: 674-675/2024 | BA56: 1 - LISTA GERAL_2020 A ... | BC56: 45308 | BI56: #VALUE! | BM56: 13 | BO56: 13
H57: 2023 | I57: 0068488-28.2023.8.16.6000 | J57: V Encontro de Magistrados da Infância e Juventude do Paraná e IV reunião do Fórum Estadual de Magistrados da Infância e Juventude do Paraná, | Q57: 9617916 | AA57: 249/2023 | AH57: Guaratuba | AI57: 2023 | AJ57: 45204 | AK57: 45206 | AL57: Certificado | AM57: híbrido | AN57: MAGISTRATURA | AO57: 0.91666667 | AP57: 22 h | AQ57: 900 | AR57: https://ead.tjpr.jus.br/course/view.php?id=900 | AU57: Curso fechado | AX57: 13/11/2023_cert docentes não expedido | AY57: 610-623/2023 | BA57: 1 - LISTA GERAL_2020 A ... | BC57: 45243 | BI57: #VALUE! | BL57: 25
H58: 2023 | I58: 0105220-08.2023.8.16.6000 | J58: Curso de Formação de Técnicos Cumpridores de MandadosII EDIÇÃO - 2023 | L58: EJUD | Q58: 9537370 | AB58: CURSO | AD58: 40 | AH58: paraná | AI58: 2023 | AJ58: 45204 | AK58: 45250 | AL58: certificado | AM58: transmissão ao vivo | AN58: Livre | AO58: 1.6666667 | AP58: 40 h | AQ58: 899 | AR58: https://ead.tjpr.jus.br/course/view.php?id=899 | AU58: Curso fechado | AY58: 661/2023 | BA58: 1 - LISTA GERAL_2020 A ... | BC58: 45274 | BI58: #VALUE! | BM58: 29
H59: 2023 | I59: 0099801-07.2023.8.16.6000 | J59: Psicologia do Testemunho e Tomada de Decisão | L59: EJUD | AA59: 214/2023 | AB59: Curso | AD59: 40 | AH59: Paraná | AI59: 2023 | AJ59: 45210 | AK59: 45243 | AL59: Certificado | AM59: EAD | AN59: MAGISTRATURA | AO59: 1.25 | AP59: 30 h | AQ59: 878 | AR59: https://ead.tjpr.jus.br/course/view.php?id=878 | AU59: curso fechado | BA59: 1 - LISTA GERAL_2020 A ... | BC59: 45338 | BI59: #VALUE! | BM59: 27 | BP59: 1
H60: 2023 | I60: 0117054-08.2023.8.16.6000 | J60: CURSO DE JUSTIÇA RESTAURATIVA – FORMAÇÃO PRÁTICA I (CÍRCULOS NÃO CONFLITIVOS) – MODALIDADE À DISTÂNCIA (SÍNCRONO E ASSÍNCRONO) - 11ª e 12ª Edições | L60: EJUD | AI60: 2023 | AJ60: 45215 | AK60: 45238 | AQ60: 902 | AR60: https://ead.tjpr.jus.br/course/view.php?id=902 | AU60: Curso fechado | AY60: 523-626/2023 | BA60: 1 - LISTA GERAL_2020 A ... | BC60: 45254 | BI60: #VALUE! | BM60: 23 | BO60: 13
A61: sim | B61: sim | H61: 2023 | I61: 0117054-08.2023.8.16.6000 | J61: Justiça Restaurativa: Formação Prática I - 12ª Edição | Z61: 3. Direitos Humanos e Cidadania | AI61: 2023 | AJ61: 45215 | AK61: 45238 | AQ61: 903 | AU61: Curso fechado | BA61: 1 - LISTA GERAL_2020 A ... | BC61: 45254 | BO61: 10
H62: 2023 | I62: 0127019-10.2023.8.16.6000 | J62: XXIV Congresso Paranaense de Direito Administrativo | L62: EJUD | AB62: 1. CONGRESSO | AD62: 25 | AF62: IN COMPANY | AH62: Curitiba/PR | AI62: 2023 | AJ62: 45217 | AK62: 45219 | AL62: Certificado | AM62: presencial | AO62: 1.25 | AP62: 30 h | AU62: Curso fechado | AY62: não tem | BA62: 1 - LISTA GERAL_2020 A ... | BC62: 45226 | BI62: #VALUE! | BM62: 25
H63: 2023 | I63: 0113674-74.2023.8.16.6000 | J63: CURSOS DE FORMAÇÃO DE CONCILIADORES E MEDIADORES JUDICIAL (EaD) – etapa teórica - Turma IX e X | L63: EJUD | Z63: MEDIAÇÃO | AC63: Turma IX e X | AF63: Evento externo | AI63: 2023 | AJ63: 45218 | AK63: 45257 | AO63: 2.2916667 | AP63: 55 h | AQ63: 904 | AU63: Curso fechado | AX63: CONCILIAJUD/2023 | AY63: 818-825/2024 | BA63: CONCILIAJUD | BC63: 45275 | BI63: #VALUE! | BM63: 74
H64: 2023 | I64: 0123357-38.2023.8.16.6000 | J64: 4º Seminário Nacional - Gestão por Competência e Avaliação de Desempenho com foco no sistema "s", estatais e administração pública | L64: EJUD | W64: DGRH-AT - Assessoria Técnica do Departamento de Gestão de Recursos Humanos | AF64: IN COMPANY | AI64: 2023 | AJ64: 45218 | AK64: 45251 | AL64: certificado | AM64: Híbrido | AO64: 1 | AP64: 24 h | AU64: Curso fechado | AX64: Certificação dos inscritos (9817128) | BA64: IN COMPANY | BC64: 45264 | BI64: #VALUE! | BM64: 8
H65: 2023 | I65: 0121435-59.2023.8.16.6000 | J65: XXVII CONGRESSO NACIONAL DE CERIMONIAL E PROTOCOLO | L65: EJUD | AB65: Congresso | AD65: 2 | AF65: EVENTO EXTERNO | AH65: Cuiabá - MT | AI65: 2023 | AJ65: 45224 | AK65: 45226 | AL65: certificado | AM65: presencial | AO65: 0.875 | AP65: 21 h | AU65: Curso fechado | BA65: 3 - EVENTO EXTERNO | BC65: 45258 | BI65: #VALUE!
H66: 2023 | I66: 0113674-74.2023.8.16.6000 | J66: CURSOS DE FORMAÇÃO DE CONCILIADORES E MEDIADORES JUDICIAL (EaD) – etapa teórica - Turma XI e XII | L66: EJUD | AC66: Turma XI e XII | AF66: Evento externo | AI66: 2023 | AJ66: 45225 | AK66: 45264 | AO66: 2.2916667 | AP66: 55 h | AQ66: 904 | AU66: Curso fechado | AX66: CONCILIAJUD/2023 | AY66: 818-825/2024 | BA66: CONCILIAJUD | BC66: 45275 | BI66: #VALUE! | BM66: 73
H67: 2023 | I67: 0122248-86.2023.8.16.6000 | J67: Curso de Aperfeiçoamento para magistrados e magistradas: Moderna Teoria do Conflito, Consensualidade e Jurisdição | L67: EJUD | AA67: 263/2023 | AB67: curso | AD67: 40 | AH67: Paraná | AI67: 2023 | AJ67: 45231 | AK67: 45264 | AL67: certificado | AM67: híbrido | AN67: MAGISTRATURA | AO67: 1.6666667 | AP67: 40 h | AQ67: 912 | AR67: https://ead.tjpr.jus.br/course/view.php?id=912 | AU67: Curso fechado | AY67: 662-666/2023 | BA67: 1 - LISTA GERAL_2020 A ... | BC67: 45275 | BI67: #VALUE! | BM67: 37
H68: 2023 | I68: 0064910-57.2023.8.16.6000 | J68: Capacitação em ITIL V4 | L68: CITS | W68: DTIC-AT - Assessoria Técnica do Departamento de Tecnologia da Informação e Comunicação | Z68: TECNOLOGIA | AC68: 8 turmas | AD68: 232 | AF68: IN COMPANY | AG68: 9462031 | AH68: Paraná | AI68: 2023 | AJ68: 45236 | AK68: 45386 | AO68: 0.66666667 | AP68: 16 h | AU68: Curso fechado | BA68: IN COMPANY | BC68: 45441 | BI68: #VALUE! | BP68: 224
H69: 2023 | I69: 0095423-08.2023.8.16.6000 | J69: Curso Juízo de Admissibilidade de Recursos Excepcionais | L69: EJUD | AD69: 30 | AI69: 2023 | AJ69: 45236 | AK69: 45239 | AL69: CERTIFICADO | AO69: 0.5 | AP69: 12 h | AQ69: 913 | AR69: https://ead.tjpr.jus.br/course/view.php?id=913 | AU69: Curso fechado | BA69: 1 - LISTA GERAL_2020 A ... | BC69: 45264 | BI69: #VALUE! | BM69: 21
H70: 2023 | I70: 0130508-55.2023.8.16.6000 | J70: Formação de Formadores – Desenvolvimento Docente – N1 M2 | L70: EJUD | AA70: 105/2022 | AB70: Curso | AD70: 40 | AH70: Paraná | AI70: 2023 | AJ70: 45236 | AK70: 45265 | AL70: Certificado | AM70: EAD | AN70: MAGISTRATURA | AO70: 1.6666667 | AP70: 40 H | AQ70: 906 | AR70: https://ead.tjpr.jus.br/course/view.php?id=906 | AU70: Curso fechado | AY70: 629-633/2023 | BA70: 1 - LISTA GERAL_2020 A ... | BC70: 45274 | BI70: #VALUE! | BM70: 35
H71: 2023 | I71: 0114628-23.2023.8.16.6000 | J71: Curso de capacitação dos servidores do Núcleo de Cálculos e Contas Processuais | L71: EJUD | X71: Formação Inicial e Continuada | Z71: Gestão | AI71: 2023 | AJ71: 45246 | AK71: 45257 | AL71: Certificado | AM71: transmissão ao vivo | AN71: servidores lotados no Núcleo de Cálculos e Contas Processuais da Central de Movimentações Processuais (NUCCON) | AO71: 1.0416667 | AP71: 25 h | AQ71: 915 | AR71: https://ead.tjpr.jus.br/course/view.php?id=915 | AU71: Curso fechado | BA71: 1 - LISTA GERAL_2020 A ... | BC71: 45275 | BI71: #VALUE! | BM71: 10
H72: 2023 | I72: 0091818-54.2023.8.16.6000 | J72: A Reflexologia das Emoções: Ferramenta de Cura no Pilates | L72: EJUD | W72: CPER-CPASMS - Comissão Permanente de Apoio à Saúde dos Magistrados e Servidores das Comissões Permanentes | AI72: 2023 | AJ72: 45252 | AK72: 45252 | AL72: SEM CERTIFICAÇÃO | AU72: Curso fechado | AX72: não teve certificação | BI72: #VALUE!
H73: 2023 | I73: 0123988-79.2023.8.16.6000 | J73: Curso de Capacitação de gestores do 1º Grau de Jurisdição (Chefes e Supervisores de Secretaria) em Gestão por Competências | L73: EJUD | W73: P-CGC - Comitê de Gestão por Competências | Z73: Gestão | AB73: curso | AH73: paraná | AI73: 2023 | AJ73: 45258 | AK73: 45260 | AN73: gestores do 1 grau | AO73: 0.25 | AP73: 6 h | AQ73: 920 | AR73: https://ead.tjpr.jus.br/course/view.php?id=920 | AU73: Curso fechado | AX73: outras turmas - linha repetida para outras turmas registrado dia 28,29 e 30/11/2023 | BA73: 1 - LISTA GERAL_2020 A ... | BC73: 45320 | BI73: #VALUE!
H74: 2023 | I74: 0098280-27.2023.8.16.6000 | J74: 7º Encontro de Magistrados dos Juizados Especiais do Paraná – EMAJEP e 3º Encontro Paranaense dos Centros Judiciários de Solução de Conflitos e Cidadania – EPACEJUSC | L74: EJUD | W74: NUPEMEC | AB74: curso | AI74: 2023 | AJ74: 45259 | AK74: 45261 | AN74: MAGISTRATURA | AO74: 0.45833333 | AP74: 11 h | AQ74: 922 | AR74: https://ead.tjpr.jus.br/course/view.php?id=922 | AU74: curso fechado | AY74: 634-660/2023 | BA74: 1 - LISTA GERAL_2020 A ... | BC74: 45274 | BI74: #VALUE! | BM74: 82
H75: 2023 | I75: 0148187-68.2023.8.16.6000 | J75: curso de brigada de incêndio da comarca de Barracão -PR | Z75: BRIGADISTA | AH75: Barracão | AI75: 2023 | AJ75: 45272 | AK75: 45272 | AO75: 1.3333333 | AP75: 32 h | AQ75: 840 | AR75: https://ead.tjpr.jus.br/course/view.php?id=840 | AU75: Curso fechado | BC75: 45455 | BP75: 4 | BQ75: 3
H76: 2024 | I76: 0159346-08.2023.8.16.6000 | J76: IX Encontro Especial de posse da nova Diretoria Consepre | L76: CONSEPRE | AC76: IX | AF76: EVENTO EXTERNO | AH76: Foz do Iguaçu | AI76: 2024 | AJ76: 45315 | AK76: 45317 | AL76: CERTIFICADO | AM76: presencial | AU76: Curso fechado | BA76: 3 - EVENTO EXTERNO | BC76: 45327 | BI76: #VALUE! | BP76: 137
H77: 2024 | I77: 0159547-97.2023.8.16.6000 | J77: Curso Oficial de Formação Inicial para Juiz Substituto | L77: EJUD | S77: 10393907 | Z77: MAGISTRADO | AA77: 315/2023 | AB77: Curso | AD77: 3 | AG77: Plano 9868381 | AI77: 2024 | AJ77: 45315 | AK77: 45412 | AL77: Certificado | AM77: presencial | AN77: MAGISTRADO | AO77: 20.416667 | AP77: 490 h | AQ77: 941 | AR77: https://ead.tjpr.jus.br/course/view.php?id=941 | AU77: Curso fechado | AY77: 744-765/2024 | BC77: 45475 | BI77: #VALUE! | BQ77: 3
H78: 2024 | I78: 0026527-73.2024.8.16.6000 | J78: curso para capacitação de Gestores de Pessoas do 1º Grau de Jurisdição (Chefes e Supervisores de Secretaria) acerca da gestão por competências, etapa de Oficina presencial realizada em Paranaguá | W78: SG-SGP-CGP-DD - Divisão de Desenvolvimento da Coordenadoria de Gestão de Pessoal da Secretaria de Gestão de Pessoas | Z78: Gestão | AB78: 12. CURSOS | AH78: Paranaguá | AI78: 2024 | AJ78: 45342 | AK78: 45342 | AM78: presencial | AP78: 6 | AU78: Curso fechado | AX78: registro no processo 0123988-79.2023.8.16.6000
H79: 2024 | I79: 0123988-79.2023.8.16.6000 | J79: Curso de Capacitação de gestores do 1º Grau de Jurisdição (Chefes e Supervisores de Secretaria) em Gestão por Competências | L79: EJUD | W79: P-CGC - Comitê de Gestão por Competências | Z79: Gestão | AB79: curso | AG79: Cota 9927786 | AH79: Paranaguá | AI79: 2024 | AJ79: 45342 | AK79: 45342 | AN79: gestores do 1 grau | AO79: 0.25 | AP79: 6 h | AQ79: 920 | AR79: https://ead.tjpr.jus.br/course/view.php?id=920 | AU79: Curso fechado | BC79: 45391 | BP79: 18
H80: 2024 | I80: 0005942-97.2024.8.16.6000 | J80: cursos de Mediação e Conciliação Judicial - Turmas XIII | L80: EJUD | P80: 0007820-57.2024.8.16.6000 | Q80: Mariana Pisacco, Liciane Junia Baltazar, Bruno Fernando Gasparotto e Marcel Tulio | Z80: MEDIAÇÃO | AD80: 40 | AF80: Evento externo | AI80: 2024 | AJ80: 45344 | AK80: 45383 | AL80: Declaração | AO80: 2.2916667 | AP80: 55 h | AQ80: 925 | AR80: https://ead.tjpr.jus.br/course/view.php?id=925 | AU80: Curso fechado | AX80: CONCILIAJUD | AY80: CONCILIAJUD | BA80: CONCILIAJUD | BC80: 45398 | BI80: #VALUE! | BO80: 30 | BQ80: 30
H81: 2024 | I81: 0020551-85.2024.8.16.6000 | J81: Reforma Tributária: debates e perspectivas | AD81: 300 | AH81: Curitiba | AI81: 2024 | AJ81: 45345 | AK81: 45345 | AM81: híbrido | AN81: QUADRO INTERNO | AO81: 0.3125 | AP81: 7h30m | AQ81: 930 | AR81: https://ead.tjpr.jus.br/course/view.php?id=930 | AU81: Curso fechado | AX81: forcei a emissão dos certificados | AY81: não emitido | BC81: 45387 | BP81: 71
H82: 2024 | I82: 0014185-30.2024.8.16.6000 | J82: Webinário Equivalência de Carga de Trabalho: Um Novo Paradigma do Trabalho na Justiça | L82: CNJ | W82: CNJ | AB82: webnário | AF82: EVENTO EXTERNO | AH82: Paraná | AI82: 2024 | AJ82: 45348 | AK82: 45349 | AU82: Curso fechado | AW82: 45397 | AX82: cnj - não tem certif nos autos | BA82: 3 - EVENTO EXTERNO | BI82: #VALUE!
H83: 2024 | I83: 0123988-79.2023.8.16.6000 | J83: Curso de Capacitação de gestores do 1º Grau de Jurisdição (Chefes e Supervisores de Secretaria) em Gestão por Competências | L83: EJUD | W83: P-CGC - Comitê de Gestão por Competências | Z83: Gestão | AB83: curso | AG83: Cota 9927786 | AH83: Ponta Grossa | AI83: 2024 | AJ83: 45349 | AK83: 45349 | AN83: gestores do 1 grau | AO83: 0.25 | AP83: 6 h | AQ83: 920 | AR83: https://ead.tjpr.jus.br/course/view.php?id=920 | AU83: Curso fechado | BC83: 45391 | BP83: 19
H84: 2024 | I84: 0123988-79.2023.8.16.6000 | J84: Curso de Capacitação de gestores do 1º Grau de Jurisdição (Chefes e Supervisores de Secretaria) em Gestão por Competências | L84: EJUD | W84: P-CGC - Comitê de Gestão por Competências | Z84: Gestão | AB84: curso | AG84: Cota 9927786 | AH84: Ponta Grossa | AI84: 2024 | AJ84: 45350 | AK84: 45350 | AN84: gestores do 1 grau | AO84: 0.25 | AP84: 6 h | AQ84: 920 | AR84: https://ead.tjpr.jus.br/course/view.php?id=920 | AU84: Curso fechado | BC84: 45391 | BP84: 13
H85: 2024 | I85: 0026063-49.2024.8.16.6000 | J85: Justiça Restaurativa: Formação Prática I - 13ª edição | L85: EJUD | P85: 0030438-93.2024.8.16.6000 | Z85: JUSTIÇA RESTAURATIVA | AB85: 12. CURSOS | AD85: 20 | AG85: 10094890 | AH85: Cascavel | AI85: 2024 | AJ85: 45355 | AK85: 45358 | AL85: Declaração | AM85: EAD | AO85: 1.6666667 | AP85: 40 h | AQ85: 931 | AR85: https://ead.tjpr.jus.br/course/view.php?id=931 | AU85: Curso fechado | AY85: 697-698/2024 | BA85: 1 - LISTA GERAL_2020 A ... | BC85: 45398 | BO85: 13 | BQ85: 13
H86: 2024 | I86: 0011106-43.2024.8.16.6000 | J86: Curso de Aperfeiçoamento para magistrados e magistradas em Psicologia do Testemunho e Tomada de Decisão – 2ª Edição | L86: EJUD | P86: 0021726-17.2024.8.16.6000 | Z86: MAGISTRADO | AA86: 214/2023 | AB86: 12. CURSOS | AG86: 10004437 | AI86: 2024 | AJ86: 45358 | AK86: 45390 | AL86: certificado | AN86: MAGISTRADO | AO86: 1.25 | AP86: 30 H | AQ86: 927 | AR86: https://ead.tjpr.jus.br/course/view.php?id=927 | AU86: Curso fechado | AX86: forcei a emissão dos certificados | AY86: 701/2024 - não emitido | BC86: 45406 | BI86: #VALUE! | BQ86: 31
H87: 2024 | I87: 0028033-84.2024.8.16.6000 | J87: heteroidentificação/curso "Ações Afirmativas, Comissões de Heteroidentificação e relações sociais no contexto do Judiciário" | P87: 0029287-92.2024.8.16.6000 | Z87: ACESSIBILIDADE E INCLUSÃO | AB87: Curso | AD87: 40 | AF87: EAD | AI87: 2024 | AJ87: 45358 | AK87: 45366 | AL87: certificado | AM87: EAD | AN87: Comissão de Heteroidentificação e convidados pela Comissão | AO87: 0.83333333 | AP87: 20 h | AQ87: 933 | AR87: https://ead.tjpr.jus.br/course/view.php?id=933 | AU87: Curso fechado | AY87: 687-689/2024 | BA87: 1 - LISTA GERAL_2020 A ... | BC87: 45387 | BP87: 12
H88: 2024 | I88: 0019244-96.2024.8.16.6000 | J88: Curso de Aperfeiçoamento para Magistradas e Magistrados sobre aspectos práticos da Recuperação Judicial e Falência | P88: 0032647-35.2024.8.16.6000 | S88: Atesto 10394035 | T88: ok | Z88: MAGISTRADO | AA88: 40/2024 | AB88: 12. CURSOS | AG88: Plano 10057420 | AH88: Paraná | AI88: 2024 | AJ88: 45365 | AK88: 45412 | AL88: Certificado | AM88: híbrido | AN88: MAGISTRADO | AO88: 1.6666667 | AP88: 40 h | AQ88: 935 | AR88: https://ead.tjpr.jus.br/course/view.php?id=935 | AU88: Curso fechado | AW88: 45470 | AY88: 717-725/2024 | BC88: 45468 | BQ88: 33
H89: 2024 | I89: 0026060-94.2024.8.16.6000 | J89: Curso Formação Prática II em Justiça Restaurativa (práticas circulares conflitivas - turma 2 | Q89: Marli Takaiama e Samuel Augusto Rampon | Z89: JUSTIÇA RESTAURATIVA | AB89: 12. CURSOS | AD89: 20 | AG89: 10095971 | AH89: Cascavel | AI89: 2024 | AJ89: 45369 | AK89: 45373 | AL89: Declaração | AO89: 0.75 | AP89: 18 h | AQ89: 932 | AR89: https://ead.tjpr.jus.br/course/view.php?id=932 | AU89: Curso fechado | AY89: 699-700/2024 | BA89: 1 - LISTA GERAL_2020 A ... | BC89: 45398 | BO89: 14 | BQ89: 14
H90: 2024 | I90: 0028039-91.2024.8.16.6000 | J90: 19º CONGRESSO BRASILEIRO DE PREGOEIROS, organizado pelo Instituto Negócios Públicos do Brasil Ltda, na modalidade ON-LINE, a ser realizado nas datas de 18 a 21 de março de 2024. | W90: SG-SLCC-GS-AT - Assessoria Técnica do Gabinete do Secretário da Secretaria de Licitações, Contratos e Convênios | AB90: Congresso | AF90: IN COMPANY | AH90: on line | AI90: 2024 | AJ90: 45369 | AK90: 45372 | AM90: on line | AU90: Curso fechado | BA90: IN COMPANY | BC90: 45399 | BQ90: 26
H91: 2024 | I91: 0028449-52.2024.8.16.6000 | J91: Curso de Aperfeiçoamento para Magistradas e Magistrados "Gestão e Produtividade no 1º grau de jurisdição: Projudi e outras ferramentas". | P91: 0030951-61.2024.8.16.6000 | S91: Atesto 10390709 | Z91: Gestão | AA91: 197/2023 | AB91: 12. CURSOS | AI91: 2024 | AJ91: 45372 | AK91: 45411 | AN91: MAGISTRATURA | AO91: 1.6666667 | AP91: 40 h | AQ91: 934 | AR91: https://ead.tjpr.jus.br/course/view.php?id=934 | AU91: Curso fechado | AY91: 703-713/2024 | BC91: 45448 | BQ91: 22
H92: 2024 | I92: 0127200-11.2023.8.16.6000 | J92: II Seminário de Acessibilidade e Inclusão do Tribunal de Justiça do Paraná | W92: GCJ-UEA - Unidade Especial de Atuação no Primeiro Grau de Jurisdição do Gabinete do Corregedor-Geral da Justiça | Z92: ACESSIBILIDADE E INCLUSÃO | AB92: 3. SEMINÁRIO | AC92: II Ed | AE92: sim | AH92: Curitiba | AI92: 2024 | AJ92: 45372 | AK92: 45372 | AM92: híbrido | AO92: 0.125 | AP92: 3 h | AQ92: 936 | AR92: https://ead.tjpr.jus.br/course/view.php?id=936 | AU92: Curso fechado | AX92: 05/04/2024_forcei a emissão dos certificados | AY92: 692-696/2024 | BA92: 1 - LISTA GERAL_2020 A ... | BC92: 45391 | BP92: 277
H93: 2024 | I93: 0026626-43.2024.8.16.6000 | J93: Live Março Azul Marinho Mês da Prevenção do Câncer Colorretal | X93: Formação Inicial e Continuada | AB93: 13. LIVES | AI93: 2024 | AJ93: 45373 | AK93: 45373 | AO93: 0.041666667 | AP93: 1 H | AR93: não localizado | AU93: Curso fechado | AX93: certificado somente do palestrante | AY93: 743/2024 | BC93: 45475
H94: 2024 | I94: 0023952-92.2024.8.16.6000 | J94: Ciclos de discussão e atualização jurídica: competências das Câmaras Cíveis e Criminais do TJPR | AC94: Ciclo 1 | AG94: 10151042 | AI94: 2024 | AJ94: 45378 | AK94: 45378 | AL94: certificado | AN94: Desembargadores, Desembargadores Substitutos, Juízes, Assessores de Gabinetes e demais interessados integrantes do quadro do TJPR | AO94: 0.083333333 | AP94: 2h | AQ94: 939 | AR94: https://ead.tjpr.jus.br/course/view.php?id=939 | AU94: Curso fechado | AY94: 690-691/2024 | BA94: 1 - LISTA GERAL_2020 A ... | BC94: 45387 | BQ94: 132
H95: 2024 | I95: 0134029-08.2023.8.16.6000 | J95: Formação de Formadores da Unidade Especial de Atuação no Primeiro Grau de Jurisdição | AB95: 12. CURSOS | AG95: Plano de curso (10236912) | AI95: 2024 | AJ95: 45383 | AK95: 45447 | AM95: HÍBRIDO | AN95: formadores da Unidade Especial de Atuação no 1º Grau de Jurisdição | AP95: 50 h | AQ95: 940 | AR95: https://ead.tjpr.jus.br/course/view.php?id=940 | AU95: Curso fechado | BC95: 45492 | BI95: #VALUE! | BQ95: 26
H96: 2024 | I96: 0035823-22.2024.8.16.6000 | J96: IX Seminário de Segurança LAAD 2024 | N96: Creative Events Brazil Exibições e Feiras Ltda | O96: 10.432.341/0001-90 | S96: 10297684 | W96: P-SEP-GSEP-AM - Assessoria Militar | AB96: 3. SEMINÁRIO | AD96: 4 | AF96: IN COMPANY | AG96: 10248958 | AH96: São Paulo - SP | AI96: 2024 | AJ96: 45384 | AK96: 45386 | AM96: presencial | AN96: Assessoria Militar e Divisão de Segurança Patrimonial | AO96: 0.66666667 | AP96: 16 h | AU96: Curso fechado | BA96: IN COMPANY | BQ96: 4
H97: 2024 | I97: 0123988-79.2023.8.16.6000 | J97: Curso de Capacitação de gestores do 1º Grau de Jurisdição (Chefes e Supervisores de Secretaria) em Gestão por Competências | L97: EJUD | W97: P-CGC - Comitê de Gestão por Competências | Z97: Gestão | AB97: curso | AG97: Informação 10080944 | AH97: Francisco Beltrão | AI97: 2024 | AJ97: 45384 | AK97: 45384 | AN97: gestores do 1 grau | AO97: 0.25 | AP97: 6 h | AQ97: 920 | AR97: https://ead.tjpr.jus.br/course/view.php?id=920 | AU97: Curso fechado | BC97: 45455 | BQ97: 10
H98: 2024 | I98: 0032267-12.2024.8.16.6000 | J98: Curso Formação Prática I em Justiça Restaurativa" - 14ª e 15ª Edições | S98: Atesto 10461219 | T98: ok | Z98: DTOS HUMANOS E CIDADANIA | AD98: 20 | AG98: Projeto 10137350 | AH98: paran | AI98: 2024 | AJ98: 45390 | AK98: 45414 | AM98: on line | AO98: 1.6666667 | AP98: 40 h | AQ98: 938 | AR98: https://ead.tjpr.jus.br/course/view.php?id=938 | AU98: Curso fechado | AY98: 766-769/2024 | BA98: 1 - LISTA GERAL_2020 A ... | BC98: 45485 | BO98: 34 | BQ98: 34
H99: 2024 | I99: 0122714-80.2023.8.16.6000 | J99: Treinamento em LGPD | N99: VETALUTI CONSULTORIA E ASSESSORIA LTDA | O99: 37.781.826/0001-45 | S99: Atesto 10505071 | W99: P-CGPD - Comitê Gestor de Proteção de Dados | AB99: 12. CURSOS | AD99: 56 | AF99: IN COMPANY | AI99: 2024 | AJ99: 45390 | AK99: 45436 | AM99: ON LINE | AN99: Analistas, técnicos e demais servidores lotados no Departamento de Tecnologia da Informação e Comunicação | AP99: 60 h | AU99: Curso fechado | AX99: Certificação dos inscritos (10577034) | BA99: IN COMPANY | BC99: 45470 | BI99: #VALUE! | BQ99: 58
H100: 2024 | I100: 0034024-41.2024.8.16.6000 | J100: Oficinas de Parentalidade: O amor aos filhos como ferramenta de superação de conflitos" | AF100: IN COMPANY | AI100: 2024 | AJ100: 45392 | AK100: 45418 | AL100: certificado | AP100: 18 h | AU100: Curso fechado | BA100: IN COMPANY | BC100: 45692 | BO100: 3
...

Sheet controle_matriz
A1: MODALIDADE | B1: ID DA PLANILHA | C1: ANO | D1: SEI | E1: NOME DO Curso | F1: conteúdo programatico | G1: NENHUMA CLASSIFICAÇÃO COPILOT | H1: Capacitação em Direitos Humanos, Gênero, Raça e Etnia; e em Depoimento Especial" - 0148945-13.2024.8.16.6000 | I1: Justiça Restaurativa - 0148919-15.2024.8.16.6000 | J1: Capacitação de Facilitadores 0148959-94.2024.8.16.6000 | K1: Acessibilidade e Inclusão - 0148938-21.2024.8.16.6000 | L1: Política de Prevenção e Enfrentamento do Assédio Moral, do Assédio Sexual e da Discriminação.0148908-83.2024.8.16.6000 | M1: SOCIOAMBIENTAL | N1: SUSTENTABILIDADE https://portal.tjpr.jus.br/portletforms/frm.do?idFormulario=7430 0017859-16.2024.8.16.6000 | O1: CURSO PARA MAGISTRADOS | P1: CATEGORIA DO Curso | Q1: RESPONSÁVEL PELA CERTIFICAÇÃO | R1: INSTITUIÇÃO DE ENSINO | S1: EMPRESA CONTRATADA | T1: CNPJ | U1: SEI DOC INSTRUTORES | V1: Intrutor (andamento do SEI) | W1: TERMO DE USO DE IMAGEM | X1: ATESTO | Y1: PRE ANOTAÇÃO ATESTO | Z1: REG DE INSTRUTORES | AA1: DESPESAS | AB1: VALOR DAS DESPESAS | AC1: PRODUÇÃO/UNIDADE SOLICITANTE | AD1: Eixo de Capacitação - Itinerários Formativos | AE1: PAE | AF1: INDICADORES | AG1: PORTARIA ENFAM | AH1: Tipo de evento | AI1: TURMA | AJ1: nº de vagas | AK1: INTÉRPRETES DE LIBRAS | AL1: MODALIDADE2 | AM1: PLANO DE CURSO/SEI | AN1: LOCAL | AO1: ANO DO CURSO2 | AP1: DATA INÍCIO | AQ1: DATA TERMINO | AR1: DECLARAÇÃO/ CERTIFICADO/ SEM CERTIFICAÇÃO | AS1: ON LINE OU PRESENCIAL | AT1: PUBLICO ALVO | AU1: RELATORIO_CARGA HORÁRIA | AV1: CARGA HORARIA | AW1: ID | AX1: ID do AVA novo | AY1: LINK AVA/ANDAMENTO DO CERTIFICADO | AZ1: lista de presença | BA1: SEI DOS INSCRITOS | BB1: STATUS | BC1: pronto para registro | BD1: DATA DA ULTIMA VERIFICAÇÃO | BE1: obs 2: | BF1: LIVRO DE REGISTRO | BG1: DATA DO ULTIMO REGISTRO | BH1: REG DE INSTRUTORES2 | BI1: REGISTRO DE INSTRUTORES NO SEI | BJ1: 2021 | BK1: 2022 | BL1: 2023 | BM1: REGISTRO NO SEI/2024 | BN1: 2024 | BO1: REGISTRO NO SEI/2025 | BP1: TOTAL CERTIFICADOS EMITIDOS/2025 | BQ1: 1º trim/2025 | BR1: 2º trim/2025 | BS1: 3º trim/2025 | BT1: 4º trim/2025
B2: 1 | C2: 1 | E2: 1° Curso de Formação de Laboratorista | AW2: 424 | BB2: Curso fechado | BP2: =Tabela3[[#This Row],[1º trim/2025]]+Tabela3[[#This Row],[2º trim/2025]]+Tabela3[[#This Row],[3º trim/2025]]+Tabela3[[#This Row],[4º trim/2025]] -> 0
B3: 2 | C3: 1 | E3: 10A/17CM - CURITIBA | AF3: MEDIAÇÃO | AI3: 10A/17CM - CURITIBA | AN3: CURITIBA | AW3: 111 | BB3: Curso fechado | BP3: =Tabela3[[#This Row],[1º trim/2025]]+Tabela3[[#This Row],[2º trim/2025]]+Tabela3[[#This Row],[3º trim/2025]]+Tabela3[[#This Row],[4º trim/2025]] -> 0
B4: 3 | C4: 1 | E4: 10A/18CM - CURITIBA | AF4: MEDIAÇÃO | AI4: 10A/18CM - CURITIBA | AN4: CURITIBA | AW4: 171 | BB4: Curso fechado | BP4: =Tabela3[[#This Row],[1º trim/2025]]+Tabela3[[#This Row],[2º trim/2025]]+Tabela3[[#This Row],[3º trim/2025]]+Tabela3[[#This Row],[4º trim/2025]] -> 0
B5: 4 | C5: 1 | E5: 10B/17CM - CURITIBA | AF5: MEDIAÇÃO | AI5: 10B/17CM - CURITIBA | AN5: CURITIBA | AW5: 112 | BB5: Curso fechado | BP5: =Tabela3[[#This Row],[1º trim/2025]]+Tabela3[[#This Row],[2º trim/2025]]+Tabela3[[#This Row],[3º trim/2025]]+Tabela3[[#This Row],[4º trim/2025]] -> 0
B6: 5 | C6: 1 | E6: 10B/18CM - CURITIBA | AF6: MEDIAÇÃO | AI6: 10B/18CM - CURITIBA | AN6: CURITIBA | AW6: 172 | BB6: Curso fechado | BP6: =Tabela3[[#This Row],[1º trim/2025]]+Tabela3[[#This Row],[2º trim/2025]]+Tabela3[[#This Row],[3º trim/2025]]+Tabela3[[#This Row],[4º trim/2025]] -> 0
B7: 6 | C7: 1 | E7: 11A/17CM - PONTA GROSSA | AF7: MEDIAÇÃO | AI7: 11A/17CM - PONTA GROSSA | AN7: PONTA GROSSA | AW7: 104 | BB7: Curso fechado | BP7: =Tabela3[[#This Row],[1º trim/2025]]+Tabela3[[#This Row],[2º trim/2025]]+Tabela3[[#This Row],[3º trim/2025]]+Tabela3[[#This Row],[4º trim/2025]] -> 0
B8: 7 | C8: 1 | E8: 11A/18CM - CURITIBA | AF8: MEDIAÇÃO | AI8: 11A/18CM - CURITIBA | AN8: CURITIBA | AW8: 176 | BB8: Curso fechado | BP8: =Tabela3[[#This Row],[1º trim/2025]]+Tabela3[[#This Row],[2º trim/2025]]+Tabela3[[#This Row],[3º trim/2025]]+Tabela3[[#This Row],[4º trim/2025]] -> 0
B9: 8 | C9: 1 | E9: 11B/18CM - CURITIBA | AF9: MEDIAÇÃO | AI9: 11B/18CM - CURITIBA | AN9: CURITIBA | AW9: 177 | BB9: Curso fechado | BP9: =Tabela3[[#This Row],[1º trim/2025]]+Tabela3[[#This Row],[2º trim/2025]]+Tabela3[[#This Row],[3º trim/2025]]+Tabela3[[#This Row],[4º trim/2025]] -> 0
B10: 9 | C10: 1 | E10: 12A/17CM - CIANORTE | AF10: MEDIAÇÃO | AI10: 12A/17CM - CIANORTE | AN10: CIANORTE | AW10: 107 | BB10: Curso fechado | BP10: =Tabela3[[#This Row],[1º trim/2025]]+Tabela3[[#This Row],[2º trim/2025]]+Tabela3[[#This Row],[3º trim/2025]]+Tabela3[[#This Row],[4º trim/2025]] -> 0
B11: 10 | C11: 1 | E11: 12A/18CM - CURITIBA | AF11: MEDIAÇÃO | AI11: 12A/18CM - CURITIBA | AN11: CURITIBA | AW11: 178 | BB11: Curso fechado | BP11: =Tabela3[[#This Row],[1º trim/2025]]+Tabela3[[#This Row],[2º trim/2025]]+Tabela3[[#This Row],[3º trim/2025]]+Tabela3[[#This Row],[4º trim/2025]] -> 0
B12: 11 | C12: 1 | E12: 12B/17CM - CIANORTE | AF12: MEDIAÇÃO | AI12: 12B/17CM - CIANORTE | AN12: CIANORTE | AW12: 108 | BB12: Curso fechado | BP12: =Tabela3[[#This Row],[1º trim/2025]]+Tabela3[[#This Row],[2º trim/2025]]+Tabela3[[#This Row],[3º trim/2025]]+Tabela3[[#This Row],[4º trim/2025]] -> 0
B13: 12 | C13: 1 | E13: 12B/18CM - CURITIBA | AF13: MEDIAÇÃO | AI13: 12B/18CM - CURITIBA | AN13: CURITIBA | AW13: 179 | BB13: Curso fechado | BP13: =Tabela3[[#This Row],[1º trim/2025]]+Tabela3[[#This Row],[2º trim/2025]]+Tabela3[[#This Row],[3º trim/2025]]+Tabela3[[#This Row],[4º trim/2025]] -> 0
B14: 13 | C14: 1 | E14: 13A/17CM - CURITIBA | AF14: MEDIAÇÃO | AI14: 13A/17CM - CURITIBA | AN14: CURITIBA | AW14: 110 | BB14: Curso fechado | BP14: =Tabela3[[#This Row],[1º trim/2025]]+Tabela3[[#This Row],[2º trim/2025]]+Tabela3[[#This Row],[3º trim/2025]]+Tabela3[[#This Row],[4º trim/2025]] -> 0
... B43: 42 | C43: 1 | E43: 1A/18CM - CURITIBA | AF43: MEDIAÇÃO | AI43: 1A/18CM - CURITIBA | AN43: CURITIBA | AW43: 137 | BB43: Curso fechado | BP43: =Tabela3[[#This Row],[1º trim/2025]]+Tabela3[[#This Row],[2º trim/2025]]+Tabela3[[#This Row],[3º trim/2025]]+Tabela3[[#This Row],[4º trim/2025]] -> 0
B44: 43 | C44: 1 | E44: 2024 _ Brigada _ Etapa Prática-Certificado de Brigadista _ Jandaia do Sul | AF44: BRIGADISTA | AN44: Jandaia do Sul | AW44: 954 | AY44: https://ead.tjpr.jus.br/course/view.php?id=954 | BB44: Curso fechado | BP44: =Tabela3[[#This Row],[1º trim/2025]]+Tabela3[[#This Row],[2º trim/2025]]+Tabela3[[#This Row],[3º trim/2025]]+Tabela3[[#This Row],[4º trim/2025]] -> 0
B45: 44 | C45: 1 | E45: 2024 _ Brigada _ Etapa Prática-Certificado de Brigadista _ Cruzeiro do Oeste | AF45: BRIGADISTA | AN45: Cruzeiro do Oeste | AW45: 954 | AY45: https://ead.tjpr.jus.br/course/view.php?id=954 | BB45: Curso fechado | BP45: =Tabela3[[#This Row],[1º trim/2025]]+Tabela3[[#This Row],[2º trim/2025]]+Tabela3[[#This Row],[3º trim/2025]]+Tabela3[[#This Row],[4º trim/2025]] -> 0
B46: 45 | C46: 1 | E46: 2024 _ Brigada _ Etapa Prática-Certificado de Brigadista _ Palácio do Tribunal de Justiça | AF46: BRIGADISTA | AN46: Palácio do Tribunal de Justiça | AW46: 954 | AY46: https://ead.tjpr.jus.br/course/view.php?id=954 | BB46: Curso fechado | BP46: =Tabela3[[#This Row],[1º trim/2025]]+Tabela3[[#This Row],[2º trim/2025]]+Tabela3[[#This Row],[3º trim/2025]]+Tabela3[[#This Row],[4º trim/2025]] -> 0
B47: 46 | C47: 1 | E47: 20A/17CM - TOLEDO | AF47: MEDIAÇÃO | AI47: 20A/17CM - TOLEDO | AN47: TOLEDO | AW47: 133 | BB47: Curso fechado | BP47: =Tabela3[[#This Row],[1º trim/2025]]+Tabela3[[#This Row],[2º trim/2025]]+Tabela3[[#This Row],[3º trim/2025]]+Tabela3[[#This Row],[4º trim/2025]] -> 0
B48: 47 | C48: 1 | E48: 20A/18CM - CURITIBA | AF48: MEDIAÇÃO | AI48: 20A/18CM - CURITIBA | AN48: CURITIBA | AW48: 209 | BB48: Curso fechado | BP48: =Tabela3[[#This Row],[1º trim/2025]]+Tabela3[[#This Row],[2º trim/2025]]+Tabela3[[#This Row],[3º trim/2025]]+Tabela3[[#This Row],[4º trim/2025]] -> 0
B49: 48 | C49: 1 | E49: 20B/17CM - TOLEDO | AF49: MEDIAÇÃO | AI49: 20B/17CM - TOLEDO | AN49: TOLEDO | AW49: 134 | BB49: Curso fechado | BP49: =Tabela3[[#This Row],[1º trim/2025]]+Tabela3[[#This Row],[2º trim/2025]]+Tabela3[[#This Row],[3º trim/2025]]+Tabela3[[#This Row],[4º trim/2025]] -> 0
B50: 49 | C50: 1 | E50: 21A/17CM - LONDRINA | AF50: MEDIAÇÃO | AI50: 21A/17CM - LONDRINA | AN50: Londrina | AW50: 124 | BB50: Curso fechado | BP50: =Tabela3[[#This Row],[1º trim/2025]]+Tabela3[[#This Row],[2º trim/2025]]+Tabela3[[#This Row],[3º trim/2025]]+Tabela3[[#This Row],[4º trim/2025]] -> 0
B51: 50 | C51: 1 | E51: 21B/17CM - LONDRINA | AF51: MEDIAÇÃO | AI51: 21B/17CM - LONDRINA | AN51: Londrina | AW51: 125 | BB51: Curso fechado | BP51: =Tabela3[[#This Row],[1º trim/2025]]+Tabela3[[#This Row],[2º trim/2025]]+Tabela3[[#This Row],[3º trim/2025]]+Tabela3[[#This Row],[4º trim/2025]] -> 0
B52: 51 | C52: 1 | E52: 22A/17CM - MARINGÁ | AF52: MEDIAÇÃO | AI52: 22A/17CM - MARINGÁ | AN52: Maringá | AW52: 131 | BB52: Curso fechado | BP52: =Tabela3[[#This Row],[1º trim/2025]]+Tabela3[[#This Row],[2º trim/2025]]+Tabela3[[#This Row],[3º trim/2025]]+Tabela3[[#This Row],[4º trim/2025]] -> 0
B53: 52 | C53: 1 | E53: 22A/18CM - CURITIBA | AF53: MEDIAÇÃO | AI53: 22A/18CM - CURITIBA | AN53: CURITIBA | AW53: 224 | BB53: Curso fechado | BP53: =Tabela3[[#This Row],[1º trim/2025]]+Tabela3[[#This Row],[2º trim/2025]]+Tabela3[[#This Row],[3º trim/2025]]+Tabela3[[#This Row],[4º trim/2025]] -> 0
B54: 53 | C54: 1 | E54: 22B/17CM - MARINGÁ | AF54: MEDIAÇÃO | AI54: 22B/17CM - MARINGÁ | AN54: Maringá | AW54: 132 | BB54: Curso fechado | BP54: =Tabela3[[#This Row],[1º trim/2025]]+Tabela3[[#This Row],[2º trim/2025]]+Tabela3[[#This Row],[3º trim/2025]]+Tabela3[[#This Row],[4º trim/2025]] -> 0
B55: 54 | C55: 1 | E55: 22B/18CM - CURITIBA | AF55: MEDIAÇÃO | AI55: 22B/18CM - CURITIBA | AN55: CURITIBA | AW55: 226 | BB55: Curso fechado | BP55: =Tabela3[[#This Row],[1º trim/2025]]+Tabela3[[#This Row],[2º trim/2025]]+Tabela3[[#This Row],[3º trim/2025]]+Tabela3[[#This Row],[4º trim/2025]] -> 0
B56: 55 | C56: 1 | E56: 22C/18CM - CURITIBA | AF56: MEDIAÇÃO | AI56: 22C/18CM - CURITIBA | AN56: CURITIBA | AW56: 229 | BB56: Curso fechado | BP56: =Tabela3[[#This Row],[1º trim/2025]]+Tabela3[[#This Row],[2º trim/2025]]+Tabela3[[#This Row],[3º trim/2025]]+Tabela3[[#This Row],[4º trim/2025]] -> 0
B57: 56 | C57: 1 | E57: 23A/17CM - CASCAVEL | AF57: MEDIAÇÃO | AI57: 23A/17CM - CASCAVEL | AN57: Cascavel | AW57: 136 | BB57: Curso fechado | BP57: =Tabela3[[#This Row],[1º trim/2025]]+Tabela3[[#This Row],[2º trim/2025]]+Tabela3[[#This Row],[3º trim/2025]]+Tabela3[[#This Row],[4º trim/2025]] -> 0
B58: 57 | C58: 1 | E58: 23A/18CM - CURITIBA | AF58: MEDIAÇÃO | AI58: 23A/18CM - CURITIBA | AN58: CURITIBA | AW58: 211 | BB58: Curso fechado | BP58: =Tabela3[[#This Row],[1º trim/2025]]+Tabela3[[#This Row],[2º trim/2025]]+Tabela3[[#This Row],[3º trim/2025]]+Tabela3[[#This Row],[4º trim/2025]] -> 0
... B70: 69 | C70: 1 | E70: 2C/17CM - CURITIBA | AF70: MEDIAÇÃO | AI70: 2C/17CM - CURITIBA | AN70: CURITIBA | AW70: 82 | BB70: Curso fechado | BP70: =Tabela3[[#This Row],[1º trim/2025]]+Tabela3[[#This Row],[2º trim/2025]]+Tabela3[[#This Row],[3º trim/2025]]+Tabela3[[#This Row],[4º trim/2025]] -> 0
B71: 70 | C71: 1 | E71: 2º Seminário Nacional sobre a Atuação da Assessoria Jurídica em Licitações e Contratos e suas Boas Práticas | AN71: Práticas | AW71: 515 | BB71: Curso fechado | BP71: =Tabela3[[#This Row],[1º trim/2025]]+Tabela3[[#This Row],[2º trim/2025]]+Tabela3[[#This Row],[3º trim/2025]]+Tabela3[[#This Row],[4º trim/2025]] -> 0
B72: 71 | C72: 1 | E72: 30A/18CM - FRANCISCO BELTRÃO | AF72: MEDIAÇÃO | AI72: 30A/18CM - FRANCISCO BELTRÃO | AN72: Francisco Beltrão | AW72: 234 | BB72: Curso fechado | BP72: =Tabela3[[#This Row],[1º trim/2025]]+Tabela3[[#This Row],[2º trim/2025]]+Tabela3[[#This Row],[3º trim/2025]]+Tabela3[[#This Row],[4º trim/2025]] -> 0
B73: 72 | C73: 1 | E73: 31A/18CM - CEJUSC 2º GRAU | AF73: MEDIAÇÃO | AI73: 31A/18CM - CEJUSC 2º GRAU | AN73: CEJUSC 2º GRAU | AW73: 248 | BB73: Curso fechado | BP73: =Tabela3[[#This Row],[1º trim/2025]]+Tabela3[[#This Row],[2º trim/2025]]+Tabela3[[#This Row],[3º trim/2025]]+Tabela3[[#This Row],[4º trim/2025]] -> 0
B74: 73 | C74: 1 | E74: 31B/18CM - CEJUSC 2º GRAU | AF74: MEDIAÇÃO | AI74: 31B/18CM - CEJUSC 2º GRAU | AN74: CEJUSC 2º GRAU | AW74: 249 | BB74: Curso fechado | BP74: =Tabela3[[#This Row],[1º trim/2025]]+Tabela3[[#This Row],[2º trim/2025]]+Tabela3[[#This Row],[3º trim/2025]]+Tabela3[[#This Row],[4º trim/2025]] -> 0
B75: 74 | C75: 1 | E75: 32A/18CM - REALEZA | AF75: MEDIAÇÃO | AI75: 32A/18CM - REALEZA | AN75: REALEZA | AW75: 242 | BB75: Curso fechado | BP75: =Tabela3[[#This Row],[1º trim/2025]]+Tabela3[[#This Row],[2º trim/2025]]+Tabela3[[#This Row],[3º trim/2025]]+Tabela3[[#This Row],[4º trim/2025]] -> 0
B76: 75 | C76: 1 | E76: 33A/18CM - IRATI | AF76: MEDIAÇÃO | AI76: 33A/18CM - IRATI | AN76: IRATI | AW76: 250 | BB76: Curso fechado | BP76: =Tabela3[[#This Row],[1º trim/2025]]+Tabela3[[#This Row],[2º trim/2025]]+Tabela3[[#This Row],[3º trim/2025]]+Tabela3[[#This Row],[4º trim/2025]] -> 0
B77: 76 | C77: 1 | E77: 33B/18CM - IRATI | AF77: MEDIAÇÃO | AI77: 33B/18CM - IRATI | AN77: IRATI | AW77: 251 | BB77: Curso fechado | BP77: =Tabela3[[#This Row],[1º trim/2025]]+Tabela3[[#This Row],[2º trim/2025]]+Tabela3[[#This Row],[3º trim/2025]]+Tabela3[[#This Row],[4º trim/2025]] -> 0
B78: 77 | C78: 1 | E78: 34A/18CM - MARINGÁ | AF78: MEDIAÇÃO | AI78: 34A/18CM - MARINGÁ | AN78: Maringá | AW78: 257 | BB78: Curso fechado | BP78: =Tabela3[[#This Row],[1º trim/2025]]+Tabela3[[#This Row],[2º trim/2025]]+Tabela3[[#This Row],[3º trim/2025]]+Tabela3[[#This Row],[4º trim/2025]] -> 0
B79: 78 | C79: 1 | E79: 34B/18CM - MARINGÁ | AF79: MEDIAÇÃO | AI79: 34B/18CM - MARINGÁ | AN79: Maringá | AW79: 256 | BB79: Curso fechado | BP79: =Tabela3[[#This Row],[1º trim/2025]]+Tabela3[[#This Row],[2º trim/2025]]+Tabela3[[#This Row],[3º trim/2025]]+Tabela3[[#This Row],[4º trim/2025]] -> 0
B80: 79 | C80: 1 | E80: 35A/18CM - PONTA GROSSA | AF80: MEDIAÇÃO | AI80: 35A/18CM - PONTA GROSSA | AN80: PONTA GROSSA | AW80: 253 | BB80: Curso fechado | BP80: =Tabela3[[#This Row],[1º trim/2025]]+Tabela3[[#This Row],[2º trim/2025]]+Tabela3[[#This Row],[3º trim/2025]]+Tabela3[[#This Row],[4º trim/2025]] -> 0
B81: 80 | C81: 1 | E81: 35B/18CM - PONTA GROSSA | AF81: MEDIAÇÃO | AI81: 35B/18CM - PONTA GROSSA | AN81: PONTA GROSSA | AW81: 254 | BB81: Curso fechado | BP81: =Tabela3[[#This Row],[1º trim/2025]]+Tabela3[[#This Row],[2º trim/2025]]+Tabela3[[#This Row],[3º trim/2025]]+Tabela3[[#This Row],[4º trim/2025]] -> 0
B82: 81 | C82: 1 | E82: 35C/18CM - PONTA GROSSA | AF82: MEDIAÇÃO | AI82: 35C/18CM - PONTA GROSSA | AN82: PONTA GROSSA | AW82: 255 | BB82: Curso fechado | BP82: =Tabela3[[#This Row],[1º trim/2025]]+Tabela3[[#This Row],[2º trim/2025]]+Tabela3[[#This Row],[3º trim/2025]]+Tabela3[[#This Row],[4º trim/2025]] -> 0
B83: 82 | C83: 1 | E83: 36A/18CM - CURITIBA | AF83: MEDIAÇÃO | AI83: 36A/18CM - CURITIBA | AN83: CURITIBA | AW83: 271 | BB83: Curso fechado | BP83: =Tabela3[[#This Row],[1º trim/2025]]+Tabela3[[#This Row],[2º trim/2025]]+Tabela3[[#This Row],[3º trim/2025]]+Tabela3[[#This Row],[4º trim/2025]] -> 0
... B133: 132 | C133: 1 | E133: 9B/17CM - COLORADO | AF133: MEDIAÇÃO | AI133: 9B/17CM - COLORADO | AN133: COLORADO | AW133: 106 | BB133: Curso fechado | BP133: =Tabela3[[#This Row],[1º trim/2025]]+Tabela3[[#This Row],[2º trim/2025]]+Tabela3[[#This Row],[3º trim/2025]]+Tabela3[[#This Row],[4º trim/2025]] -> 0
B134: 133 | C134: 1 | E134: A atuação dos Juízes Leigos | AW134: 727 | BB134: Curso fechado | BP134: =Tabela3[[#This Row],[1º trim/2025]]+Tabela3[[#This Row],[2º trim/2025]]+Tabela3[[#This Row],[3º trim/2025]]+Tabela3[[#This Row],[4º trim/2025]] -> 0
B135: 134 | C135: 1 | E135: A Resolução de Conflitos na Era Digital | AW135: 886 | BB135: Curso fechado | BP135: =Tabela3[[#This Row],[1º trim/2025]]+Tabela3[[#This Row],[2º trim/2025]]+Tabela3[[#This Row],[3º trim/2025]]+Tabela3[[#This Row],[4º trim/2025]] -> 0
B136: 135 | C136: 1 | E136: Administração Judiciária | AW136: 44 | BB136: Curso fechado | BP136: =Tabela3[[#This Row],[1º trim/2025]]+Tabela3[[#This Row],[2º trim/2025]]+Tabela3[[#This Row],[3º trim/2025]]+Tabela3[[#This Row],[4º trim/2025]] -> 0
B137: 136 | C137: 1 | E137: Ambiente Virtual de Aprendizagem - Mobile | AW137: 465 | BB137: Curso fechado | BP137: =Tabela3[[#This Row],[1º trim/2025]]+Tabela3[[#This Row],[2º trim/2025]]+Tabela3[[#This Row],[3º trim/2025]]+Tabela3[[#This Row],[4º trim/2025]] -> 0
B138: 137 | C138: 1 | E138: Apontamentos sobre o Programa Nacional de Prevenção à Corrupção no TJPR | AW138: 764 | BB138: Curso fechado | BP138: =Tabela3[[#This Row],[1º trim/2025]]+Tabela3[[#This Row],[2º trim/2025]]+Tabela3[[#This Row],[3º trim/2025]]+Tabela3[[#This Row],[4º trim/2025]] -> 0
B139: 138 | C139: 1 | E139: Arquivos | AW139: 445 | BB139: Curso fechado | BP139: =Tabela3[[#This Row],[1º trim/2025]]+Tabela3[[#This Row],[2º trim/2025]]+Tabela3[[#This Row],[3º trim/2025]]+Tabela3[[#This Row],[4º trim/2025]] -> 0
B140: 139 | C140: 1 | E140: As novas regras previdenciárias | AW140: 470 | BB140: Curso fechado | BP140: =Tabela3[[#This Row],[1º trim/2025]]+Tabela3[[#This Row],[2º trim/2025]]+Tabela3[[#This Row],[3º trim/2025]]+Tabela3[[#This Row],[4º trim/2025]] -> 0
B141: 140 | C141: 1 | E141: Atendimento ao público para CNJ | AW141: 36 | BB141: Curso fechado | BP141: =Tabela3[[#This Row],[1º trim/2025]]+Tabela3[[#This Row],[2º trim/2025]]+Tabela3[[#This Row],[3º trim/2025]]+Tabela3[[#This Row],[4º trim/2025]] -> 0
B142: 141 | C142: 1 | E142: Atuação dos estagiários junto ao TJPR - Turma 31jul2019 | AO142: 2019 | AP142: 43677 | AW142: 354 | BB142: Curso fechado | BP142: =Tabela3[[#This Row],[1º trim/2025]]+Tabela3[[#This Row],[2º trim/2025]]+Tabela3[[#This Row],[3º trim/2025]]+Tabela3[[#This Row],[4º trim/2025]] -> 0
B143: 142 | C143: 1 | E143: Atualização em custas processuais de 1º grau de jurisdição | AW143: 395 | BB143: Curso fechado | BP143: =Tabela3[[#This Row],[1º trim/2025]]+Tabela3[[#This Row],[2º trim/2025]]+Tabela3[[#This Row],[3º trim/2025]]+Tabela3[[#This Row],[4º trim/2025]] -> 0
B144: 143 | C144: 1 | E144: Atualização em Gramática da Língua Portuguesa | AW144: 549 | BB144: Curso fechado | BP144: =Tabela3[[#This Row],[1º trim/2025]]+Tabela3[[#This Row],[2º trim/2025]]+Tabela3[[#This Row],[3º trim/2025]]+Tabela3[[#This Row],[4º trim/2025]] -> 0
B145: 144 | C145: 1 | E145: Atualização em Gramática da Língua Portuguesa turma teste | AW145: 37 | BB145: Curso fechado | BP145: =Tabela3[[#This Row],[1º trim/2025]]+Tabela3[[#This Row],[2º trim/2025]]+Tabela3[[#This Row],[3º trim/2025]]+Tabela3[[#This Row],[4º trim/2025]] -> 0
B146: 145 | C146: 1 | E146: Atualização em Mediação Judicial | AF146: MEDIAÇÃO | AW146: 142 | BB146: Curso fechado | BP146: =Tabela3[[#This Row],[1º trim/2025]]+Tabela3[[#This Row],[2º trim/2025]]+Tabela3[[#This Row],[3º trim/2025]]+Tabela3[[#This Row],[4º trim/2025]] -> 0
B147: 146 | C147: 1 | E147: Br1gadistas - evacuação | AF147: BRIGADISTA | AW147: 319 | BB147: Curso fechado | BP147: =Tabela3[[#This Row],[1º trim/2025]]+Tabela3[[#This Row],[2º trim/2025]]+Tabela3[[#This Row],[3º trim/2025]]+Tabela3[[#This Row],[4º trim/2025]] -> 0
B148: 147 | C148: 1 | E148: Brigadista | AF148: BRIGADISTA | AW148: 393 | BB148: Curso fechado | BP148: =Tabela3[[#This Row],[1º trim/2025]]+Tabela3[[#This Row],[2º trim/2025]]+Tabela3[[#This Row],[3º trim/2025]]+Tabela3[[#This Row],[4º trim/2025]] -> 0
B149: 148 | C149: 1 | E149: Brigadista Prático | AF149: BRIGADISTA | AW149: 394 | BB149: Curso fechado | BP149: =Tabela3[[#This Row],[1º trim/2025]]+Tabela3[[#This Row],[2º trim/2025]]+Tabela3[[#This Row],[3º trim/2025]]+Tabela3[[#This Row],[4º trim/2025]] -> 0
B150: 149 | C150: 1 | E150: Brigadistas - Pitanga | AF150: BRIGADISTA | AN150: Pitanga | AW150: 329 | BB150: Curso fechado | BP150: =Tabela3[[#This Row],[1º trim/2025]]+Tabela3[[#This Row],[2º trim/2025]]+Tabela3[[#This Row],[3º trim/2025]]+Tabela3[[#This Row],[4º trim/2025]] -> 0
B151: 150 | C151: 1 | E151: Brigadistas - teórico | AF151: BRIGADISTA | AW151: 312 | BB151: Curso fechado | BP151: =Tabela3[[#This Row],[1º trim/2025]]+Tabela3[[#This Row],[2º trim/2025]]+Tabela3[[#This Row],[3º trim/2025]]+Tabela3[[#This Row],[4º trim/2025]] -> 0
B152: 151 | C152: 1 | E152: Capacitação em Precatórios | AW152: 308 | BB152: Curso fechado | BP152: =Tabela3[[#This Row],[1º trim/2025]]+Tabela3[[#This Row],[2º trim/2025]]+Tabela3[[#This Row],[3º trim/2025]]+Tabela3[[#This Row],[4º trim/2025]] -> 0
B153: 152 | C153: 1 | E153: Cartórios Distribuidores - Umuarama | AN153: Umuarama | AW153: 396 | BB153: Curso fechado | BP153: =Tabela3[[#This Row],[1º trim/2025]]+Tabela3[[#This Row],[2º trim/2025]]+Tabela3[[#This Row],[3º trim/2025]]+Tabela3[[#This Row],[4º trim/2025]] -> 0
B154: 153 | C154: 1 | E154: Comunicação Social, Judiciário, Gênero e Diversidade | AW154: 560 | BB154: Curso fechado | BP154: =Tabela3[[#This Row],[1º trim/2025]]+Tabela3[[#This Row],[2º trim/2025]]+Tabela3[[#This Row],[3º trim/2025]]+Tabela3[[#This Row],[4º trim/2025]] -> 0
B155: 154 | C155: 1 | E155: Conhecendo a Mediação | AF155: MEDIAÇÃO | AW155: 574 | BB155: Curso fechado | BP155: =Tabela3[[#This Row],[1º trim/2025]]+Tabela3[[#This Row],[2º trim/2025]]+Tabela3[[#This Row],[3º trim/2025]]+Tabela3[[#This Row],[4º trim/2025]] -> 0
B156: 155 | C156: 1 | E156: Conhecendo o Poder Judiciário e o Papel do CNJ | AW156: 200 | BB156: Curso fechado | BP156: =Tabela3[[#This Row],[1º trim/2025]]+Tabela3[[#This Row],[2º trim/2025]]+Tabela3[[#This Row],[3º trim/2025]]+Tabela3[[#This Row],[4º trim/2025]] -> 0
B157: 156 | C157: 1 | E157: Consciência Negra | H157: sim | AW157: 260 | BB157: Curso fechado | BP157: =Tabela3[[#This Row],[1º trim/2025]]+Tabela3[[#This Row],[2º trim/2025]]+Tabela3[[#This Row],[3º trim/2025]]+Tabela3[[#This Row],[4º trim/2025]] -> 0
B158: 157 | C158: 1 | E158: construção 1 | AW158: 760 | BB158: Curso fechado | BP158: =Tabela3[[#This Row],[1º trim/2025]]+Tabela3[[#This Row],[2º trim/2025]]+Tabela3[[#This Row],[3º trim/2025]]+Tabela3[[#This Row],[4º trim/2025]] -> 0
B159: 158 | C159: 1 | E159: Contratação de Bens e Serviços de Tecnologia da Informação e Comunicação – TIC copiar 1 | AW159: 514 | BB159: Curso fechado | BP159: =Tabela3[[#This Row],[1º trim/2025]]+Tabela3[[#This Row],[2º trim/2025]]+Tabela3[[#This Row],[3º trim/2025]]+Tabela3[[#This Row],[4º trim/2025]] -> 0
B160: 159 | C160: 1 | E160: Criando um Laboratório de Inovação no Judiciário | AW160: 381 | BB160: Curso fechado | BP160: =Tabela3[[#This Row],[1º trim/2025]]+Tabela3[[#This Row],[2º trim/2025]]+Tabela3[[#This Row],[3º trim/2025]]+Tabela3[[#This Row],[4º trim/2025]] -> 0
B161: 160 | C161: 1 | E161: Curso - Assédio no Ambiente de Trabalho Para Chefias | AW161: 290 | BB161: Curso fechado | BP161: =Tabela3[[#This Row],[1º trim/2025]]+Tabela3[[#This Row],[2º trim/2025]]+Tabela3[[#This Row],[3º trim/2025]]+Tabela3[[#This Row],[4º trim/2025]] -> 0
B162: 161 | C162: 1 | E162: Curso - Nivelamento dos Servidores do Poder Judiciário - Turma 2 | AI162: Turma 2 | AW162: 428 | BB162: Curso fechado | BP162: =Tabela3[[#This Row],[1º trim/2025]]+Tabela3[[#This Row],[2º trim/2025]]+Tabela3[[#This Row],[3º trim/2025]]+Tabela3[[#This Row],[4º trim/2025]] -> 0
B163: 162 | C163: 1 | E163: Curso de Admissibilidade Recursal por EAD | AW163: 562 | BB163: Curso fechado | BP163: =Tabela3[[#This Row],[1º trim/2025]]+Tabela3[[#This Row],[2º trim/2025]]+Tabela3[[#This Row],[3º trim/2025]]+Tabela3[[#This Row],[4º trim/2025]] -> 0
B164: 163 | C164: 1 | E164: CURSO DE FORMAÇÃO BÁSICA PARA TERCEIROS FACILITADORES 0001/2017 | I164: SIM | AF164: JUSTIÇA RESTAURATIVA | AI164: 0001/2017 | AN164: FACILITADORES 0001/2017 | AW164: 68 | BB164: Curso fechado | BP164: =Tabela3[[#This Row],[1º trim/2025]]+Tabela3[[#This Row],[2º trim/2025]]+Tabela3[[#This Row],[3º trim/2025]]+Tabela3[[#This Row],[4º trim/2025]] -> 0
B165: 164 | C165: 1 | E165: CURSO DE FORMAÇÃO EM DEPOIMENTO ESPECIAL COM O PROTOCOLO BRASILEIRO DE ENTREVISTA FORENSE | H165: Depoimento especial | AF165: Depoimento especial | AN165: FORENSE | AW165: 565 | BB165: Curso fechado | BP165: =Tabela3[[#This Row],[1º trim/2025]]+Tabela3[[#This Row],[2º trim/2025]]+Tabela3[[#This Row],[3º trim/2025]]+Tabela3[[#This Row],[4º trim/2025]] -> 0
B166: 165 | C166: 1 | E166: CURSO DE INSTRUTORES EM JUSTIÇA RESTAURATIVA 28 e 29 SET de 2017 | I166: SIM | AF166: JUSTIÇA RESTAURATIVA | AO166: 2017 | AP166: 42996 | AQ166: 43007 | AW166: 85 | BB166: Curso fechado | BP166: =Tabela3[[#This Row],[1º trim/2025]]+Tabela3[[#This Row],[2º trim/2025]]+Tabela3[[#This Row],[3º trim/2025]]+Tabela3[[#This Row],[4º trim/2025]] -> 0
B167: 166 | C167: 1 | E167: Curso de Justiça Restaurativa - Maringá - 24 a 27 de abril de 2018 | I167: SIM | AF167: JUSTIÇA RESTAURATIVA | AN167: Maringá | AO167: 2018 | AP167: 43214 | AQ167: 43217 | AW167: 158 | BB167: Curso fechado | BP167: =Tabela3[[#This Row],[1º trim/2025]]+Tabela3[[#This Row],[2º trim/2025]]+Tabela3[[#This Row],[3º trim/2025]]+Tabela3[[#This Row],[4º trim/2025]] -> 0
B168: 167 | C168: 1 | E168: Curso de Mediação Judicial | AF168: MEDIAÇÃO | AW168: 51 | BB168: Curso fechado | BP168: =Tabela3[[#This Row],[1º trim/2025]]+Tabela3[[#This Row],[2º trim/2025]]+Tabela3[[#This Row],[3º trim/2025]]+Tabela3[[#This Row],[4º trim/2025]] -> 0
B169: 168 | C169: 1 | E169: Curso de Mediação Judicial NUPEMEC/CNJ/2016 | AF169: MEDIAÇÃO | AW169: 53 | BB169: Curso fechado | BP169: =Tabela3[[#This Row],[1º trim/2025]]+Tabela3[[#This Row],[2º trim/2025]]+Tabela3[[#This Row],[3º trim/2025]]+Tabela3[[#This Row],[4º trim/2025]] -> 0
B170: 169 | C170: 1 | E170: Curso de teste - Solange | AW170: 733 | BB170: Curso fechado | BP170: =Tabela3[[#This Row],[1º trim/2025]]+Tabela3[[#This Row],[2º trim/2025]]+Tabela3[[#This Row],[3º trim/2025]]+Tabela3[[#This Row],[4º trim/2025]] -> 0
B171: 170 | C171: 1 | E171: Curso Justiça Restaurativa - Campo Mourão - 12 a 15 SET de 2017 | I171: SIM | AF171: JUSTIÇA RESTAURATIVA | AN171: CAMPO MOURÃO | AO171: 2017 | AP171: 12 a 15 SET de 2017 | AW171: 84 | BB171: Curso fechado | BP171: =Tabela3[[#This Row],[1º trim/2025]]+Tabela3[[#This Row],[2º trim/2025]]+Tabela3[[#This Row],[3º trim/2025]]+Tabela3[[#This Row],[4º trim/2025]] -> 0
B172: 171 | C172: 1 | E172: Curso Justiça Restaurativa - DEASE Curitiba - 16 e 17 Nov de 2017 | I172: SIM | AF172: JUSTIÇA RESTAURATIVA | AN172: CURITIBA | AO172: 2017 | AP172: 16 e 17 Nov de 2017 | AW172: 116 | BB172: Curso fechado | BP172: =Tabela3[[#This Row],[1º trim/2025]]+Tabela3[[#This Row],[2º trim/2025]]+Tabela3[[#This Row],[3º trim/2025]]+Tabela3[[#This Row],[4º trim/2025]] -> 0
B173: 172 | C173: 1 | E173: Curso Justiça Restaurativa - DEASE Londrina - 31 de Out e 01 de Nov de 2017 | I173: SIM | AF173: JUSTIÇA RESTAURATIVA | AN173: Londrina | AO173: 2017 | AP173: 31 de Out e 01 de Nov de 2017 | AW173: 115 | BB173: Curso fechado | BP173: =Tabela3[[#This Row],[1º trim/2025]]+Tabela3[[#This Row],[2º trim/2025]]+Tabela3[[#This Row],[3º trim/2025]]+Tabela3[[#This Row],[4º trim/2025]] -> 0
B174: 173 | C174: 1 | E174: Curso Justiça Restaurativa - DEASE Toledo - 26 a 27 de Out de 2017 | I174: SIM | AF174: JUSTIÇA RESTAURATIVA | AN174: TOLEDO | AO174: 2017 | AP174: 26 a 27 de Out de 2017 | AW174: 114 | BB174: Curso fechado | BP174: =Tabela3[[#This Row],[1º trim/2025]]+Tabela3[[#This Row],[2º trim/2025]]+Tabela3[[#This Row],[3º trim/2025]]+Tabela3[[#This Row],[4º trim/2025]] -> 0
B175: 174 | C175: 1 | E175: Curso Justiça Restaurativa - LON - Agosto 2017 | I175: SIM | AF175: JUSTIÇA RESTAURATIVA | AN175: Londrina | AO175: 2017 | AP175: 42948 | AW175: 80 | BB175: Curso fechado | BP175: =Tabela3[[#This Row],[1º trim/2025]]+Tabela3[[#This Row],[2º trim/2025]]+Tabela3[[#This Row],[3º trim/2025]]+Tabela3[[#This Row],[4º trim/2025]] -> 0
B176: 175 | C176: 1 | E176: Curso Justiça Restaurativa - Londrina 24 a 27 Out de 2017 | I176: SIM | AF176: JUSTIÇA RESTAURATIVA | AN176: Londrina | AO176: 2017 | AP176: 24 a 27 Out de 2017 | AW176: 113 | BB176: Curso fechado | BP176: =Tabela3[[#This Row],[1º trim/2025]]+Tabela3[[#This Row],[2º trim/2025]]+Tabela3[[#This Row],[3º trim/2025]]+Tabela3[[#This Row],[4º trim/2025]] -> 0
B177: 176 | C177: 1 | E177: Curso Justiça Restaurativa CTBA - agosto 2017 | I177: SIM | AF177: JUSTIÇA RESTAURATIVA | AN177: CURITIBA | AO177: 2017 | AP177: agosto | AW177: 76 | BB177: Curso fechado | BP177: =Tabela3[[#This Row],[1º trim/2025]]+Tabela3[[#This Row],[2º trim/2025]]+Tabela3[[#This Row],[3º trim/2025]]+Tabela3[[#This Row],[4º trim/2025]] -> 0
B178: 177 | C178: 1 | E178: Curso Justiça Restaurativa CTBA - junho 2017 | I178: SIM | AF178: JUSTIÇA RESTAURATIVA | AN178: CURITIBA | AO178: 2017 | AP178: junho | AW178: 69 | BB178: Curso fechado | BP178: =Tabela3[[#This Row],[1º trim/2025]]+Tabela3[[#This Row],[2º trim/2025]]+Tabela3[[#This Row],[3º trim/2025]]+Tabela3[[#This Row],[4º trim/2025]] -> 0
B179: 178 | C179: 1 | E179: Curso Justiça Restaurativa MGA - junho 2017 | I179: SIM | AF179: JUSTIÇA RESTAURATIVA | AN179: Maringá | AO179: 2017 | AP179: junho | AW179: 70 | BB179: Curso fechado | BP179: =Tabela3[[#This Row],[1º trim/2025]]+Tabela3[[#This Row],[2º trim/2025]]+Tabela3[[#This Row],[3º trim/2025]]+Tabela3[[#This Row],[4º trim/2025]] -> 0
B180: 179 | C180: 1 | E180: Curso Justiça Restaurativa PG - 02 a 05 OUT de 2017 | I180: SIM | AF180: JUSTIÇA RESTAURATIVA | AN180: PONTA GROSSA | AO180: 2017 | AP180: 02 a 05 OUT de 2017 | AW180: 98 | BB180: Curso fechado | BP180: =Tabela3[[#This Row],[1º trim/2025]]+Tabela3[[#This Row],[2º trim/2025]]+Tabela3[[#This Row],[3º trim/2025]]+Tabela3[[#This Row],[4º trim/2025]] -> 0
B181: 180 | C181: 1 | E181: Curso Práticas de Restaurativas - Curitiba - março de 2017 | I181: SIM | AF181: JUSTIÇA RESTAURATIVA | AN181: CURITIBA | AO181: 2017 | AP181: março de 2017 | AW181: 60 | BB181: Curso fechado | BP181: =Tabela3[[#This Row],[1º trim/2025]]+Tabela3[[#This Row],[2º trim/2025]]+Tabela3[[#This Row],[3º trim/2025]]+Tabela3[[#This Row],[4º trim/2025]] -> 0
B182: 181 | C182: 1 | E182: Curso Práticas Restaurativas - Curitiba - abril de 2017 | I182: SIM | AF182: JUSTIÇA RESTAURATIVA | AN182: CURITIBA | AO182: 2017 | AP182: abril de 2017 | AW182: 65 | BB182: Curso fechado | BP182: =Tabela3[[#This Row],[1º trim/2025]]+Tabela3[[#This Row],[2º trim/2025]]+Tabela3[[#This Row],[3º trim/2025]]+Tabela3[[#This Row],[4º trim/2025]] -> 0
B183: 182 | C183: 1 | E183: Curso Prático I - JR (TESTE - NÃO USAR) | AW183: 701 | BB183: Curso fechado | BP183: =Tabela3[[#This Row],[1º trim/2025]]+Tabela3[[#This Row],[2º trim/2025]]+Tabela3[[#This Row],[3º trim/2025]]+Tabela3[[#This Row],[4º trim/2025]] -> 0
B184: 183 | C184: 1 | E184: Curso TESTE | AW184: 716 | BB184: Curso fechado | BP184: =Tabela3[[#This Row],[1º trim/2025]]+Tabela3[[#This Row],[2º trim/2025]]+Tabela3[[#This Row],[3º trim/2025]]+Tabela3[[#This Row],[4º trim/2025]] -> 0
B185: 184 | C185: 1 | E185: delete-backup | AW185: 596 | BB185: Curso fechado | BP185: =Tabela3[[#This Row],[1º trim/2025]]+Tabela3[[#This Row],[2º trim/2025]]+Tabela3[[#This Row],[3º trim/2025]]+Tabela3[[#This Row],[4º trim/2025]] -> 0
B186: 185 | C186: 1 | E186: Depoimento Especial | H186: Depoimento especial | AF186: Depoimento especial | AW186: 62 | BB186: Curso fechado | BP186: =Tabela3[[#This Row],[1º trim/2025]]+Tabela3[[#This Row],[2º trim/2025]]+Tabela3[[#This Row],[3º trim/2025]]+Tabela3[[#This Row],[4º trim/2025]] -> 0
B187: 186 | C187: 1 | E187: Depoimento Especial | H187: Depoimento especial | AF187: Depoimento especial | AW187: 66 | BB187: Curso fechado | BP187: =Tabela3[[#This Row],[1º trim/2025]]+Tabela3[[#This Row],[2º trim/2025]]+Tabela3[[#This Row],[3º trim/2025]]+Tabela3[[#This Row],[4º trim/2025]] -> 0
B188: 187 | C188: 1 | E188: Depoimento Especial - 4ª Edição | H188: Depoimento especial | AF188: Depoimento especial | AI188: 4ª Edição | AW188: 414 | BB188: Curso fechado | BP188: =Tabela3[[#This Row],[1º trim/2025]]+Tabela3[[#This Row],[2º trim/2025]]+Tabela3[[#This Row],[3º trim/2025]]+Tabela3[[#This Row],[4º trim/2025]] -> 0
...

Sheet autoistrucionais
B1: MODALIDADE | C1: ID DA PLANILHA | D1: ANO | E1: SEI | F1: NOME DO Curso | G1: ID | H1: LINK AVA/ANDAMENTO DO CERTIFICADO | I1: STATUS
B2: =VLOOKUP("autoinstrucional",controle_matriz!A:A,0,FALSE) -> #VALUE! | C2: 422 | D2: 2019 | E2: 0034789-85.2019.8.16.6000 | F2: Proservidor - Agentes Delegados - SDP | G2: 620 | H2: https://ead.tjpr.jus.br/course/view.php?id=620
B3: =VLOOKUP("autoinstrucional",controle_matriz!A:A,0,FALSE) -> #VALUE! | C3: 432 | D3: 2019 | E3: 0062050-25.2019.8.16.6000 | F3: Nivelamento dos Servidores do Poder Judiciário | G3: 355 | H3: https://ead.tjpr.jus.br/course/view.php?id=355
A4: {=_xlfn._xlws.FILTER(controle_matriz!A:A,controle_matriz!A:A="autoistrucional","")} | B4: =VLOOKUP("autoinstrucional",controle_matriz!A:A,0,FALSE) -> #VALUE! | C4: 439 | D4: 2019 | E4: 0082087-73.2019.8.16.6000 | F4: Crase | G4: 378 | H4: https://ead.tjpr.jus.br/course/view.php?id=378
A5: {=_xlfn._xlws.FILTER(controle_matriz!A:A,controle_matriz!A:A="autoistrucional","")} | B5: =VLOOKUP("autoinstrucional",controle_matriz!A:A,0,FALSE) -> #VALUE! | C5: 451 | D5: 2020 | E5: 0009727-09.2020.8.16.6000 | F5: Habilidades sociais no trabalho | G5: 429 | H5: https://ead.tjpr.jus.br/course/view.php?id=429
A6: {=_xlfn._xlws.FILTER(controle_matriz!A:A,controle_matriz!A:A="autoistrucional","")} | B6: =VLOOKUP("autoinstrucional",controle_matriz!A:A,0,FALSE) -> #VALUE! | C6: 453 | D6: 2020 | E6: 0011322-43.2020.8.16.6000 | F6: Proservidor - Cartório Distribuidor | G6: 384 | H6: https://ead.tjpr.jus.br/course/view.php?id=384
A7: {=_xlfn._xlws.FILTER(controle_matriz!A:A,controle_matriz!A:A="autoistrucional","")} | B7: =VLOOKUP("autoinstrucional",controle_matriz!A:A,0,FALSE) -> #VALUE! | C7: 463 | D7: 2020 | E7: 0030036-51.2020.8.16.6000 | F7: Tríade da Felicidade | G7: 492 | H7: https://ead.tjpr.jus.br/course/view.php?id=492
A8: {=_xlfn._xlws.FILTER(controle_matriz!A:A,controle_matriz!A:A="autoistrucional","")} | B8: =VLOOKUP("autoinstrucional",controle_matriz!A:A,0,FALSE) -> #VALUE! | C8: 464 | D8: 2020 | E8: 0033257-81.2016.8.16.6000 | F8: Nome Social - Identidade, Reconhecimento e Memória | G8: 417 | H8: https://ead.tjpr.jus.br/course/view.php?id=417
A9: {=_xlfn._xlws.FILTER(controle_matriz!A:A,controle_matriz!A:A="autoistrucional","")} | B9: =VLOOKUP("autoinstrucional",controle_matriz!A:A,0,FALSE) -> #VALUE! | C9: 477 | D9: 2020 | E9: 0060521-68.2019.8.16.6000 | F9: Sistema Eletrônico de Execução Unificado- SEEU | G9: 409 | H9: https://ead.tjpr.jus.br/course/view.php?id=409
A10: {=_xlfn._xlws.FILTER(controle_matriz!A:A,controle_matriz!A:A="autoistrucional","")} | B10: =VLOOKUP("autoinstrucional",controle_matriz!A:A,0,FALSE) -> #VALUE! | C10: 481 | D10: 2020 | E10: 0074115-23.2017.8.16.6000 | F10: Calculadora Judicial Agnesi | G10: 528 | H10: https://ead.tjpr.jus.br/course/view.php?id=528
A11: {=_xlfn._xlws.FILTER(controle_matriz!A:A,controle_matriz!A:A="autoistrucional","")} | B11: =VLOOKUP("autoinstrucional",controle_matriz!A:A,0,FALSE) -> #VALUE! | C11: 501 | D11: 2021 | E11: 0003414-32.2020.8.16.6000 | F11: Teletrabalho - 3ª Edição | G11: 655 | H11: https://ead.tjpr.jus.br/course/view.php?id=655
A12: {=_xlfn._xlws.FILTER(controle_matriz!A:A,controle_matriz!A:A="autoistrucional","")} | B12: =VLOOKUP("autoinstrucional",controle_matriz!A:A,0,FALSE) -> #VALUE! | C12: 502 | D12: 2021 | E12: 0003689-78.2020.8.16.6000 | F12: Regras Práticas da Nova Ortografia - 5ª edição | G12: 426
A13: {=_xlfn._xlws.FILTER(controle_matriz!A:A,controle_matriz!A:A="autoistrucional","")} | B13: =VLOOKUP("autoinstrucional",controle_matriz!A:A,0,FALSE) -> #VALUE! | C13: 615 | D13: 2021 | E13: 0003706-17.2020.8.16.6000 | F13: SEI - Sistema Eletrônico de Informações | G13: 427 | H13: https://ead.tjpr.jus.br/course/view.php?id=427
A14: {=_xlfn._xlws.FILTER(controle_matriz!A:A,controle_matriz!A:A="autoistrucional","")} | B14: =VLOOKUP("autoinstrucional",controle_matriz!A:A,0,FALSE) -> #VALUE! | C14: 507 | D14: 2021 | E14: 0013203-89.2019.8.16.6000 | F14: Precatório e Requisição de Pequeno Valor | G14: 585 | H14: https://ead.tjpr.jus.br/course/view.php?id=585
A15: {=_xlfn._xlws.FILTER(controle_matriz!A:A,controle_matriz!A:A="autoistrucional","")} | B15: =VLOOKUP("autoinstrucional",controle_matriz!A:A,0,FALSE) -> #VALUE! | C15: 509 | D15: 2021 | E15: 0014757-88.2021.8.16.6000 | F15: Formação de Gestores Liderança, Gestão e Indicadores de Desempenho | G15: 532 | H15: https://ead.tjpr.jus.br/course/view.php?id=532
A16: {=_xlfn._xlws.FILTER(controle_matriz!A:A,controle_matriz!A:A="autoistrucional","")} | B16: =VLOOKUP("autoinstrucional",controle_matriz!A:A,0,FALSE) -> #VALUE! | C16: 511 | D16: 2021 | E16: 0015797-03.2024.8.16.6000 | F16: Gestão Documental no Poder Judiciário | G16: 376 | H16: https://ead.tjpr.jus.br/course/view.php?id=376
A17: {=_xlfn._xlws.FILTER(controle_matriz!A:A,controle_matriz!A:A="autoistrucional","")} | B17: =VLOOKUP("autoinstrucional",controle_matriz!A:A,0,FALSE) -> #VALUE! | C17: 515 | D17: 2021 | E17: 0023891-76.2020.8.16.6000 | F17: Fundo Rotativo | G17: 297 | H17: https://ead.tjpr.jus.br/course/view.php?id=297
A18: {=_xlfn._xlws.FILTER(controle_matriz!A:A,controle_matriz!A:A="autoistrucional","")} | B18: =VLOOKUP("autoinstrucional",controle_matriz!A:A,0,FALSE) -> #VALUE! | C18: 545 | D18: 2021 | E18: 0064934-61.2018.8.16.6000 | F18: Acessibilidade e Inclusão no TJPR | G18: 617 | H18: https://ead.tjpr.jus.br/course/view.php?id=617
A19: {=_xlfn._xlws.FILTER(controle_matriz!A:A,controle_matriz!A:A="autoistrucional","")} | B19: =VLOOKUP("autoinstrucional",controle_matriz!A:A,0,FALSE) -> #VALUE! | C19: 546 | D19: 2021 | E19: 0064934-61.2018.8.16.6000 | F19: Conhecendo o Poder Judiciário | G19: 533 | H19: https://ead.tjpr.jus.br/course/view.php?id=533
A20: {=_xlfn._xlws.FILTER(controle_matriz!A:A,controle_matriz!A:A="autoistrucional","")} | B20: =VLOOKUP("autoinstrucional",controle_matriz!A:A,0,FALSE) -> #VALUE! | C20: 547 | D20: 2021 | E20: 0064934-61.2018.8.16.6000 | F20: Gestão por Competências | G20: 487 | H20: https://ead.tjpr.jus.br/course/view.php?id=487
A21: {=_xlfn._xlws.FILTER(controle_matriz!A:A,controle_matriz!A:A="autoistrucional","")} | B21: =VLOOKUP("autoinstrucional",controle_matriz!A:A,0,FALSE) -> #VALUE! | C21: 552 | D21: 2021 | E21: 0072085-73.2021.8.16.6000 | F21: A Violência Doméstica, suas relações com ações cíveis em matéria de família e o atendimento humanizado | G21: 665 e 545 | H21: https://ead.tjpr.jus.br/course/view.php?id=665
A22: {=_xlfn._xlws.FILTER(controle_matriz!A:A,controle_matriz!A:A="autoistrucional","")} | B22: =VLOOKUP("autoinstrucional",controle_matriz!A:A,0,FALSE) -> #VALUE! | C22: 563 | D22: 2021 | E22: 0080451-38.2020.8.16.6000 | F22: Lei de Introdução às Normas do Direito Brasileiro | G22: 521 | H22: https://ead.tjpr.jus.br/course/view.php?id=521
A23: {=_xlfn._xlws.FILTER(controle_matriz!A:A,controle_matriz!A:A="autoistrucional","")} | B23: =VLOOKUP("autoinstrucional",controle_matriz!A:A,0,FALSE) -> #VALUE! | C23: 578 | D23: 2021 | E23: 0092653-13.2021.8.16.6000 | F23: Avaliação de Imóveis para Oficiais de Justiça e Cumpridores de Mandados | G23: 601 | H23: https://ead.tjpr.jus.br/course/view.php?id=601
A24: {=_xlfn._xlws.FILTER(controle_matriz!A:A,controle_matriz!A:A="autoistrucional","")} | B24: =VLOOKUP("autoinstrucional",controle_matriz!A:A,0,FALSE) -> #VALUE! | C24: 609 | D24: 2021 | E24: 0120406-76.2020.8.16.6000 | F24: Formação de novos professores da ginástica laboral | G24: 541 | H24: https://ead.tjpr.jus.br/course/view.php?id=541
A25: {=_xlfn._xlws.FILTER(controle_matriz!A:A,controle_matriz!A:A="autoistrucional","")} | B25: =VLOOKUP("autoinstrucional",controle_matriz!A:A,0,FALSE) -> #VALUE! | C25: 617 | D25: 2022 | E25: 0008308-85.2019.8.16.6000 | F25: Gestão de Precedentes | G25: 475 | H25: https://ead.tjpr.jus.br/course/view.php?id=475
A26: {=_xlfn._xlws.FILTER(controle_matriz!A:A,controle_matriz!A:A="autoistrucional","")} | B26: =VLOOKUP("autoinstrucional",controle_matriz!A:A,0,FALSE) -> #VALUE! | C26: 623 | D26: 2022 | E26: 0013762-41.2022.8.16.6000 | F26: Funções do Assistente da Direção de Fórum relacionadas ao Departamento de Gestão de Serviços Terceirizados | G26: 742 | H26: https://ead.tjpr.jus.br/course/view.php?id=742
A27: {=_xlfn._xlws.FILTER(controle_matriz!A:A,controle_matriz!A:A="autoistrucional","")} | B27: =VLOOKUP("autoinstrucional",controle_matriz!A:A,0,FALSE) -> #VALUE! | C27: 628 | D27: 2022 | E27: 0015995-11.2022.8.16.6000 | F27: Formação de secretários e secretárias das sessões de julgamento | G27: 690 | H27: https://ead.tjpr.jus.br/course/view.php?id=690
A28: {=_xlfn._xlws.FILTER(controle_matriz!A:A,controle_matriz!A:A="autoistrucional","")} | B28: =VLOOKUP("autoinstrucional",controle_matriz!A:A,0,FALSE) -> #VALUE! | C28: 663 | D28: 2022 | E28: 0026507-53.2022.8.16.6000 | F28: PROGRAMA JUSTIÇA 4.0 DPPJ - CNJ | G28: 715 | H28: https://ead.tjpr.jus.br/course/view.php?id=715
A29: {=_xlfn._xlws.FILTER(controle_matriz!A:A,controle_matriz!A:A="autoistrucional","")} | B29: =VLOOKUP("autoinstrucional",controle_matriz!A:A,0,FALSE) -> #VALUE! | C29: 665 | D29: 2022 | E29: 0031499-28.2020.8.16.6000 | F29: Proservidor - Unidade Cível | G29: 649 | H29: https://ead.tjpr.jus.br/course/view.php?id=649
A30: {=_xlfn._xlws.FILTER(controle_matriz!A:A,controle_matriz!A:A="autoistrucional","")} | B30: =VLOOKUP("autoinstrucional",controle_matriz!A:A,0,FALSE) -> #VALUE! | C30: 768 | D30: 2022 | E30: 0108225-09.2021.8.16.6000 | F30: Curso de Introdução à Justiça Restaurativa - Formação Teórica - 30h | G30: 693 | H30: https://ead.tjpr.jus.br/course/view.php?id=693
A31: {=_xlfn._xlws.FILTER(controle_matriz!A:A,controle_matriz!A:A="autoistrucional","")} | B31: =VLOOKUP("autoinstrucional",controle_matriz!A:A,0,FALSE) -> #VALUE! | C31: 772 | D31: 2022 | E31: 0111591-22.2022.8.16.6000 | F31: Curso teórico de Brigadistas | G31: 729 | H31: https://ead.tjpr.jus.br/course/view.php?id=729
A32: {=_xlfn._xlws.FILTER(controle_matriz!A:A,controle_matriz!A:A="autoistrucional","")} | B32: =VLOOKUP("autoinstrucional",controle_matriz!A:A,0,FALSE) -> #VALUE! | C32: 776 | D32: 2022 | E32: 0113724-37.2022.8.16.6000 | F32: Gestão de Conflitos | G32: 803 | H32: https://ead.tjpr.jus.br/course/view.php?id=803
A33: {=_xlfn._xlws.FILTER(controle_matriz!A:A,controle_matriz!A:A="autoistrucional","")} | B33: =VLOOKUP("autoinstrucional",controle_matriz!A:A,0,FALSE) -> #VALUE! | C33: 777 | D33: 2022 | E33: 0114783-94.2021.8.16.6000 | F33: Código de Ética e Conduta dos servidores e demais colaboradores do Poder Judiciário do Estado do Paraná | G33: 697 | H33: https://ead.tjpr.jus.br/course/view.php?id=697
... A40: {=_xlfn._xlws.FILTER(controle_matriz!A:A,controle_matriz!A:A="autoistrucional","")} | B40: =VLOOKUP("autoinstrucional",controle_matriz!A:A,0,FALSE) -> #VALUE! | C40: 987 | D40: 2024 | E40: 0013494-50.2023.8.16.6000 | F40: Unindo esforços contra a violência doméstica e familiar - Turma 2 | G40: 681 | H40: https://ead.tjpr.jus.br/course/view.php?id=681
A41: {=_xlfn._xlws.FILTER(controle_matriz!A:A,controle_matriz!A:A="autoistrucional","")} | B41: =VLOOKUP("autoinstrucional",controle_matriz!A:A,0,FALSE) -> #VALUE! | C41: 1028 | D41: 2024 | E41: 0040184-82.2024.8.16.6000 | F41: Gestão Aplicada às Unidades Judiciais (SEMPs) | G41: 1003
A42: {=_xlfn._xlws.FILTER(controle_matriz!A:A,controle_matriz!A:A="autoistrucional","")} | B42: =VLOOKUP("autoinstrucional",controle_matriz!A:A,0,FALSE) -> #VALUE! | C42: 1033 | D42: 2024 | E42: 0043367-95.2023.8.16.6000 | F42: CURSO DE APERFEIÇOAMENTO PARA SERVIDORES E SERVIDORAS E ASSESSORES E ASSESSORAS ATUANTES NA JURISDIÇÃO DA INFÂNCIA E JUVENTUDE | G42: 981 | H42: https://ead.tjpr.jus.br/course/view.php?id=981
A43: {=_xlfn._xlws.FILTER(controle_matriz!A:A,controle_matriz!A:A="autoistrucional","")} | B43: =VLOOKUP("autoinstrucional",controle_matriz!A:A,0,FALSE) -> #VALUE! | C43: 1056 | D43: 2024 | E43: 0061954-34.2024.8.16.6000 | F43: INTRODUÇÃO DOS PROFISSIONAIS DAS ÁREAS DE PSICOLOGIA E SERVIÇO SOCIAL NO ÂMBITO DO PODER JUDICIÁRIO DO PARANÁ NAS ÁREAS DE FAMÍLIA, INFÂNCIA E JUVENTUDE E VIOLÊNCIA DOMÉSTICA E FAMILIAR | G43: 978 | H43: https://ead.tjpr.jus.br/course/view.php?id=978
A44: {=_xlfn._xlws.FILTER(controle_matriz!A:A,controle_matriz!A:A="autoistrucional","")} | B44: =VLOOKUP("autoinstrucional",controle_matriz!A:A,0,FALSE) -> #VALUE! | C44: 1058 | D44: 2024 | E44: 0063696-31.2023.8.16.6000 | F44: Projudi digital: efetividade e produtividade | G44: 958 | H44: https://ead.tjpr.jus.br/course/view.php?id=958
A45: {=_xlfn._xlws.FILTER(controle_matriz!A:A,controle_matriz!A:A="autoistrucional","")} | B45: =VLOOKUP("autoinstrucional",controle_matriz!A:A,0,FALSE) -> #VALUE! | C45: 1364 | D45: 2024 | E45: 0080329-83.2024.8.16.6000 | F45: I Jornada CEVID Orienta – Conhecendo o Programa | G45: 975 | H45: https://ead.tjpr.jus.br/course/view.php?id=975
A46: {=_xlfn._xlws.FILTER(controle_matriz!A:A,controle_matriz!A:A="autoistrucional","")} | B46: =VLOOKUP("autoinstrucional",controle_matriz!A:A,0,FALSE) -> #VALUE! | C46: 1082 | D46: 2024 | E46: 0089071-34.2023.8.16.6000 | F46: Sistema Distribuidor do Paraná (SDP). | G46: 1030
A47: {=_xlfn._xlws.FILTER(controle_matriz!A:A,controle_matriz!A:A="autoistrucional","")} | B47: =VLOOKUP("autoinstrucional",controle_matriz!A:A,0,FALSE) -> #VALUE! | C47: 1351 | D47: 2024 | E47: 0092272-97.2024.8.16.6000 | F47: I Encontro de Instituições Facilitadoras de Grupos Reflexivos e Responsabilizantes para Autores de Violência Doméstica e Familiar da Cidade de Curitiba | G47: 990
A48: {=_xlfn._xlws.FILTER(controle_matriz!A:A,controle_matriz!A:A="autoistrucional","")} | B48: =VLOOKUP("autoinstrucional",controle_matriz!A:A,0,FALSE) -> #VALUE! | C48: 1365 | D48: 2024 | E48: 0093718-38.2024.8.16.6000 | F48: II Jornada CEVID Orienta – Segurança Institucional | G48: 992
A49: {=_xlfn._xlws.FILTER(controle_matriz!A:A,controle_matriz!A:A="autoistrucional","")} | B49: =VLOOKUP("autoinstrucional",controle_matriz!A:A,0,FALSE) -> #VALUE! | C49: 1098 | D49: 2024 | E49: 0098738-10.2024.8.16.6000 | F49: Curso Juízo de Admissibilidade de RE e RESP - Autoinstrucional | G49: 1029 | H49: https://ead.tjpr.jus.br/course/view.php?id=1029
A50: {=_xlfn._xlws.FILTER(controle_matriz!A:A,controle_matriz!A:A="autoistrucional","")} | B50: =VLOOKUP("autoinstrucional",controle_matriz!A:A,0,FALSE) -> #VALUE! | C50: 1114 | D50: 2024 | E50: 0122714-80.2023.8.16.6000 | F50: Treinamento em LGPD | G50: 1024
A51: {=_xlfn._xlws.FILTER(controle_matriz!A:A,controle_matriz!A:A="autoistrucional","")} | B51: =VLOOKUP("autoinstrucional",controle_matriz!A:A,0,FALSE) -> #VALUE! | C51: 1134 | D51: 2024 | E51: 0126785-28.2023.8.16.6000 | F51: curso Implementando Grupos Reflexivos para Homens Autores de Violência Doméstica | G51: 957 | H51: https://ead.tjpr.jus.br/course/view.php?id=957
A52: {=_xlfn._xlws.FILTER(controle_matriz!A:A,controle_matriz!A:A="autoistrucional","")} | B52: =VLOOKUP("autoinstrucional",controle_matriz!A:A,0,FALSE) -> #VALUE! | C52: 1158 | D52: 2024 | E52: 0137656-83.2024.8.16.6000 | F52: Curso de Capacitação para os(as) Servidores(as) que Participarão da Operação Litoral 2024/2025 | G52: 1049
A53: {=_xlfn._xlws.FILTER(controle_matriz!A:A,controle_matriz!A:A="autoistrucional","")} | B53: =VLOOKUP("autoinstrucional",controle_matriz!A:A,0,FALSE) -> #VALUE! | C53: 1379 | D53: 2024 | E53: 0141450-15.2024.8.16.6000 | F53: II ENCONTRO DE INSTITUIÇÕES FACILITADORAS DE GRUPOS REFLEXIVOS E RESPONSABILIZANTES PARA AUTORES DE VIOLÊNCIA DOMÉSTICA E FAMILIAR DA CIDADE DE CURITIBA | G53: 1050
A54: {=_xlfn._xlws.FILTER(controle_matriz!A:A,controle_matriz!A:A="autoistrucional","")} | B54: =VLOOKUP("autoinstrucional",controle_matriz!A:A,0,FALSE) -> #VALUE! | C54: 1181 | D54: 2024 | E54: 0154244-68.2024.8.16.6000 | F54: Lançamento do Copilot 365 | G54: 1039
A55: {=_xlfn._xlws.FILTER(controle_matriz!A:A,controle_matriz!A:A="autoistrucional","")} | B55: =VLOOKUP("autoinstrucional",controle_matriz!A:A,0,FALSE) -> #VALUE! | C55: 1335 | D55: 2024 | E55: 0158376-71.2024.8.16.6000 | F55: curso "Unindo esforços contra a violência doméstica e familiar" | G55: 681 | H55: https://ead.tjpr.jus.br/course/view.php?id=681
A56: {=_xlfn._xlws.FILTER(controle_matriz!A:A,controle_matriz!A:A="autoistrucional","")} | B56: =VLOOKUP("autoinstrucional",controle_matriz!A:A,0,FALSE) -> #VALUE! | C56: 1190 | D56: 2024 | E56: 0164470-35.2024.8.16.6000 | F56: Adoção da Ferramenta Copilot 365 - Como utilizar o Copilot no Word | G56: 1046
A57: {=_xlfn._xlws.FILTER(controle_matriz!A:A,controle_matriz!A:A="autoistrucional","")} | B57: =VLOOKUP("autoinstrucional",controle_matriz!A:A,0,FALSE) -> #VALUE! | C57: 1191 | D57: 2024 | E57: 0164691-18.2024.8.16.6000 | F57: Como utilizar o Copilot no Teams | G57: 1055
A58: {=_xlfn._xlws.FILTER(controle_matriz!A:A,controle_matriz!A:A="autoistrucional","")} | B58: =VLOOKUP("autoinstrucional",controle_matriz!A:A,0,FALSE) -> #VALUE! | C58: 1192 | D58: 2024 | E58: 0164692-03.2024.8.16.6000 | F58: Como utilizar o BizChat | G58: 1056
A59: {=_xlfn._xlws.FILTER(controle_matriz!A:A,controle_matriz!A:A="autoistrucional","")} | B59: =VLOOKUP("autoinstrucional",controle_matriz!A:A,0,FALSE) -> #VALUE! | C59: 1193 | D59: 2024 | E59: 0164693-85.2024.8.16.6000 | F59: Como utilizar o Copilot no Excel, Forms e Excel Avançado | G59: 1057
A60: {=_xlfn._xlws.FILTER(controle_matriz!A:A,controle_matriz!A:A="autoistrucional","")} | B60: =VLOOKUP("autoinstrucional",controle_matriz!A:A,0,FALSE) -> #VALUE! | C60: 1194 | D60: 2024 | E60: 0164694-70.2024.8.16.6000 | F60: Como utilizar o Copilot no Power Point, no One Note e no Outlook | G60: 1058
A61: {=_xlfn._xlws.FILTER(controle_matriz!A:A,controle_matriz!A:A="autoistrucional","")} | B61: =VLOOKUP("autoinstrucional",controle_matriz!A:A,0,FALSE) -> #VALUE! | C61: 1195 | D61: 2024 | E61: 0164695-55.2024.8.16.6000 | F61: Como utilizar o Copilot Pages | G61: 1059
A62: {=_xlfn._xlws.FILTER(controle_matriz!A:A,controle_matriz!A:A="autoistrucional","")} | B62: =VLOOKUP("autoinstrucional",controle_matriz!A:A,0,FALSE) -> #VALUE! | C62: 1196 | D62: 2024 | E62: 0164696-40.2024.8.16.6000 | F62: Como dominar a arte do prompt para Copilot | G62: 1060
A63: {=_xlfn._xlws.FILTER(controle_matriz!A:A,controle_matriz!A:A="autoistrucional","")} | B63: =VLOOKUP("autoinstrucional",controle_matriz!A:A,0,FALSE) -> #VALUE! | C63: 1253 | D63: 2025 | E63: 0008819-49.2020.8.16.6000 | F63: A atuação dos Juízes Leigos | G63: 963 | H63: ttps://ead.tjpr.jus.br/course/view.php?id=963
A64: {=_xlfn._xlws.FILTER(controle_matriz!A:A,controle_matriz!A:A="autoistrucional","")} | B64: =VLOOKUP("autoinstrucional",controle_matriz!A:A,0,FALSE) -> #VALUE! | C64: 1249 | E64: 0002297-98.2023.8.16.6000 | F64: manual de boas práticas quanto à implementação das medidas previstas nesta Resolução", determina-se o sobrestamento do presente expediente por 180 (cento e oitenta) dias até que seja publicado o Manual citado pelo CNJ | H64: ag disponibilização no ava | I64: ag disponibilização no ava
A65: {=_xlfn._xlws.FILTER(controle_matriz!A:A,controle_matriz!A:A="autoistrucional","")} | B65: =VLOOKUP("autoinstrucional",controle_matriz!A:A,0,FALSE) -> #VALUE! | C65: 1043 | E65: 0055466-63.2024.8.16.6000 | F65: LEI GERAL DE PROTEÇÃO DE DADOS - LGPD | H65: ag disponibilização no ava
A66: {=_xlfn._xlws.FILTER(controle_matriz!A:A,controle_matriz!A:A="autoistrucional","")} | B66: =VLOOKUP("autoinstrucional",controle_matriz!A:A,0,FALSE) -> #VALUE! | C66: 1062 | E66: 0070279-32.2023.8.16.6000 | F66: Elaboração de Ementas Jurisprudenciais - Procedimentos e Padronização | G66: 923 | I66: fazer
A67: {=_xlfn._xlws.FILTER(controle_matriz!A:A,controle_matriz!A:A="autoistrucional","")} | B67: =VLOOKUP("autoinstrucional",controle_matriz!A:A,0,FALSE) -> #VALUE! | C67: 1300 | E67: 0087665-75.2023.8.16.6000 | F67: ALFABETIZAÇÃO DE DADOS | H67: ag disponibilização no ava | I67: ag disponibilização no ava
A68: {=_xlfn._xlws.FILTER(controle_matriz!A:A,controle_matriz!A:A="autoistrucional","")} | B68: =VLOOKUP("autoinstrucional",controle_matriz!A:A,0,FALSE) -> #VALUE! | C68: 1115 | E68: 0123647-53.2023.8.16.6000 | F68: DESENVOLVIMENTO BASICO EM QLIK SENSE | G68: 921
A69: {=_xlfn._xlws.FILTER(controle_matriz!A:A,controle_matriz!A:A="autoistrucional","")} | B69: =VLOOKUP("autoinstrucional",controle_matriz!A:A,0,FALSE) -> #VALUE! | C69: 1147 | E69: 0131022-76.2021.8.16.6000 | F69: Governança no Setor Público e a sua aplicação no TJPR | H69: ag disponibilização no ava | I69: ag disponibilização no ava

Sheet Sandro-informação simplificada
A1: {=Tabela3[[#Headers],[MODALIDADE]:[NOME DO Curso]]} -> MODALIDADE | B1: ID DA PLANILHA | C1: ANO | D1: SEI | E1: NOME DO Curso | F1: NENHUMA CLASSIFICAÇÃO COPILOT | G1: Capacitação em Direitos Humanos, Gênero, Raça e Etnia; e em Depoimento Especial" - 0148945-13.2024.8.16.6000 | H1: Justiça Restaurativa - 0148919-15.2024.8.16.6000 | I1: Capacitação de Facilitadores 0148959-94.2024.8.16.6000 | J1: Acessibilidade e Inclusão - 0148938-21.2024.8.16.6000 | K1: Política de Prevenção e Enfrentamento do Assédio Moral, do Assédio Sexual e da Discriminação.0148908-83.2024.8.16.6000 | L1: SOCIOAMBIENTAL | M1: SUSTENTABILIDADE https://portal.tjpr.jus.br/portletforms/frm.do?idFormulario=7430 0017859-16.2024.8.16.6000 | N1: CURSO PARA MAGISTRADOS | O1: LIVRO DE REGISTRO | P1: DATA DO ULTIMO REGISTRO | Q1: REG DE INSTRUTORES2 | R1: REGISTRO DE INSTRUTORES NO SEI | S1: 2021 | T1: 2022 | U1: 2023 | V1: REGISTRO NO SEI/2024 | W1: 2024 | X1: REGISTRO NO SEI/2025 | Y1: TOTAL CERTIFICADOS EMITIDOS/2025 | Z1: 1º trim/2025 | AA1: 2º trim/2025 | AB1: 3º trim/2025 | AC1: 4º trim/2025
A2: =Tabela3[[#This Row],[MODALIDADE]] -> 0 | B2: =Tabela3[[#This Row],[ID DA PLANILHA]] -> 1 | C2: =Tabela3[[#This Row],[ANO]] -> 1 | D2: =Tabela3[[#This Row],[SEI]] -> 0 | E2: =Tabela3[[#This Row],[NOME DO Curso]] -> 1° Curso de Formação de Laboratorista | F2: =Tabela3[[#This Row],[NENHUMA CLASSIFICAÇÃO COPILOT]] -> 0 | G2: =Tabela3[[#This Row],[Capacitação em Direitos Humanos, Gênero, Raça e Etnia; e em Depoimento Especial" - 0148945-13.2024.8.16.6000]] -> 0 | H2: =Tabela3[[#This Row],[Justiça Restaurativa - 0148919-15.2024.8.16.6000]] -> 0 | I2: =Tabela3[[#This Row],[Capacitação de Facilitadores 0148959-94.2024.8.16.6000]] -> 0 | J2: =Tabela3[[#This Row],[Acessibilidade e Inclusão - 0148938-21.2024.8.16.6000]] -> 0 | K2: =Tabela3[[#This Row],[Política de Prevenção e Enfrentamento do Assédio Moral, do Assédio Sexual e da Discriminação.0148908-83.2024.8.16.6000]] -> 0 | L2: =Tabela3[[#This Row],[SOCIOAMBIENTAL]] -> 0 | M2: =Tabela3[[#This Row],[SUSTENTABILIDADE https://portal.tjpr.jus.br/portletforms/frm.do?idFormulario=7430 0017859-16.2024.8.16.6000]] -> 0 | N2: =Tabela3[[#This Row],[CURSO PARA MAGISTRADOS]] -> 0 | O2: =Tabela3[[#This Row],[LIVRO DE REGISTRO]] -> 0 | P2: =Tabela3[[#This Row],[DATA DO ULTIMO REGISTRO]] -> 0 | Q2: =Tabela3[[#This Row],[REG DE INSTRUTORES2]] -> 0 | R2: =Tabela3[[#This Row],[REGISTRO DE INSTRUTORES NO SEI]] -> 0 | S2: =Tabela3[[#This Row],[2021]] -> 0 | T2: =Tabela3[[#This Row],[2022]] -> 0 | U2: =Tabela3[[#This Row],[2023]] -> 0 | V2: =Tabela3[[#This Row],[REGISTRO NO SEI/2024]] -> 0 | W2: =Tabela3[[#This Row],[2024]] -> 0 | X2: =Tabela3[[#This Row],[REGISTRO NO SEI/2025]] -> 0 | Y2: =Tabela3[[#This Row],[TOTAL CERTIFICADOS EMITIDOS/2025]] -> 0 | Z2: =Tabela3[[#This Row],[1º trim/2025]] -> 0 | AA2: =Tabela3[[#This Row],[2º trim/2025]] -> 0 | AB2: =Tabela3[[#This Row],[3º trim/2025]] -> 0 | AC2: =Tabela3[[#This Row],[4º trim/2025]] -> 0
A3: =Tabela3[[#This Row],[MODALIDADE]] -> 0 | B3: =Tabela3[[#This Row],[ID DA PLANILHA]] -> 2 | C3: =Tabela3[[#This Row],[ANO]] -> 1 | D3: =Tabela3[[#This Row],[SEI]] -> 0 | E3: =Tabela3[[#This Row],[NOME DO Curso]] -> 10A/17CM - CURITIBA | F3: =Tabela3[[#This Row],[NENHUMA CLASSIFICAÇÃO COPILOT]] -> 0 | G3: =Tabela3[[#This Row],[Capacitação em Direitos Humanos, Gênero, Raça e Etnia; e em Depoimento Especial" - 0148945-13.2024.8.16.6000]] -> 0 | H3: =Tabela3[[#This Row],[Justiça Restaurativa - 0148919-15.2024.8.16.6000]] -> 0 | I3: =Tabela3[[#This Row],[Capacitação de Facilitadores 0148959-94.2024.8.16.6000]] -> 0 | J3: =Tabela3[[#This Row],[Acessibilidade e Inclusão - 0148938-21.2024.8.16.6000]] -> 0 | K3: =Tabela3[[#This Row],[Política de Prevenção e Enfrentamento do Assédio Moral, do Assédio Sexual e da Discriminação.0148908-83.2024.8.16.6000]] -> 0 | L3: =Tabela3[[#This Row],[SOCIOAMBIENTAL]] -> 0 | M3: =Tabela3[[#This Row],[SUSTENTABILIDADE https://portal.tjpr.jus.br/portletforms/frm.do?idFormulario=7430 0017859-16.2024.8.16.6000]] -> 0 | N3: =Tabela3[[#This Row],[CURSO PARA MAGISTRADOS]] -> 0 | O3: =Tabela3[[#This Row],[LIVRO DE REGISTRO]] -> 0 | P3: =Tabela3[[#This Row],[DATA DO ULTIMO REGISTRO]] -> 0 | Q3: =Tabela3[[#This Row],[REG DE INSTRUTORES2]] -> 0 | R3: =Tabela3[[#This Row],[REGISTRO DE INSTRUTORES NO SEI]] -> 0 | S3: =Tabela3[[#This Row],[2021]] -> 0 | T3: =Tabela3[[#This Row],[2022]] -> 0 | U3: =Tabela3[[#This Row],[2023]] -> 0 | V3: =Tabela3[[#This Row],[REGISTRO NO SEI/2024]] -> 0 | W3: =Tabela3[[#This Row],[2024]] -> 0 | X3: =Tabela3[[#This Row],[REGISTRO NO SEI/2025]] -> 0 | Y3: =Tabela3[[#This Row],[TOTAL CERTIFICADOS EMITIDOS/2025]] -> 0 | Z3: =Tabela3[[#This Row],[1º trim/2025]] -> 0 | AA3: =Tabela3[[#This Row],[2º trim/2025]] -> 0 | AB3: =Tabela3[[#This Row],[3º trim/2025]] -> 0 | AC3: =Tabela3[[#This Row],[4º trim/2025]] -> 0
A4: =Tabela3[[#This Row],[MODALIDADE]] -> 0 | B4: =Tabela3[[#This Row],[ID DA PLANILHA]] -> 3 | C4: =Tabela3[[#This Row],[ANO]] -> 1 | D4: =Tabela3[[#This Row],[SEI]] -> 0 | E4: =Tabela3[[#This Row],[NOME DO Curso]] -> 10A/18CM - CURITIBA | F4: =Tabela3[[#This Row],[NENHUMA CLASSIFICAÇÃO COPILOT]] -> 0 | G4: =Tabela3[[#This Row],[Capacitação em Direitos Humanos, Gênero, Raça e Etnia; e em Depoimento Especial" - 0148945-13.2024.8.16.6000]] -> 0 | H4: =Tabela3[[#This Row],[Justiça Restaurativa - 0148919-15.2024.8.16.6000]] -> 0 | I4: =Tabela3[[#This Row],[Capacitação de Facilitadores 0148959-94.2024.8.16.6000]] -> 0 | J4: =Tabela3[[#This Row],[Acessibilidade e Inclusão - 0148938-21.2024.8.16.6000]] -> 0 | K4: =Tabela3[[#This Row],[Política de Prevenção e Enfrentamento do Assédio Moral, do Assédio Sexual e da Discriminação.0148908-83.2024.8.16.6000]] -> 0 | L4: =Tabela3[[#This Row],[SOCIOAMBIENTAL]] -> 0 | M4: =Tabela3[[#This Row],[SUSTENTABILIDADE https://portal.tjpr.jus.br/portletforms/frm.do?idFormulario=7430 0017859-16.2024.8.16.6000]] -> 0 | N4: =Tabela3[[#This Row],[CURSO PARA MAGISTRADOS]] -> 0 | O4: =Tabela3[[#This Row],[LIVRO DE REGISTRO]] -> 0 | P4: =Tabela3[[#This Row],[DATA DO ULTIMO REGISTRO]] -> 0 | Q4: =Tabela3[[#This Row],[REG DE INSTRUTORES2]] -> 0 | R4: =Tabela3[[#This Row],[REGISTRO DE INSTRUTORES NO SEI]] -> 0 | S4: =Tabela3[[#This Row],[2021]] -> 0 | T4: =Tabela3[[#This Row],[2022]] -> 0 | U4: =Tabela3[[#This Row],[2023]] -> 0 | V4: =Tabela3[[#This Row],[REGISTRO NO SEI/2024]] -> 0 | W4: =Tabela3[[#This Row],[2024]] -> 0 | X4: =Tabela3[[#This Row],[REGISTRO NO SEI/2025]] -> 0 | Y4: =Tabela3[[#This Row],[TOTAL CERTIFICADOS EMITIDOS/2025]] -> 0 | Z4: =Tabela3[[#This Row],[1º trim/2025]] -> 0 | AA4: =Tabela3[[#This Row],[2º trim/2025]] -> 0 | AB4: =Tabela3[[#This Row],[3º trim/2025]] -> 0 | AC4: =Tabela3[[#This Row],[4º trim/2025]] -> 0
A5: =Tabela3[[#This Row],[MODALIDADE]] -> 0 | B5: =Tabela3[[#This Row],[ID DA PLANILHA]] -> 4 | C5: =Tabela3[[#This Row],[ANO]] -> 1 | D5: =Tabela3[[#This Row],[SEI]] -> 0 | E5: =Tabela3[[#This Row],[NOME DO Curso]] -> 10B/17CM - CURITIBA | F5: =Tabela3[[#This Row],[NENHUMA CLASSIFICAÇÃO COPILOT]] -> 0 | G5: =Tabela3[[#This Row],[Capacitação em Direitos Humanos, Gênero, Raça e Etnia; e em Depoimento Especial" - 0148945-13.2024.8.16.6000]] -> 0 | H5: =Tabela3[[#This Row],[Justiça Restaurativa - 0148919-15.2024.8.16.6000]] -> 0 | I5: =Tabela3[[#This Row],[Capacitação de Facilitadores 0148959-94.2024.8.16.6000]] -> 0 | J5: =Tabela3[[#This Row],[Acessibilidade e Inclusão - 0148938-21.2024.8.16.6000]] -> 0 | K5: =Tabela3[[#This Row],[Política de Prevenção e Enfrentamento do Assédio Moral, do Assédio Sexual e da Discriminação.0148908-83.2024.8.16.6000]] -> 0 | L5: =Tabela3[[#This Row],[SOCIOAMBIENTAL]] -> 0 | M5: =Tabela3[[#This Row],[SUSTENTABILIDADE https://portal.tjpr.jus.br/portletforms/frm.do?idFormulario=7430 0017859-16.2024.8.16.6000]] -> 0 | N5: =Tabela3[[#This Row],[CURSO PARA MAGISTRADOS]] -> 0 | O5: =Tabela3[[#This Row],[LIVRO DE REGISTRO]] -> 0 | P5: =Tabela3[[#This Row],[DATA DO ULTIMO REGISTRO]] -> 0 | Q5: =Tabela3[[#This Row],[REG DE INSTRUTORES2]] -> 0 | R5: =Tabela3[[#This Row],[REGISTRO DE INSTRUTORES NO SEI]] -> 0 | S5: =Tabela3[[#This Row],[2021]] -> 0 | T5: =Tabela3[[#This Row],[2022]] -> 0 | U5: =Tabela3[[#This Row],[2023]] -> 0 | V5: =Tabela3[[#This Row],[REGISTRO NO SEI/2024]] -> 0 | W5: =Tabela3[[#This Row],[2024]] -> 0 | X5: =Tabela3[[#This Row],[REGISTRO NO SEI/2025]] -> 0 | Y5: =Tabela3[[#This Row],[TOTAL CERTIFICADOS EMITIDOS/2025]] -> 0 | Z5: =Tabela3[[#This Row],[1º trim/2025]] -> 0 | AA5: =Tabela3[[#This Row],[2º trim/2025]] -> 0 | AB5: =Tabela3[[#This Row],[3º trim/2025]] -> 0 | AC5: =Tabela3[[#This Row],[4º trim/2025]] -> 0
A6: =Tabela3[[#This Row],[MODALIDADE]] -> 0 | B6: =Tabela3[[#This Row],[ID DA PLANILHA]] -> 5 | C6: =Tabela3[[#This Row],[ANO]] -> 1 | D6: =Tabela3[[#This Row],[SEI]] -> 0 | E6: =Tabela3[[#This Row],[NOME DO Curso]] -> 10B/18CM - CURITIBA | F6: =Tabela3[[#This Row],[NENHUMA CLASSIFICAÇÃO COPILOT]] -> 0 | G6: =Tabela3[[#This Row],[Capacitação em Direitos Humanos, Gênero, Raça e Etnia; e em Depoimento Especial" - 0148945-13.2024.8.16.6000]] -> 0 | H6: =Tabela3[[#This Row],[Justiça Restaurativa - 0148919-15.2024.8.16.6000]] -> 0 | I6: =Tabela3[[#This Row],[Capacitação de Facilitadores 0148959-94.2024.8.16.6000]] -> 0 | J6: =Tabela3[[#This Row],[Acessibilidade e Inclusão - 0148938-21.2024.8.16.6000]] -> 0 | K6: =Tabela3[[#This Row],[Política de Prevenção e Enfrentamento do Assédio Moral, do Assédio Sexual e da Discriminação.0148908-83.2024.8.16.6000]] -> 0 | L6: =Tabela3[[#This Row],[SOCIOAMBIENTAL]] -> 0 | M6: =Tabela3[[#This Row],[SUSTENTABILIDADE https://portal.tjpr.jus.br/portletforms/frm.do?idFormulario=7430 0017859-16.2024.8.16.6000]] -> 0 | N6: =Tabela3[[#This Row],[CURSO PARA MAGISTRADOS]] -> 0 | O6: =Tabela3[[#This Row],[LIVRO DE REGISTRO]] -> 0 | P6: =Tabela3[[#This Row],[DATA DO ULTIMO REGISTRO]] -> 0 | Q6: =Tabela3[[#This Row],[REG DE INSTRUTORES2]] -> 0 | R6: =Tabela3[[#This Row],[REGISTRO DE INSTRUTORES NO SEI]] -> 0 | S6: =Tabela3[[#This Row],[2021]] -> 0 | T6: =Tabela3[[#This Row],[2022]] -> 0 | U6: =Tabela3[[#This Row],[2023]] -> 0 | V6: =Tabela3[[#This Row],[REGISTRO NO SEI/2024]] -> 0 | W6: =Tabela3[[#This Row],[2024]] -> 0 | X6: =Tabela3[[#This Row],[REGISTRO NO SEI/2025]] -> 0 | Y6: =Tabela3[[#This Row],[TOTAL CERTIFICADOS EMITIDOS/2025]] -> 0 | Z6: =Tabela3[[#This Row],[1º trim/2025]] -> 0 | AA6: =Tabela3[[#This Row],[2º trim/2025]] -> 0 | AB6: =Tabela3[[#This Row],[3º trim/2025]] -> 0 | AC6: =Tabela3[[#This Row],[4º trim/2025]] -> 0
A7: =Tabela3[[#This Row],[MODALIDADE]] -> 0 | B7: =Tabela3[[#This Row],[ID DA PLANILHA]] -> 6 | C7: =Tabela3[[#This Row],[ANO]] -> 1 | D7: =Tabela3[[#This Row],[SEI]] -> 0 | E7: =Tabela3[[#This Row],[NOME DO Curso]] -> 11A/17CM - PONTA GROSSA | F7: =Tabela3[[#This Row],[NENHUMA CLASSIFICAÇÃO COPILOT]] -> 0 | G7: =Tabela3[[#This Row],[Capacitação em Direitos Humanos, Gênero, Raça e Etnia; e em Depoimento Especial" - 0148945-13.2024.8.16.6000]] -> 0 | H7: =Tabela3[[#This Row],[Justiça Restaurativa - 0148919-15.2024.8.16.6000]] -> 0 | I7: =Tabela3[[#This Row],[Capacitação de Facilitadores 0148959-94.2024.8.16.6000]] -> 0 | J7: =Tabela3[[#This Row],[Acessibilidade e Inclusão - 0148938-21.2024.8.16.6000]] -> 0 | K7: =Tabela3[[#This Row],[Política de Prevenção e Enfrentamento do Assédio Moral, do Assédio Sexual e da Discriminação.0148908-83.2024.8.16.6000]] -> 0 | L7: =Tabela3[[#This Row],[SOCIOAMBIENTAL]] -> 0 | M7: =Tabela3[[#This Row],[SUSTENTABILIDADE https://portal.tjpr.jus.br/portletforms/frm.do?idFormulario=7430 0017859-16.2024.8.16.6000]] -> 0 | N7: =Tabela3[[#This Row],[CURSO PARA MAGISTRADOS]] -> 0 | O7: =Tabela3[[#This Row],[LIVRO DE REGISTRO]] -> 0 | P7: =Tabela3[[#This Row],[DATA DO ULTIMO REGISTRO]] -> 0 | Q7: =Tabela3[[#This Row],[REG DE INSTRUTORES2]] -> 0 | R7: =Tabela3[[#This Row],[REGISTRO DE INSTRUTORES NO SEI]] -> 0 | S7: =Tabela3[[#This Row],[2021]] -> 0 | T7: =Tabela3[[#This Row],[2022]] -> 0 | U7: =Tabela3[[#This Row],[2023]] -> 0 | V7: =Tabela3[[#This Row],[REGISTRO NO SEI/2024]] -> 0 | W7: =Tabela3[[#This Row],[2024]] -> 0 | X7: =Tabela3[[#This Row],[REGISTRO NO SEI/2025]] -> 0 | Y7: =Tabela3[[#This Row],[TOTAL CERTIFICADOS EMITIDOS/2025]] -> 0 | Z7: =Tabela3[[#This Row],[1º trim/2025]] -> 0 | AA7: =Tabela3[[#This Row],[2º trim/2025]] -> 0 | AB7: =Tabela3[[#This Row],[3º trim/2025]] -> 0 | AC7: =Tabela3[[#This Row],[4º trim/2025]] -> 0
A8: =Tabela3[[#This Row],[MODALIDADE]] -> 0 | B8: =Tabela3[[#This Row],[ID DA PLANILHA]] -> 7 | C8: =Tabela3[[#This Row],[ANO]] -> 1 | D8: =Tabela3[[#This Row],[SEI]] -> 0 | E8: =Tabela3[[#This Row],[NOME DO Curso]] -> 11A/18CM - CURITIBA | F8: =Tabela3[[#This Row],[NENHUMA CLASSIFICAÇÃO COPILOT]] -> 0 | G8: =Tabela3[[#This Row],[Capacitação em Direitos Humanos, Gênero, Raça e Etnia; e em Depoimento Especial" - 0148945-13.2024.8.16.6000]] -> 0 | H8: =Tabela3[[#This Row],[Justiça Restaurativa - 0148919-15.2024.8.16.6000]] -> 0 | I8: =Tabela3[[#This Row],[Capacitação de Facilitadores 0148959-94.2024.8.16.6000]] -> 0 | J8: =Tabela3[[#This Row],[Acessibilidade e Inclusão - 0148938-21.2024.8.16.6000]] -> 0 | K8: =Tabela3[[#This Row],[Política de Prevenção e Enfrentamento do Assédio Moral, do Assédio Sexual e da Discriminação.0148908-83.2024.8.16.6000]] -> 0 | L8: =Tabela3[[#This Row],[SOCIOAMBIENTAL]] -> 0 | M8: =Tabela3[[#This Row],[SUSTENTABILIDADE https://portal.tjpr.jus.br/portletforms/frm.do?idFormulario=7430 0017859-16.2024.8.16.6000]] -> 0 | N8: =Tabela3[[#This Row],[CURSO PARA MAGISTRADOS]] -> 0 | O8: =Tabela3[[#This Row],[LIVRO DE REGISTRO]] -> 0 | P8: =Tabela3[[#This Row],[DATA DO ULTIMO REGISTRO]] -> 0 | Q8: =Tabela3[[#This Row],[REG DE INSTRUTORES2]] -> 0 | R8: =Tabela3[[#This Row],[REGISTRO DE INSTRUTORES NO SEI]] -> 0 | S8: =Tabela3[[#This Row],[2021]] -> 0 | T8: =Tabela3[[#This Row],[2022]] -> 0 | U8: =Tabela3[[#This Row],[2023]] -> 0 | V8: =Tabela3[[#This Row],[REGISTRO NO SEI/2024]] -> 0 | W8: =Tabela3[[#This Row],[2024]] -> 0 | X8: =Tabela3[[#This Row],[REGISTRO NO SEI/2025]] -> 0 | Y8: =Tabela3[[#This Row],[TOTAL CERTIFICADOS EMITIDOS/2025]] -> 0 | Z8: =Tabela3[[#This Row],[1º trim/2025]] -> 0 | AA8: =Tabela3[[#This Row],[2º trim/2025]] -> 0 | AB8: =Tabela3[[#This Row],[3º trim/2025]] -> 0 | AC8: =Tabela3[[#This Row],[4º trim/2025]] -> 0
A9: =Tabela3[[#This Row],[MODALIDADE]] -> 0 | B9: =Tabela3[[#This Row],[ID DA PLANILHA]] -> 8 | C9: =Tabela3[[#This Row],[ANO]] -> 1 | D9: =Tabela3[[#This Row],[SEI]] -> 0 | E9: =Tabela3[[#This Row],[NOME DO Curso]] -> 11B/18CM - CURITIBA | F9: =Tabela3[[#This Row],[NENHUMA CLASSIFICAÇÃO COPILOT]] -> 0 | G9: =Tabela3[[#This Row],[Capacitação em Direitos Humanos, Gênero, Raça e Etnia; e em Depoimento Especial" - 0148945-13.2024.8.16.6000]] -> 0 | H9: =Tabela3[[#This Row],[Justiça Restaurativa - 0148919-15.2024.8.16.6000]] -> 0 | I9: =Tabela3[[#This Row],[Capacitação de Facilitadores 0148959-94.2024.8.16.6000]] -> 0 | J9: =Tabela3[[#This Row],[Acessibilidade e Inclusão - 0148938-21.2024.8.16.6000]] -> 0 | K9: =Tabela3[[#This Row],[Política de Prevenção e Enfrentamento do Assédio Moral, do Assédio Sexual e da Discriminação.0148908-83.2024.8.16.6000]] -> 0 | L9: =Tabela3[[#This Row],[SOCIOAMBIENTAL]] -> 0 | M9: =Tabela3[[#This Row],[SUSTENTABILIDADE https://portal.tjpr.jus.br/portletforms/frm.do?idFormulario=7430 0017859-16.2024.8.16.6000]] -> 0 | N9: =Tabela3[[#This Row],[CURSO PARA MAGISTRADOS]] -> 0 | O9: =Tabela3[[#This Row],[LIVRO DE REGISTRO]] -> 0 | P9: =Tabela3[[#This Row],[DATA DO ULTIMO REGISTRO]] -> 0 | Q9: =Tabela3[[#This Row],[REG DE INSTRUTORES2]] -> 0 | R9: =Tabela3[[#This Row],[REGISTRO DE INSTRUTORES NO SEI]] -> 0 | S9: =Tabela3[[#This Row],[2021]] -> 0 | T9: =Tabela3[[#This Row],[2022]] -> 0 | U9: =Tabela3[[#This Row],[2023]] -> 0 | V9: =Tabela3[[#This Row],[REGISTRO NO SEI/2024]] -> 0 | W9: =Tabela3[[#This Row],[2024]] -> 0 | X9: =Tabela3[[#This Row],[REGISTRO NO SEI/2025]] -> 0 | Y9: =Tabela3[[#This Row],[TOTAL CERTIFICADOS EMITIDOS/2025]] -> 0 | Z9: =Tabela3[[#This Row],[1º trim/2025]] -> 0 | AA9: =Tabela3[[#This Row],[2º trim/2025]] -> 0 | AB9: =Tabela3[[#This Row],[3º trim/2025]] -> 0 | AC9: =Tabela3[[#This Row],[4º trim/2025]] -> 0
A10: =Tabela3[[#This Row],[MODALIDADE]] -> 0 | B10: =Tabela3[[#This Row],[ID DA PLANILHA]] -> 9 | C10: =Tabela3[[#This Row],[ANO]] -> 1 | D10: =Tabela3[[#This Row],[SEI]] -> 0 | E10: =Tabela3[[#This Row],[NOME DO Curso]] -> 12A/17CM - CIANORTE | F10: =Tabela3[[#This Row],[NENHUMA CLASSIFICAÇÃO COPILOT]] -> 0 | G10: =Tabela3[[#This Row],[Capacitação em Direitos Humanos, Gênero, Raça e Etnia; e em Depoimento Especial" - 0148945-13.2024.8.16.6000]] -> 0 | H10: =Tabela3[[#This Row],[Justiça Restaurativa - 0148919-15.2024.8.16.6000]] -> 0 | I10: =Tabela3[[#This Row],[Capacitação de Facilitadores 0148959-94.2024.8.16.6000]] -> 0 | J10: =Tabela3[[#This Row],[Acessibilidade e Inclusão - 0148938-21.2024.8.16.6000]] -> 0 | K10: =Tabela3[[#This Row],[Política de Prevenção e Enfrentamento do Assédio Moral, do Assédio Sexual e da Discriminação.0148908-83.2024.8.16.6000]] -> 0 | L10: =Tabela3[[#This Row],[SOCIOAMBIENTAL]] -> 0 | M10: =Tabela3[[#This Row],[SUSTENTABILIDADE https://portal.tjpr.jus.br/portletforms/frm.do?idFormulario=7430 0017859-16.2024.8.16.6000]] -> 0 | N10: =Tabela3[[#This Row],[CURSO PARA MAGISTRADOS]] -> 0 | O10: =Tabela3[[#This Row],[LIVRO DE REGISTRO]] -> 0 | P10: =Tabela3[[#This Row],[DATA DO ULTIMO REGISTRO]] -> 0 | Q10: =Tabela3[[#This Row],[REG DE INSTRUTORES2]] -> 0 | R10: =Tabela3[[#This Row],[REGISTRO DE INSTRUTORES NO SEI]] -> 0 | S10: =Tabela3[[#This Row],[2021]] -> 0 | T10: =Tabela3[[#This Row],[2022]] -> 0 | U10: =Tabela3[[#This Row],[2023]] -> 0 | V10: =Tabela3[[#This Row],[REGISTRO NO SEI/2024]] -> 0 | W10: =Tabela3[[#This Row],[2024]] -> 0 | X10: =Tabela3[[#This Row],[REGISTRO NO SEI/2025]] -> 0 | Y10: =Tabela3[[#This Row],[TOTAL CERTIFICADOS EMITIDOS/2025]] -> 0 | Z10: =Tabela3[[#This Row],[1º trim/2025]] -> 0 | AA10: =Tabela3[[#This Row],[2º trim/2025]] -> 0 | AB10: =Tabela3[[#This Row],[3º trim/2025]] -> 0 | AC10: =Tabela3[[#This Row],[4º trim/2025]] -> 0
A11: =Tabela3[[#This Row],[MODALIDADE]] -> 0 | B11: =Tabela3[[#This Row],[ID DA PLANILHA]] -> 10 | C11: =Tabela3[[#This Row],[ANO]] -> 1 | D11: =Tabela3[[#This Row],[SEI]] -> 0 | E11: =Tabela3[[#This Row],[NOME DO Curso]] -> 12A/18CM - CURITIBA | F11: =Tabela3[[#This Row],[NENHUMA CLASSIFICAÇÃO COPILOT]] -> 0 | G11: =Tabela3[[#This Row],[Capacitação em Direitos Humanos, Gênero, Raça e Etnia; e em Depoimento Especial" - 0148945-13.2024.8.16.6000]] -> 0 | H11: =Tabela3[[#This Row],[Justiça Restaurativa - 0148919-15.2024.8.16.6000]] -> 0 | I11: =Tabela3[[#This Row],[Capacitação de Facilitadores 0148959-94.2024.8.16.6000]] -> 0 | J11: =Tabela3[[#This Row],[Acessibilidade e Inclusão - 0148938-21.2024.8.16.6000]] -> 0 | K11: =Tabela3[[#This Row],[Política de Prevenção e Enfrentamento do Assédio Moral, do Assédio Sexual e da Discriminação.0148908-83.2024.8.16.6000]] -> 0 | L11: =Tabela3[[#This Row],[SOCIOAMBIENTAL]] -> 0 | M11: =Tabela3[[#This Row],[SUSTENTABILIDADE https://portal.tjpr.jus.br/portletforms/frm.do?idFormulario=7430 0017859-16.2024.8.16.6000]] -> 0 | N11: =Tabela3[[#This Row],[CURSO PARA MAGISTRADOS]] -> 0 | O11: =Tabela3[[#This Row],[LIVRO DE REGISTRO]] -> 0 | P11: =Tabela3[[#This Row],[DATA DO ULTIMO REGISTRO]] -> 0 | Q11: =Tabela3[[#This Row],[REG DE INSTRUTORES2]] -> 0 | R11: =Tabela3[[#This Row],[REGISTRO DE INSTRUTORES NO SEI]] -> 0 | S11: =Tabela3[[#This Row],[2021]] -> 0 | T11: =Tabela3[[#This Row],[2022]] -> 0 | U11: =Tabela3[[#This Row],[2023]] -> 0 | V11: =Tabela3[[#This Row],[REGISTRO NO SEI/2024]] -> 0 | W11: =Tabela3[[#This Row],[2024]] -> 0 | X11: =Tabela3[[#This Row],[REGISTRO NO SEI/2025]] -> 0 | Y11: =Tabela3[[#This Row],[TOTAL CERTIFICADOS EMITIDOS/2025]] -> 0 | Z11: =Tabela3[[#This Row],[1º trim/2025]] -> 0 | AA11: =Tabela3[[#This Row],[2º trim/2025]] -> 0 | AB11: =Tabela3[[#This Row],[3º trim/2025]] -> 0 | AC11: =Tabela3[[#This Row],[4º trim/2025]] -> 0
A12: =Tabela3[[#This Row],[MODALIDADE]] -> 0 | B12: =Tabela3[[#This Row],[ID DA PLANILHA]] -> 11 | C12: =Tabela3[[#This Row],[ANO]] -> 1 | D12: =Tabela3[[#This Row],[SEI]] -> 0 | E12: =Tabela3[[#This Row],[NOME DO Curso]] -> 12B/17CM - CIANORTE | F12: =Tabela3[[#This Row],[NENHUMA CLASSIFICAÇÃO COPILOT]] -> 0 | G12: =Tabela3[[#This Row],[Capacitação em Direitos Humanos, Gênero, Raça e Etnia; e em Depoimento Especial" - 0148945-13.2024.8.16.6000]] -> 0 | H12: =Tabela3[[#This Row],[Justiça Restaurativa - 0148919-15.2024.8.16.6000]] -> 0 | I12: =Tabela3[[#This Row],[Capacitação de Facilitadores 0148959-94.2024.8.16.6000]] -> 0 | J12: =Tabela3[[#This Row],[Acessibilidade e Inclusão - 0148938-21.2024.8.16.6000]] -> 0 | K12: =Tabela3[[#This Row],[Política de Prevenção e Enfrentamento do Assédio Moral, do Assédio Sexual e da Discriminação.0148908-83.2024.8.16.6000]] -> 0 | L12: =Tabela3[[#This Row],[SOCIOAMBIENTAL]] -> 0 | M12: =Tabela3[[#This Row],[SUSTENTABILIDADE https://portal.tjpr.jus.br/portletforms/frm.do?idFormulario=7430 0017859-16.2024.8.16.6000]] -> 0 | N12: =Tabela3[[#This Row],[CURSO PARA MAGISTRADOS]] -> 0 | O12: =Tabela3[[#This Row],[LIVRO DE REGISTRO]] -> 0 | P12: =Tabela3[[#This Row],[DATA DO ULTIMO REGISTRO]] -> 0 | Q12: =Tabela3[[#This Row],[REG DE INSTRUTORES2]] -> 0 | R12: =Tabela3[[#This Row],[REGISTRO DE INSTRUTORES NO SEI]] -> 0 | S12: =Tabela3[[#This Row],[2021]] -> 0 | T12: =Tabela3[[#This Row],[2022]] -> 0 | U12: =Tabela3[[#This Row],[2023]] -> 0 | V12: =Tabela3[[#This Row],[REGISTRO NO SEI/2024]] -> 0 | W12: =Tabela3[[#This Row],[2024]] -> 0 | X12: =Tabela3[[#This Row],[REGISTRO NO SEI/2025]] -> 0 | Y12: =Tabela3[[#This Row],[TOTAL CERTIFICADOS EMITIDOS/2025]] -> 0 | Z12: =Tabela3[[#This Row],[1º trim/2025]] -> 0 | AA12: =Tabela3[[#This Row],[2º trim/2025]] -> 0 | AB12: =Tabela3[[#This Row],[3º trim/2025]] -> 0 | AC12: =Tabela3[[#This Row],[4º trim/2025]] -> 0
A13: =Tabela3[[#This Row],[MODALIDADE]] -> 0 | B13: =Tabela3[[#This Row],[ID DA PLANILHA]] -> 12 | C13: =Tabela3[[#This Row],[ANO]] -> 1 | D13: =Tabela3[[#This Row],[SEI]] -> 0 | E13: =Tabela3[[#This Row],[NOME DO Curso]] -> 12B/18CM - CURITIBA | F13: =Tabela3[[#This Row],[NENHUMA CLASSIFICAÇÃO COPILOT]] -> 0 | G13: =Tabela3[[#This Row],[Capacitação em Direitos Humanos, Gênero, Raça e Etnia; e em Depoimento Especial" - 0148945-13.2024.8.16.6000]] -> 0 | H13: =Tabela3[[#This Row],[Justiça Restaurativa - 0148919-15.2024.8.16.6000]] -> 0 | I13: =Tabela3[[#This Row],[Capacitação de Facilitadores 0148959-94.2024.8.16.6000]] -> 0 | J13: =Tabela3[[#This Row],[Acessibilidade e Inclusão - 0148938-21.2024.8.16.6000]] -> 0 | K13: =Tabela3[[#This Row],[Política de Prevenção e Enfrentamento do Assédio Moral, do Assédio Sexual e da Discriminação.0148908-83.2024.8.16.6000]] -> 0 | L13: =Tabela3[[#This Row],[SOCIOAMBIENTAL]] -> 0 | M13: =Tabela3[[#This Row],[SUSTENTABILIDADE https://portal.tjpr.jus.br/portletforms/frm.do?idFormulario=7430 0017859-16.2024.8.16.6000]] -> 0 | N13: =Tabela3[[#This Row],[CURSO PARA MAGISTRADOS]] -> 0 | O13: =Tabela3[[#This Row],[LIVRO DE REGISTRO]] -> 0 | P13: =Tabela3[[#This Row],[DATA DO ULTIMO REGISTRO]] -> 0 | Q13: =Tabela3[[#This Row],[REG DE INSTRUTORES2]] -> 0 | R13: =Tabela3[[#This Row],[REGISTRO DE INSTRUTORES NO SEI]] -> 0 | S13: =Tabela3[[#This Row],[2021]] -> 0 | T13: =Tabela3[[#This Row],[2022]] -> 0 | U13: =Tabela3[[#This Row],[2023]] -> 0 | V13: =Tabela3[[#This Row],[REGISTRO NO SEI/2024]] -> 0 | W13: =Tabela3[[#This Row],[2024]] -> 0 | X13: =Tabela3[[#This Row],[REGISTRO NO SEI/2025]] -> 0 | Y13: =Tabela3[[#This Row],[TOTAL CERTIFICADOS EMITIDOS/2025]] -> 0 | Z13: =Tabela3[[#This Row],[1º trim/2025]] -> 0 | AA13: =Tabela3[[#This Row],[2º trim/2025]] -> 0 | AB13: =Tabela3[[#This Row],[3º trim/2025]] -> 0 | AC13: =Tabela3[[#This Row],[4º trim/2025]] -> 0
... A1375: =Tabela3[[#This Row],[MODALIDADE]] -> 0 | B1375: =Tabela3[[#This Row],[ID DA PLANILHA]] -> 1405 | C1375: =Tabela3[[#This Row],[ANO]] -> 0 | D1375: =Tabela3[[#This Row],[SEI]] -> 0049431-87.2024.8.16.6000 | E1375: =Tabela3[[#This Row],[NOME DO Curso]] -> Elaborar trilha de capacitação para colaboradores e gestores sobre prevenção e combate ao assédio e discriminação | F1375: =Tabela3[[#This Row],[NENHUMA CLASSIFICAÇÃO COPILOT]] -> 0 | G1375: =Tabela3[[#This Row],[Capacitação em Direitos Humanos, Gênero, Raça e Etnia; e em Depoimento Especial" - 0148945-13.2024.8.16.6000]] -> 0 | H1375: =Tabela3[[#This Row],[Justiça Restaurativa - 0148919-15.2024.8.16.6000]] -> 0 | I1375: =Tabela3[[#This Row],[Capacitação de Facilitadores 0148959-94.2024.8.16.6000]] -> 0 | J1375: =Tabela3[[#This Row],[Acessibilidade e Inclusão - 0148938-21.2024.8.16.6000]] -> 0 | K1375: =Tabela3[[#This Row],[Política de Prevenção e Enfrentamento do Assédio Moral, do Assédio Sexual e da Discriminação.0148908-83.2024.8.16.6000]] -> 0 | L1375: =Tabela3[[#This Row],[SOCIOAMBIENTAL]] -> 0 | M1375: =Tabela3[[#This Row],[SUSTENTABILIDADE https://portal.tjpr.jus.br/portletforms/frm.do?idFormulario=7430 0017859-16.2024.8.16.6000]] -> 0 | N1375: =Tabela3[[#This Row],[CURSO PARA MAGISTRADOS]] -> 0 | O1375: =Tabela3[[#This Row],[LIVRO DE REGISTRO]] -> 0 | P1375: =Tabela3[[#This Row],[DATA DO ULTIMO REGISTRO]] -> 0 | Q1375: =Tabela3[[#This Row],[REG DE INSTRUTORES2]] -> 0 | R1375: =Tabela3[[#This Row],[REGISTRO DE INSTRUTORES NO SEI]] -> 0 | S1375: =Tabela3[[#This Row],[2021]] -> 0 | T1375: =Tabela3[[#This Row],[2022]] -> 0 | U1375: =Tabela3[[#This Row],[2023]] -> 0 | V1375: =Tabela3[[#This Row],[REGISTRO NO SEI/2024]] -> 0 | W1375: =Tabela3[[#This Row],[2024]] -> 0 | X1375: =Tabela3[[#This Row],[REGISTRO NO SEI/2025]] -> 0 | Y1375: =Tabela3[[#This Row],[TOTAL CERTIFICADOS EMITIDOS/2025]] -> 0 | Z1375: =Tabela3[[#This Row],[1º trim/2025]] -> 0 | AA1375: =Tabela3[[#This Row],[2º trim/2025]] -> 0 | AB1375: =Tabela3[[#This Row],[3º trim/2025]] -> 0 | AC1375: =Tabela3[[#This Row],[4º trim/2025]] -> 0

Sheet plano de contratação
A1: 0018447-86.2025.8.16.6000
A2: até o dia 22 de abril
D4: o código de item | E4: unidade requisitante do item | F4: Quantidade a ser adquirida ou contratada | G4: a descrição sucinta ou do objeto; | H4: a justificativa para a necessidade da aquisição ou contratação; | I4: a estimativa preliminar do valor; | J4: o grau de prioridade da compra ou contratação, com graduações de alto, médio e baixo; e | K4: a data estimada para a compra ou contratação." | L4: obs
B5: 0152659-78.2024.8.16.6000 | C5: renovação da plataforma UDEMY/Raleduc, | E5: SG-STI-GS-AT - Assessoria Técnica do Gabinete do Secretário da Secretaria de Tecnologia da Informação | F5: 115 lincenças | G5: contratação direta de pessoa jurídica, por inexigibilidade de licitação, referente ao processo de contratação de 115 (cento e quinze) licenças "Udemy for Government" de acesso à plataforma de cursos online Udemy para capacitação de servidores da Secretaria de Tecnologia da Informação, pelo período de 24 (vinte e quatro) meses. | I5: 3410.12 | K5: 45689 | L5: Pré-Empenho - SIAFIC 2025NR000260 (11502972)
B6: 0124397-55.2023.8.16.6000 | C6: serviços de tradução/interpretação para Linguagem Brasileira de Sinais - Libras, | E6: DP-D - Diretoria do Departamento do Patrimônio | H6: garantindo a acessibilidade | K6: 45748 | L6: Termo de Referência 11539071
B7: 0165108-68.2024.8.16.6000 | C7: fornecedor H&L PROMOÇÕES, EVENTOS E COMUNICAÇÃO LTDA, | L7: finalizado
C8: pagamento de docentes/conteudistas
C9: pagamento de diarias
B10: 0150397-58.2024.8.16.6000 | C10: impressão do livro 300 ANOS DA JUSTIÇA TOGADA NA TERRA DAS ARAUCÁRIAS | E10: P-SEP - Secretaria Especial da Presidência | F10: 400 | K10: 45717
B11: 0007585-56.2025.8.16.6000 | C11: Contratação do Pacote Adobe Creative Cloud | E11: P-SEP-GSEP-CCS - Coordenadoria de Comunicação Social do Gabinete do Secretário Especial da Presidência | F11: 13 | H11: O atual contrato do Pacote Adobe Creative Cloud (195/2022 - 8436877 ) encerra-se em Dezembro deste ano. Os programas da Adobe são utilizados diariamente na produção gráfica e audiovisual da Coordenadoria de Comunicação Social, bem como em videoaulas da Escola Judicial do Paraná. A Adobe é reconhecida mundialmente pela excelência e os softwares permitem edição de fotografias, ilustrações e vídeos, diagramação de publicações impressas, cartazes e outras peças gráficas com qualidade profissional, edição de boletins online; criação de interfaces em linguagem flash, etc. Tanto CCS quanto EJUD dependem da utilização do Pacote Adobe Creative Cloud para suas atividades. | I11: 260000 | K11: 46023
B12: 0014636-21.2025.8.16.6000 | C12: moldura para galeria dos presidentes da EJUD | E12: EJUD | F12: 1 | I12: 89.6 | K12: 45689
B13: 0014628-44.2025.8.16.6000 | C13: solicitação de contratação de molduras para estúdio de gravação | E13: EJUD | F13: 12 | H13: molduras de madeiras para estúdio de gravação da EJUD | I13: 1517.44 | K13: 45689
B14: 0018014-82.2025.8.16.6000 | C14: solicitação para alteração do Contrato nº 197/2024 (mov. 10906096), expediente 0053959-04.2023.8.16.6000, firmado entre o Tribunal de Justiça do Estado do Paraná (TJPR) e a empresa H&L Promoções, Eventos e Comunicação Ltda | E14: EJUD | H14: alteração do Contrato nº 197/2024 (10906096), que contempla, entre outros serviços, a produção de vídeo-aulas, utilizadas exclusivamente pela referida unidade. O pedido tem por objetivo o aumento da quantidade de vídeo-aulas com duração de até 12 minutos, tendo em vista que as 50 unidades inicialmente previstas já foram integralmente utilizadas. | K14: 45748 | L14: 0024199-39.2025.8.16.6000
B15: 0019008-13.2025.8.16.6000 | C15: locação de máquinas automáticas de café e bebidas quentes, com fornecimento de insumos e manutenção | E15: EJUD | H15: nova contratação uma vez que a máquina de café é muito utilizada pelos formadores e cursistas. | K15: 45748 | L15: Documentação 11601932
B16: 0009849-46.2025.8.16.6000 | C16: bottos com a identificação da EJUD. | E16: EJUD | F16: 200 bottos | K16: 45748
B17: 0019033-26.2025.8.16.6000 | C17: encadernação dos seguintes documentos | E17: EJUD | F17: a) Livro 1 - documento nº 11511796 - 02 (dois) exemplares; b) Livro 2 - documento nº 11511804 - 02 (dois) exemplares; c) Livro 3 - documento nº 11511820 - 02 (dois) exemplares; d) Livro 4 - documento nº 11511873 - 02 (dois) exemplares; | K17: 45748
B18: 0097198-24.2024.8.16.6000 | C18: aquisição de ferramenta PIPEPRO (contrato de manutenção), responsável pelo atual Sistema de Pagamento de Diárias (AlivePro | E18: SG-SF-CGF-DFRD - Divisão de Fundo Rotativo e Diárias da Coordenadoria de Gestão Financeira da Secretaria de Finanças | G18: Sistema de Pagamento de Diárias (AlivePro) | K18: 45748
B19: 0022808-49.2025.8.16.6000 | C19: Solicitação de contratação de compra de bandeiras da Escola Judicial do Paraná - EJUD | E19: EJUD | F19: 3 | G19: bandeiras da Escola Judicial do Paraná - EJUD | K19: 45748
B20: 0008700-15.2025.8.16.6000 | C20: placa de identificação externa | E20: EJUD | F20: 1 | G20: placa de identificação externa | H20: fundamental para aprimorar a sinalização e a organização do espaço, facilitando o acesso de magistrados, servidores e demais públicos que necessitam dos serviços oferecidos. | I20: 2036.97 | K20: 45717
B21: 0017506-39.2025.8.16.6000 | C21: Solicito os bons préstimos a pintura e revisão elétrica | E21: EJUD | G21: pintura e revisão elétrica do 1° andar, 2° andar, 3° andar e 4° andar do Ed. Pery Moreira e instalação de lógica cabeada na sala 215, nesta Capital. | H21: paredes sujas, no auditório existe a falta de tomadas o que compromete nos dias que tem curso e necessita de utilização de aparelhos eletrõnicos. Comprometimento dos cursos quando necessita de wi-fi.
B22: 0151757-28.2024.8.16.6000 | C22: aumento espaço onedrive | E22: EJUD | F22: ampliação do espaço de armazenamento para, no mínimo, 500 GB, | H22: Essa limitação impacta diretamente a continuidade das atividades pedagógicas, comprometendo a formação de magistrados e servidores | L22: SIGA R625169 (11487830)
B23: 0006139-18.2025.8.16.6000 | C23: cartões de visita - EJUD/2025 a 2027 | F23: 300 | K23: 45689
A24: in company | B24: 0134259-50.2023.8.16.6000 | C24: EC - Council Certified Ethical Hacker v 13 - Elite | E24: P-AUDI-CAI - Chefia da Auditoria Interna | F24: 10 | K24: 45689
A25: in company | B25: 0177370-50.2024.8.16.6000 | C25: TREINAMENTO ARQUITETO JAVA | E25: P-AUDI-CAI - Chefia da Auditoria Interna | F25: 40 | I25: 1107.5 | K25: 45809
A26: in company | B26: 0004758-72.2025.8.16.6000 | C26: 20º CONGRESSO DE PREGOEIROS | E26: SG-SCI-CLCD - Coordenadoria de Licitações e Compras Diretas da Secretaria de Contratações Institucionais | F26: 15 | I26: 60000 | K26: 45717
A27: in company | B27: 0011767-85.2025.8.16.6000 | C27: Curso "Let's Gov - Fazendo a Inovação Acontecer no Setor Público | E27: P-SEP-LPDI - Laboratório de Pesquisa, Desenvolvimento e Inovação da Secretaria Especial da Presidência | F27: 1 | G27: objetivo da oficina é capacitar os participantes em metodologias e ferramentas inovadoras e colaborativas para o setor público. | I27: 2000
A28: in company | B28: 0012195-67.2025.8.16.6000 | C28: LAAD DEFENCE & SECURITY 2025 | E28: SG-SI-CST-DSP - Divisão de Segurança Patrimonial da Coordenadoria de Serviços Terceirizados da Secretaria de Infraestrutura | F28: 3 | H28: crescente aumento tecnológico que este Tribunal tem se inserido no âmbito da segurança patrimonial, bem como a busca para alteração e aprimoramento das contratações institucionais relacionadas à vigilância e segurança patrimonial, | I28: 600 | K28: 45748
A29: in company | B29: 0020301-18.2025.8.16.6000 | C29: Seminário de Direitos Indígenas: Visão Jurídica, Antropológica e Sociológica | E29: GT-QI - Grupo de Trabalho sobre Questões Indígenas | F29: 5 | H29: proporcionará uma oportunidade ímpar de aprofundamento nos conhecimentos relativos às questões indígenas, promovendo um intercâmbio de experiências e saberes que são essenciais para o desenvolvimento de políticas públicas mais eficazes e inclusivas | I29: gratuito | K29: 45748

Sheet libras
A1: EVENTOS 2024 COM INTÉRPRETES DE LIBRAS
A3: BLOCO | B3: ID DA PLANILHA | C3: ANO DO CURSO | D3: SEI | E3: NOME DO Curso | F3: PLANO DE CURSO/SEI | G3: LOCAL | H3: ANO DO CURSO2 | I3: DATA INÍCIO | J3: DATA TERMINO | K3: CARGA HORARIA | L3: Data | M3: Nº Eventos | N3: Nº Dias | O3: Nº Horas | P3: Nº Intérpretes | Q3: Atesto | R3: sei de pagamento
B4: 988 | C4: 2024 | D4: 0013763-55.2024.8.16.6000 | E4: 1º Pré-Encontro Preparatório para a 14ª Edição do Encontro Nacional de Preparação Online para Pretendentes à Adoção | F4: Projeto (10238750) | G4: Paraná | H4: 2024 | I4: 45419 | J4: 45440 | K4: 30 h | L4: 45405 | M4: 1 | N4: 6 | O4: 1 | P4: 2
B5: 988 | C5: 2024 | D5: 0013763-55.2024.8.16.6000 | E5: 2º Pré-Encontro Preparatório para a 14ª Edição do Encontro Nacional de Preparação Online para Pretendentes à Adoção | F5: Projeto (10238750) | G5: Paraná | H5: 2024 | I5: 45419 | J5: 45440 | K5: 30 h | L5: 45412 | O5: 1 | P5: 2
B6: 988 | C6: 2024 | D6: 0013763-55.2024.8.16.6000 | E6: Abertura 14ª Edição do Encontro Nacional de Preparação Online para Pretendentes à Adoção | F6: Projeto (10238750) | G6: Paraná | H6: 2024 | I6: 45419 | J6: 45440 | K6: 30 h | L6: 45419 | O6: 2 | P6: 2
B7: 988 | C7: 2024 | D7: 0013763-55.2024.8.16.6000 | E7: 1º Encontro Síncrono 14ª Edição do Encontro Nacional de Preparação Online para Pretendentes à Adoção | F7: Projeto (10238750) | G7: Paraná | H7: 2024 | I7: 45419 | J7: 45440 | K7: 30 h | L7: 45426 | O7: 2 | P7: 2
B8: 988 | C8: 2024 | D8: 0013763-55.2024.8.16.6000 | E8: 2º Encontro Síncrono 14ª Edição do Encontro Nacional de Preparação Online para Pretendentes à Adoção | F8: Projeto (10238750) | G8: Paraná | H8: 2024 | I8: 45419 | J8: 45440 | K8: 30 h | L8: 45433 | O8: 2 | P8: 2
B9: 988 | C9: 2024 | D9: 0013763-55.2024.8.16.6000 | E9: Encerramento 14ª Edição do Encontro Nacional de Preparação Online para Pretendentes à Adoção | F9: Projeto (10238750) | G9: Paraná | H9: 2024 | I9: 45419 | J9: 45440 | K9: 30 h | L9: 45440 | O9: 2 | P9: 2
B10: 1017 | C10: 2024 | D10: 0030327-12.2024.8.16.6000 | E10: VI Semana da Adoção | F10: Projeto 10401183 | H10: 2024 | I10: 45432 | J10: 45436 | K10: 4 h | L10: 45432 | M10: 1 | N10: 1 | O10: 1 | P10: 2
B11: 1025 | C11: 2024 | D11: 0036821-87.2024.8.16.6000 | E11: V Encontro Paranaense de Justiça Restaurativa: 10 anos da Justiça Restaurativa | F11: 10172939 | G11: Curitiba | H11: 2024 | I11: 45476 | J11: 45478 | K11: 12 h | L11: 45476 | M11: 1 | N11: 4 | O11: 2 | P11: 2
B12: 1025 | C12: 2024 | D12: 0036821-87.2024.8.16.6000 | E12: V Encontro Paranaense de Justiça Restaurativa: 10 anos da Justiça Restaurativa | F12: 10172939 | G12: Curitiba | H12: 2024 | I12: 45476 | J12: 45478 | K12: 12 h | L12: 45477 | O12: 3 | P12: 2
B13: 1025 | C13: 2024 | D13: 0036821-87.2024.8.16.6000 | E13: V Encontro Paranaense de Justiça Restaurativa: 10 anos da Justiça Restaurativa | F13: 10172939 | G13: Curitiba | H13: 2024 | I13: 45476 | J13: 45478 | K13: 12 h | L13: 45477 | O13: 2 | P13: 2
B14: 1025 | C14: 2024 | D14: 0036821-87.2024.8.16.6000 | E14: V Encontro Paranaense de Justiça Restaurativa: 10 anos da Justiça Restaurativa | F14: 10172939 | G14: Curitiba | H14: 2024 | I14: 45476 | J14: 45478 | K14: 12 h | L14: 45478 | O14: 4 | P14: 2
B15: 1037 | C15: 2024 | D15: 0048221-98.2024.8.16.6000 | E15: Semana de Combate ao Assédio e à Discriminação | F15: Projeto 10322549 | H15: 2024 | I15: 45420 | J15: 45420 | K15: 3 H | L15: 45420 | M15: 1 | N15: 1 | O15: 3 | P15: 2
B16: 1076 | C16: 2024 | D16: 0083617-39.2024.8.16.6000 | E16: 8º Encontro de Gestão Judiciária Sustentável do Tribunal de Justiça do Paraná | F16: Projeto 10808941 | H16: 2024 | I16: 45539 | J16: 45539 | K16: 3 h | L16: 45539 | M16: 1 | N16: 1 | O16: 3 | P16: 2
B17: 1077 | C17: 2024 | D17: 0084941-64.2024.8.16.6000 | E17: I Simpósio de Linguagem Acessível do Judiciário Paranaense | F17: Projeto 10650332 | H17: 2024 | I17: 45496 | J17: 45499 | K17: 8 h | L17: 45496 | M17: 1 | N17: 1 | O17: 2 | P17: 2
B18: 1088 | C18: 2024 | D18: 0092962-29.2024.8.16.6000 | E18: 1º Pré-Encontro Preparatório para a 15ª Edição do Encontro Nacional de Preparação Online para Pretendentes à Adoção | F18: Projeto 15ª Edição (10787159) | H18: 2024 | I18: 45573 | J18: 45594 | K18: 30 h | L18: 45552 | M18: 1 | N18: 6 | O18: 1 | P18: 2
B19: 1088 | C19: 2024 | D19: 0092962-29.2024.8.16.6000 | E19: 2º Pré-Encontro Preparatório para a 15ª Edição do Encontro Nacional de Preparação Online para Pretendentes à Adoção | F19: Projeto 15ª Edição (10787159) | H19: 2024 | I19: 45573 | J19: 45594 | K19: 30 h | L19: 45559 | O19: 1 | P19: 2
B20: 1088 | C20: 2024 | D20: 0092962-29.2024.8.16.6000 | E20: Abertura 15ª Edição Encontro Nacional de Preparação Online para Pretendentes à Adoção | F20: Projeto 15ª Edição (10787159) | H20: 2024 | I20: 45573 | J20: 45594 | K20: 30 h | L20: 45573 | O20: 2 | P20: 2
B21: 1088 | C21: 2024 | D21: 0092962-29.2024.8.16.6000 | E21: 1º Encontro Síncrono 15ª Edição do Encontro Nacional de Preparação Online para Pretendentes à Adoção | F21: Projeto 15ª Edição (10787159) | H21: 2024 | I21: 45573 | J21: 45594 | K21: 30 h | L21: 45580 | O21: 2 | P21: 2
B22: 1088 | C22: 2024 | D22: 0092962-29.2024.8.16.6000 | E22: 2º Encontro Síncrono 15ª Edição do Encontro Nacional de Preparação Online para Pretendentes à Adoção | F22: Projeto 15ª Edição (10787159) | H22: 2024 | I22: 45573 | J22: 45594 | K22: 30 h | L22: 45587 | O22: 2 | P22: 2
B23: 1088 | C23: 2024 | D23: 0092962-29.2024.8.16.6000 | E23: 3º Encontro Síncrono e Encerramento 15ª Edição do Encontro Nacional de Preparação Online para Pretendentes à Adoção | F23: Projeto 15ª Edição (10787159) | H23: 2024 | I23: 45573 | J23: 45594 | K23: 30 h | L23: 45594 | O23: 2 | P23: 2
B24: 1110 | C24: 2024 | D24: 0115091-28.2024.8.16.6000 | E24: Projeto Judiciário Inclusivo e Acessível – Dia Nacional da Luta da Pessoa com Deficiência | F24: Projeto 10912635 | H24: 2024 | I24: 45555 | J24: 45555 | K24: 2 h | L24: 45555 | M24: 1 | N24: 1 | O24: 2 | P24: 2
B25: 1137 | C25: 2024 | D25: 0127200-11.2023.8.16.6000 | E25: II Seminário de Acessibilidade e Inclusão do Tribunal de Justiça do Paraná | G25: Curitiba | H25: 2024 | I25: 45372 | J25: 45372 | K25: 3 h | L25: 45420 | M25: 1 | N25: 1 | O25: 3 | P25: 2
B26: 1150 | C26: 2024 | D26: 0133581-98.2024.8.16.6000 | E26: 1ª Jornada do Programa PREPARAR (manhã) | F26: Projeto 11096255 | G26: Paraná | H26: 2024 | I26: 45604 | J26: 45604 | K26: 8 h | L26: 45604 | M26: 1 | N26: 1 | O26: 2 | P26: 2
B27: 1150 | C27: 2024 | D27: 0133581-98.2024.8.16.6000 | E27: 1ª Jornada do Programa PREPARAR (tarde) | F27: Projeto 11096255 | G27: Paraná | H27: 2024 | I27: 45604 | J27: 45604 | K27: 8 h | L27: 45604 | O27: 4 | P27: 2
B28: 1172 | C28: 2024 | D28: 0146379-91.2024.8.16.6000 | E28: Comemoração ao aniversário do 2º ano de funcionamento do Espaço Laços e Afetos | F28: Projeto 11157626 | H28: 2024 | I28: 45617 | J28: 45617 | K28: 3 h | L28: 45617 | M28: 1 | N28: 1 | O28: 3 | P28: 2
A29: Evento | B29: 1204 | C29: 2025 | D29: 0006578-29.2025.8.16.6000 | E29: III ENCONTRO DE INSTITUIÇÕES FACILITADORAS DE GRUPOS REFLEXIVOS E RESPONSABILIZANTES PARA AUTORES DE VIOLÊNCIA DOMÉSTICA E FAMILIAR CONTRA A MULHER | F29: Projeto 11443161 | G29: Paraná | H29: 2025 | I29: 45730 | J29: 45730 | K29: 8 h | L29: 45730 | M29: 1 | N29: 1 | O29: 7 | P29: 4 | Q29: Atesto 11564486
B30: 1220 | C30: 2025 | D30: 0013603-93.2025.8.16.6000 | E30: Elas no Direito – Liderança Feminina e Equidade no Judiciário | F30: Projeto 11534776 | H30: 2025 | I30: 45736 | J30: 45737 | K30: 8 h | L30: 45746 | M30: 1 | N30: 2 | O30: 11 | P30: 6 | Q30: Atesto 11581865 | R30: 0020537-67.2025.8.16.6000
D31: 0026293-57.2025.8.16.6000 | E31: SANÇÃO DA LEI PARA CRIAÇÃO DA CÂMARA ESPECIALIZADA EM VIOLÊNCIA DOMÉSTICA | G31: Curitiba | H31: 2025 | I31: 45772 | J31: 45772
D32: 0014158-13.2025.8.16.6000 | E32: Sessão de Treinamento sobre o Microsoft 365 Copilot Exclusiva para PCDs Ciclo de Workshops - Programa de Capacitação Institucional em Microsoft 365 Copilot | F32: Projeto 11562978 | H32: 2025 | I32: 45740 | J32: 45779 | Q32: Solicitação 11651397

Sheet diarias
C2: PROCESSO PRINCIPAL | D2: EVENTO | E2: DATA DO INICIO | F2: DATA DO TERMINO | G2: PEDIDO DE DIARIA | H2: NOME DO SOLICITANTE | J2: DATA DO INICIO | K2: DATA DO TERMINO | L2: DIARIAS DEFERIDAS
D3: diárias aos magistrados designados para frequência ao curso de formação inicial promovido pela ESMEC. | G3: 0014272-83.2024.8.16.6000
D4: Convite para o IX Encontro do Consepre Encontro Especial de Posse da nova Comissão Administrativa | G4: 0159519-32.2023.8.16.6000
D5: Vanessa Rafaela Lobato - Encontro Nacional de Formadoras e Formadores, pela (Enfam), nos dias 27 e 28 de fevereiro de 2024 | G5: 0011710-04.2024.8.16.6000
D6: erimônia de Posse dos novos Conselheiros do colendo Conselho Nacional de Justiça, que acontecerá no dia 20.02.2024, a partir das 10h, em Brasília-DF. | G6: 0019342-81.2024.8.16.6000
D7: 12 e 13 de maio do 2021, em virtude da necessidade de despachar, em Brasília -DF, com os Ministros do Supremo Tribunal Federal, tendo como pauta de assuntos a ADI nº 2.040, a ADI nº 6.433 e o RE nº 808.202. | G7: 0049511-56.2021.8.16.6000
D8: Fórum da ONU-ILANUD da Escola da Magistratura do Tribunal de Justiça do Estado do Rio de Janeiro (EMERJ) em parceria com o Colégio Permanente de Diretores de Escolas Estaduais da Magistratura (COPEDEM) nos dias 15 e 16 de abril de 2024 | G8: 0030280-38.2024.8.16.6000
D9: DIVANGELA PRÉCOMA MOREIRA KULIGOWSKI - PARTICIPAÇÃO NO FORUM NACIONAL DO JUÍZES DA EXECUÇÃO PENAL | G9: 0031699-93.2024.8.16.6000
D10: FONAJE | G10: 0033353-18.2024.8.16.6000
D11: IV Fórum Nacional de Execução Penal FONAVEP, a se realizar nos dias 14 e 15 de março de 2024, a partir das 17 h, em Foz do Iguaçu/PR. | G11: 0012035-76.2024.8.16.6000
D12: FORÚM NACIONAL DE EXECUÇÃO PENAL, PROMOVIDO PELO PRÓPRIO TJPR | G12: 0034098-95.2024.8.16.6000
D13: PARTICIPAÇÃO NO FONAVEP | G13: 0035135-60.2024.8.16.6000
D14: 2.º Diálogo da Comissão de Soluções Fundiárias com a Magistratura, a se realizar em 25 de abril de 2024, em Curitiba. | G14: 0036915-35.2024.8.16.6000
... D21: evento Conselho Nacional de Justiça: Presente, Passado e Futuro, que será realizado entre os dias 17 a 19 de abril de 2024, | G21: 0044140-09.2024.8.16.6000
G22: 0045049-51.2024.8.16.6000
G23: 0045382-03.2024.8.16.6000
G24: 0042297-09.2024.8.16.6000
G25: 0046537-41.2024.8.16.6000
G26: 0046667-31.2024.8.16.6000
G27: 0047254-53.2024.8.16.6000
G28: 0047272-74.2024.8.16.6000
G29: 0046224-80.2024.8.16.6000
G30: 0047788-94.2024.8.16.6000
G31: 0047783-72.2024.8.16.6000
G32: 0047848-67.2024.8.16.6000
G33: 0047869-43.2024.8.16.6000
... G78: 0075253-78.2024.8.16.6000
D79: Congresso Internacional Cortes Supremas no Direito Comparado: as funções institucionais e os modelos de filtros recursais", que será realizado, no período de 19 a 21 de junho de 2024 | G79: 0076364-97.2024.8.16.6000
G80: 0075237-27.2024.8.16.6000
G81: 0077781-85.2024.8.16.6000
G82: 0077844-13.2024.8.16.6000
G83: 0077493-40.2024.8.16.6000
G84: 0077791-32.2024.8.16.6000
G85: 0077698-69.2024.8.16.6000
G86: 0077643-21.2024.8.16.6000
G87: 0077916-97.2024.8.16.6000
G88: 0077956-79.2024.8.16.6000
G89: 0076709-63.2024.8.16.6000
G90: 0077860-64.2024.8.16.6000
G91: 0078379-39.2024.8.16.6000
... G106: 0080484-86.2024.8.16.6000
C107: 0036821-87.2024.8.16.6000 | D107: V Encontro Paranaense de Justiça Restaurativa: 10 anos da Justiça Restaurativa do Tribunal de Justiça do Paraná | G107: 0080569-72.2024.8.16.6000 | H107: DIANA CRISTINA SOSA
G108: 0080819-08.2024.8.16.6000
G109: 0080836-44.2024.8.16.6000
G110: 0078099-68.2024.8.16.6000
G111: 0080995-84.2024.8.16.6000
G112: 0081090-17.2024.8.16.6000
G113: 0079303-50.2024.8.16.6000
G114: 0082051-55.2024.8.16.6000
G115: 0082219-57.2024.8.16.6000
G116: 0082328-71.2024.8.16.6000
G117: 0082216-05.2024.8.16.6000
G118: 0082208-28.2024.8.16.6000
G119: 0082371-08.2024.8.16.6000
... G133: 0085535-78.2024.8.16.6000
C134: 0036821-87.2024.8.16.6000 | D134: Encontro de Justiça Restaurativa e ODS | G134: 0086303-04.2024.8.16.6000 | H134: Leticia Lilian Kirschnick Seyr
C135: 0060854-44.2024.8.16.6000 | D135: curso Temas de Direito de Família na atualidade: inovações legislativas e jurisprudenciais | G135: 0086485-87.2024.8.16.6000 | H135: Cristina Trento
G136: 0087291-25.2024.8.16.6000
G137: 0087379-63.2024.8.16.6000
G138: 0088021-36.2024.8.16.6000 | H138: diárias aos formadores externos do "III FÓRUM SOBRE OS DESAFIOS ATUAIS PARA O PODER JUDICIÁRIO E O MINISTÉRIO PÚBLICO"
G139: 0087469-71.2024.8.16.6000
G140: 0088297-67.2024.8.16.6000
G141: 0086678-05.2024.8.16.6000
G142: 0086821-91.2024.8.16.6000
G143: 0089667-81.2024.8.16.6000
G144: 0089832-31.2024.8.16.6000
G145: 0089516-18.2024.8.16.6000
G146: 0088282-98.2024.8.16.6000
G147: 0085995-65.2024.8.16.6000
G148: 0088275-09.2024.8.16.6000
G149: 0089637-46.2024.8.16.6000
G150: 0092074-60.2024.8.16.6000
... G163: 0100747-42.2024.8.16.6000
G164: 0102151-31.2024.8.16.6000 | H164: passagens aéreas e diárias aos formadores externos do curso Formação de Formadores Desenvolvimento Docente N1 M3
G165: 0102132-25.2024.8.16.6000
G166: 0103118-76.2024.8.16.6000
G167: 0104871-68.2024.8.16.6000
G168: 0105265-75.2024.8.16.6000
G169: 0106155-14.2024.8.16.6000
G170: 0105509-04.2024.8.16.6000
G171: 0106700-84.2024.8.16.6000
G172: 0105030-11.2024.8.16.6000
G173: 0110150-35.2024.8.16.6000
G174: 0110217-97.2024.8.16.6000
G175: 0112278-28.2024.8.16.6000
G176: 0112360-59.2024.8.16.6000
... G179: 0115475-88.2024.8.16.6000
D180: III FÓRUM DESAFIOS ATUAIS PARA O PODER JUDICIÁRIO E O MINISTÉRIO PÚBLICO, dias 22 a 24 de agosto de 2024, Foz do Iguaçu/PR. | G180: 0116766-26.2024.8.16.6000
D181: xpediente iniciado pelo servidor Edmar Arnaldo Lippmann Junior, que solicita "liberação, nos dias 17, 18, 19 e 20 de setembro do ano corrente, para participar do VIII ENCONTRO NACIONAL DOS OFICIAIS DE JUSTIÇA DO BRASIL VII ENOJUS PE 24 | G181: 0112364-96.2024.8.16.6000
G182: 0119057-96.2024.8.16.6000
G183: 0118952-22.2024.8.16.6000
G184: 0120810-88.2024.8.16.6000
G185: 0120709-51.2024.8.16.6000
G186: 0121073-23.2024.8.16.6000
G187: 0121127-86.2024.8.16.6000
G188: 0124562-68.2024.8.16.6000
G189: 0125600-18.2024.8.16.6000
G190: 0126171-86.2024.8.16.6000
G191: 0125802-92.2024.8.16.6000
G192: 0129084-41.2024.8.16.6000
...

Sheet EMAP - PGTO PELO TJPR
A1: Cursos realizados por outras entidades, mas pagos pelo TJPR
A2: INSTITUIÇÃO | B2: ID DA PLANILHA DE CURSOS | C2: ANO | D2: SEI | E2: NOME DO Curso | F2: PORTARIA ENFAM | G2: Tipo de evento | H2: TURMA | I2: nº de vagas | J2: LOCAL | K2: ANO DO CURSO2 | L2: DATA INÍCIO | M2: DATA TERMINO | N2: DECLARAÇÃO/ CERTIFICADO/ SEM CERTIFICAÇÃO | O2: ON LINE OU PRESENCIAL | P2: PUBLICO ALVO | Q2: CARGA HORARIA | R2: ID | S2: CARGO OCUPADO | T2: nome do instrutor | U2: CPF | V2: CARGA HORARIA | W2: ATESTO/PAGAMENTO
A3: EMAP | B3: 1221 | C3: 2025 | D3: 0014567-86.2025.8.16.6000 | E3: curso "Resolução de Conflitos na Era Digital | F3: 011/2025 | G3: Curso | H3: 2 turmas | I3: 40 | J3: Paranã | K3: 2025 | L3: 45749 | M3: 45779 | N3: certificado | O3: EAD | P3: MAGISTRADO | Q3: 40 h | R3: EMAP | S3: Coordenador | T3: Rafaela Somma Leonardi
A4: EMAP | B4: 1221 | C4: 2025 | D4: 0014567-86.2025.8.16.6000 | E4: curso "Resolução de Conflitos na Era Digital | F4: 011/2025 | G4: Curso | H4: 2 turmas | I4: 40 | J4: Paranã | K4: 2025 | L4: 45749 | M4: 45779 | N4: certificado | O4: EAD | P4: MAGISTRADO | Q4: 40 h | R4: EMAP | S4: Tutor | T4: Eduardo Novacki
A5: EMAP | B5: 1221 | C5: 2025 | D5: 0014567-86.2025.8.16.6000 | E5: curso "Resolução de Conflitos na Era Digital | F5: 011/2025 | G5: Curso | H5: 2 turmas | I5: 40 | J5: Paranã | K5: 2025 | L5: 45749 | M5: 45779 | N5: certificado | O5: EAD | P5: MAGISTRADO | Q5: 40 h | R5: EMAP | S5: Tutor | T5: Rafele Altoé
A6: EMAP | B6: 1432 | C6: 2025 | D6: 0027660-19.2025.8.16.6000 | E6: curso "Atualização do Código Civil – Direito de Família" | I6: 40 | J6: Londrina | K6: 2025 | L6: 45778 | M6: 45792 | O6: híbrido | Q6: 20 h | R6: EMAP

Sheet informação de magistrados
A1: Período avaliativo: 24 (vinte e quatro) meses que antecederam a publicação do edital | B1: dezembro/2022 a 02/04/2025
D3: LEONARDO MARCIO LAUREANO
A4: sei de solicitação | B4: NOME | C4: SEI | D4: FUNÇÃO OCUPADA | E4: Nome do Curso | F4: Portaria ENFAM | G4: Ano do curso | H4: Data de início | I4: Data de término | J4: Carga-horária | K4: Aproveitamento | L4: Código do certificado
A5: 0022329-56.2025.8.16.6000 | B5: LEONARDO MARCIO LAUREANO | C5: 0072085-73.2021.8.16.6000 | D5: Estudante | E5: A Violência Doméstica, suas relações com ações cíveis em matéria de família e o atendimento humanizado | G5: 2022 | H5: AUTOINSTRUCIONAL | I5: AUTOINSTRUCIONAL | J5: 4 h | L5: 6323a58d-a0b4-4a36-a321-bf31ac1f0214
A6: 0022329-56.2025.8.16.6000 | B6: LEONARDO MARCIO LAUREANO | C6: 0014757-88.2021.8.16.6000 | D6: Estudante | E6: Curso Formação de Gestores: Liderança, Gestão e Indicadores de Desempenho | G6: 2023 | H6: AUTOINSTRUCIONAL | I6: AUTOINSTRUCIONAL | J6: 20 h | K6: 1 | L6: 6422621a-1be0-4ebf-a1e7-761dac1f0214
A7: 0022329-56.2025.8.16.6000 | B7: LEONARDO MARCIO LAUREANO | C7: 0020225-67.2020.8.16.6000 | D7: Estudante | E7: Sindicância e Processo Administrativo Disciplinar: fundamentos legais e administrativos | G7: 2022 | H7: AUTOINSTRUCIONAL | I7: AUTOINSTRUCIONAL | J7: 16 h | K7: 1 | L7: 6414bffa-7d78-406b-8fe4-975fac1f0214
A8: 0022329-56.2025.8.16.6000 | B8: LEONARDO MARCIO LAUREANO | C8: 0054248-34.2023.8.16.6000 | D8: Estudante | E8: Instruções BNMP | F8: não | G8: 2023 | H8: 45082 | I8: 45082 | J8: 4 h | K8: 1 | L8: 64a86a8c-fe3c-40c3-a8a7-69cfac1f0214
A9: 0022329-56.2025.8.16.6000 | B9: LEONARDO MARCIO LAUREANO | C9: 0037697-42.2024.8.16.6000 | D9: Estudante | E9: Curso de Aperfeiçoamento para Magistrados e Magistradas em Audiências Concentradas na Jurisdição da Infância e da Juventude e Inspeções em Estabelecimentos Socioeducativos | F9: 102/2024 | G9: 2024 | H9: 45414 | I9: 45453 | J9: 40 h | K9: 1 | L9: 666a16b6-0984-45f0-919c-061fac1f0214
A10: 0022329-56.2025.8.16.6000 | B10: LEONARDO MARCIO LAUREANO | C10: 0158165-69.2023.8.16.6000 | D10: Estudante | E10: III Fórum Paranaense de Violência Doméstica e Familiar contra a Mulher (FOVID/PR). | G10: 2024 | H10: 45462 | I10: 45464 | J10: 17 h | K10: 1 | L10: 667b37b6-719c-413e-b268-9c67ac1f0214
A11: 0022329-56.2025.8.16.6000 | B11: LEONARDO MARCIO LAUREANO | C11: 0048036-60.2024.8.16.6000 | D11: Estudante | E11: Construção da Decisão Judicial | F11: 98/2023 | G11: 2024 | H11: 45456 | I11: 45488 | J11: 30 h | K11: 1 | L11: 6698bb4f-116c-4978-bcd4-9c73ac1f0214
A12: 0022329-56.2025.8.16.6000 | B12: LEONARDO MARCIO LAUREANO | C12: 0059503-36.2024.8.16.6000 | D12: Estudante | E12: Justiça Restaurativa: aspectos teóricos e práticos no contexto da magistratura | F12: 175/2024 | G12: 2024 | H12: 45512 | I12: 45548 | J12: 40 h | K12: 1 | L12: 66eadbf0-348c-4855-82e4-9c89ac1f0214
A13: 0022329-56.2025.8.16.6000 | B13: LEONARDO MARCIO LAUREANO | C13: 0087271-34.2024.8.16.6000 | D13: Estudante | E13: Curso de Aperfeiçoamento para Magistradas e Magistrados sobre a Moderna Teoria do Conflito, Jurisdição, Gerenciamento do Processo e Consensualidade. | F13: 263/2023 | G13: 2024 | H13: 45512 | I13: 45544 | J13: 40h | K13: 1 | L13: 66e0c22d-9108-45a2-9464-9c65ac1f0214
A14: 0022329-56.2025.8.16.6000 | B14: LEONARDO MARCIO LAUREANO | C14: 0127169-25.2022.8.16.6000 | D14: Estudante | E14: Gestão por Competências na Administração Pública | G14: 2024 | H14: AUTOINSTRUCIONAL | I14: AUTOINSTRUCIONAL | J14: 20 h | K14: 1 | L14: 66bd6711-5d1c-4e06-b143-9c6aac1f0214
A15: 0022329-56.2025.8.16.6000 | B15: LEONARDO MARCIO LAUREANO | C15: 0095105-59.2022.8.16.6000 | D15: Estudante | E15: Gerenciamento de Riscos no Poder Judiciário do Estado do Paraná | G15: 2024 | H15: AUTOINSTRUCIONAL | I15: AUTOINSTRUCIONAL | J15: 13 h | K15: 1 | L15: 66be54be-79b8-4ee2-80e6-f33eac1f0214
A16: 0022329-56.2025.8.16.6000 | B16: LEONARDO MARCIO LAUREANO | C16: 0064934-61.2018.8.16.6000 | D16: Estudante | E16: Gestão por Competências | G16: 2024 | H16: AUTOINSTRUCIONAL | I16: AUTOINSTRUCIONAL | J16: 10 h | K16: 1 | L16: 66b2784e-92fc-4647-b7ef-7866ac1f0214
A17: 0022329-56.2025.8.16.6000 | B17: LEONARDO MARCIO LAUREANO | C17: 0128335-24.2024.8.16.6000 | D17: Estudante | E17: 3ª Edição do Curso de Aperfeiçoamento para Magistradas e Magistrados "Gestão e Produtividade no 1º grau de jurisdição: Projudi e outras ferramentas" | G17: 2024 | H17: 45561 | I17: 45600 | J17: 40 h | K17: 1 | L17: 672bbf59-78e0-402a-95fa-fef6ac1f0214
A18: 0022329-56.2025.8.16.6000 | B18: LEONARDO MARCIO LAUREANO | C18: 0107063-71.2024.8.16.6000 | D18: Estudante | E18: Curso de Formação de Formadores Nível 2 “Formação de Tutores no Contexto da Magistratura | F18: 084/2021 | G18: 2024 | H18: 45561 | I18: 45600 | J18: 40 h | K18: 1 | L18: 672a7d3e-ee60-4909-a8ed-febbac1f0214
A19: 0022329-56.2025.8.16.6000 | B19: LEONARDO MARCIO LAUREANO | C19: 0115386-65.2024.8.16.6000 | D19: Estudante | E19: I Congresso de Inovação em Inteligência Artificial no Judiciário | G19: 2025 | H19: 45672 | I19: 45674 | J19: 10 | L19: 6792ba66-58d0-46a2-b5e4-2812ac1f0214
A20: 0022329-56.2025.8.16.6000 | B20: LEONARDO MARCIO LAUREANO | C20: 0012839-10.2025.8.16.6000 | D20: Estudante | E20: Lançamento do Programa Paraná-Lilás, Selo CEVID/TJPR e Concurso de Redação | G20: 2025 | H20: 45728 | I20: 45728 | J20: 2 h | L20: 67d32da8-5c98-4cf6-9a2b-d859ac1f0214
C21: 0033437-19.2024.8.16.6001 | D21: Estudante | E21: VI Encontro de Magistrados da Infância e Juventude | F21: 23/2025 | G21: 2025 | H21: 45742 | I21: 45751 | J21: 23 h | L21: 67f43802-d2f0-45a0-ab27-cf0dac1f0214
D23: GUSTAVO RAMOS GONÇALVES
A24: sei de solicitação | B24: NOME | C24: SEI | D24: FUNÇÃO OCUPADA | E24: Nome do Curso | F24: Portaria ENFAM | G24: Ano do curso | H24: Data de início | I24: Data de término | J24: Carga-horária | K24: Aproveitamento | L24: Código do certificado
A25: 0022329-56.2025.8.16.6000 | B25: GUSTAVO RAMOS GONÇALVES | C25: 0125118-41.2022.8.16.6000 | D25: Estudante | E25: Curso de aperfeiçoamento para magistrados e magistradas atuantes na jurisdição da infância e da juventude". | F25: 334/2022 | G25: 2023 | H25: 44981 | I25: 45026 | J25: 40 h | K25: 1 | L25: 64c814ca-96f0-4bab-a223-ecaeac1f0214
D28: CARLOS EDUARDO DE OLIVEIRA MENDES
A29: sei de solicitação | B29: NOME | C29: SEI | D29: FUNÇÃO OCUPADA | E29: Nome do Curso | F29: Portaria ENFAM | G29: Ano do curso | H29: Data de início | I29: Data de término | J29: Carga-horária | K29: Aproveitamento | L29: Código do certificado
B30: CARLOS EDUARDO DE OLIVEIRA MENDES | C30: 0054248-34.2023.8.16.6000 | D30: Estudante | E30: Instruções BNMP | F30: não | G30: 2023 | H30: 45082 | I30: 45082 | J30: 4 h | K30: 1 | L30: 64a86aa1-df0c-4dfc-958d-69cfac1f0214
C31: 0062706-40.2023.8.16.6000 | D31: Estudante | E31: Curso de Aperfeiçoamento para Magistrados e Magistradas – Medidas Protetivas de Urgência no Âmbito da Lei 11340/2006. Fundamentos, questões controvertidas e efetividade | F31: 126/2023 | G31: 2023 | H31: 45092 | I31: 45131 | J31: 20 h | K31: 0.99 | L31: 64de5fa4-39ac-45b0-beb2-0619ac1f0214
C32: 0087271-34.2024.8.16.6000 | D32: Estudante | E32: Curso de Aperfeiçoamento para Magistradas e Magistrados sobre a Moderna Teoria do Conflito, Jurisdição, Gerenciamento do Processo e Consensualidade. | F32: 263/2023 | G32: 2024 | H32: 45512 | I32: 45544 | J32: 40h | K32: 1 | L32: 66e9afeb-96b0-41f7-8e15-9ca9ac1f0214
C33: 0154244-68.2024.8.16.6000 | D33: Estudante | E33: Lançamento do Copilot 365 | G33: 2024 | H33: 45596 | I33: 45596 | J33: 2 h | L33: 673ba233-f574-484f-a5f8-d44dac1f0214
C34: 0113498-61.2024.8.16.6000 | D34: Estudante | E34: Resolução de conflitos na era digital | F34: 96/2023 | G34: 2024 | H34: 45589 | I34: 45621 | J34: 30 h | K34: 1 | L34: 674f61be-da4c-424d-af64-bfb7ac1f0214
C35: 0113500-31.2024.8.16.6000 | D35: Estudante | E35: Depoimento Especial de Crianças e Adolescentes - 2024 | F35: 15/2024 | G35: 2024 | H35: 45568 | I35: 45607 | J35: 40 h | K35: 0.95 | L35: 6733aae5-1a34-4382-a6be-febaac1f0214
D39: DANIELA FERNANDES DE OLIVEIRA
A40: sei de solicitação | B40: NOME | C40: SEI | D40: FUNÇÃO OCUPADA | E40: Nome do Curso | F40: Portaria ENFAM | G40: Ano do curso | H40: Data de início | I40: Data de término | J40: Carga-horária | K40: Aproveitamento | L40: Código do certificado
B41: DANIELA FERNANDES DE OLIVEIRA | C41: 0054248-34.2023.8.16.6000 | D41: Estudante | E41: Instruções BNMP | F41: não | G41: 2023 | H41: 45082 | I41: 45082 | J41: 4 h | K41: 1 | L41: 64a86ab4-3344-4c2f-bb7d-69cfac1f0214
C42: 0013489-28.2023.8.16.6000 | D42: Estudante | E42: Curso de violência doméstica e familiar contra a mulher para Magistrados(as) | F42: 074/2023 | G42: 2023 | H42: 45141 | I42: 45180 | J42: 40 h | K42: 0.83 | L42: 65031385-6e68-4758-82ad-0621ac1f0214
C43: 0115504-46.2021.8.16.6000 | D43: Estudante | E43: Efeitos psicológicos e cognitivos da violência física contra a criança e o adolescente | G43: 2021 | H43: 44491 | I43: 44491 | J43: 2 h | L43: 61732432-3d8c-4296-93bd-a625ac1f0214
C44: 0028449-52.2024.8.16.6000 | D44: Estudante | E44: Curso de Aperfeiçoamento para Magistradas e Magistrados "Gestão e Produtividade no 1º grau de jurisdição: Projudi e outras ferramentas". | F44: 197/2023 | G44: 2024 | H44: 45372 | I44: 45411 | J44: 40 h | K44: 1 | L44: 66475124-f214-4677-acc9-061bac1f0214
D47: JOSÉ VALDIR HALUCH JUNIOR
C48: SEI | D48: FUNÇÃO OCUPADA | E48: Nome do Curso | F48: Portaria ENFAM | G48: Ano do curso | H48: Data de início | I48: Data de término | J48: Carga-horária | K48: Aproveitamento | L48: Código do certificado
A49: sei de solicitação | B49: NOME | C49: 0049493-35.2021.8.16.6000 | D49: Estudante | E49: Altos Estudos em Audiências de Custódia | G49: 2022 | H49: 44343 | I49: 44344 | J49: 3 h | K49: - | L49: 61d1f085-5538-4fad-afe0-f3e1ac1f0214
B50: JOSÉ VALDIR HALUCH JUNIOR | C50: 0008434-96.2023.8.16.6000 | D50: Estudante | E50: Formação de Tutores no Contexto da Magistratura - 3ª Edição | F50: 084/2021 | G50: 2023 | H50: 44994 | I50: 45035 | J50: 40 h | K50: 0.96 | L50: 64417cd9-1934-4180-8397-6ed0ac1f0214
C51: 0024045-89.2023.8.16.6000 | D51: Estudante | E51: Judicialização da Saúde Pública - Fundamentos e Práticas para a Atuação Judicial | F51: 146/2022 | G51: 2023 | H51: 45029 | I51: 45068 | J51: 40 h | K51: 1 | L51: 646e0c90-db70-4615-89be-3d27ac1f0214
C52: 0060586-87.2024.8.16.6000 | D52: Estudante | E52: DESAFIOS ATUAIS DO TRIBUNAL DO JÚRI | G52: 2024 | H52: 45415 | I52: 45415 | J52: 2 h | K52: - | L52: 665fa158-31b4-4d33-9b6f-03b8ac1f0214
D54: ELISA SABINO DE AZEVEDO DUARTE SILVA
C55: SEI | D55: FUNÇÃO OCUPADA | E55: Nome do Curso | F55: Portaria ENFAM | G55: Ano do curso | H55: Data de início | I55: Data de término | J55: Carga-horária | K55: Aproveitamento | L55: Código do certificado
C56: 0089129-71.2022.8.16.6000 | D56: Estudante | E56: O Protocolo para Julgamento com a Perspectiva de Gênero | F56: 157/2022 | G56: 2022 | H56: 44770 | I56: 44801 | J56: 26 h | K56: 1 | L56: 63167430-ed30-492b-bc5a-273eac1f0214
C57: 0054248-34.2023.8.16.6000 | D57: Estudante | E57: Instruções BNMP | F57: não | G57: 2023 | H57: 45082 | I57: 45082 | J57: 4 h | K57: 1 | L57: 64a86aef-e754-4acd-895f-69cfac1f0214
A58: sei de solicitação | B58: NOME | C58: 0128335-24.2024.8.16.6000 | D58: Estudante | E58: 3ª Edição do Curso de Aperfeiçoamento para Magistradas e Magistrados "Gestão e Produtividade no 1º grau de jurisdição: Projudi e outras ferramentas" | G58: 2024 | H58: 45561 | I58: 45600 | J58: 40 h | K58: 1 | L58: 672bbf5e-3c6c-4da5-b6cb-fef6ac1f0214
B59: ELISA SABINO DE AZEVEDO DUARTE SILVA | C59: 0132966-11.2024.8.16.6000 | D59: Estudante | E59: Atuação do Juiz Corregedor no Foro Extrajudicial | F59: 276/2024 | G59: 2024 | H59: 45603 | I59: 45635 | J59: 30 h | L59: 6761ac6f-2cd4-499b-bd19-27e4ac1f0214
D61: TAIS SILVA TEIXEIRA
C62: SEI | D62: FUNÇÃO OCUPADA | E62: Nome do Curso | F62: Portaria ENFAM | G62: Ano do curso | H62: Data de início | I62: Data de término | J62: Carga-horária | K62: Aproveitamento | L62: Código do certificado
A63: sei de solicitação | B63: NOME | C63: 0053825-11.2022.8.16.6000 | D63: Estudante | E63: Curso de Aperfeiçoamento para Magistrados em Violência Doméstica | F63: 85/2021 | G63: 2022 | H63: 14/07/2022 | I63: 44795 | J63: 40 h | K63: 0.88 | L63: 63060f1b-5e40-464c-bdea-b685ac1f0214
B64: TAIS SILVA TEIXEIRA | C64: 0089129-71.2022.8.16.6000 | D64: Estudante | E64: O Protocolo para Julgamento com a Perspectiva de Gênero | F64: 157/2022 | G64: 2022 | H64: 44770 | I64: 44801 | J64: 26 h | K64: 0.8 | L64: 63149a44-cef8-4963-b8ba-f158ac1f0214
C65: 0009727-09.2020.8.16.6000 | D65: Estudante | E65: Habilidades sociais no trabalho | G65: 2022 | H65: AUTOINSTRUCIONAL | I65: AUTOINSTRUCIONAL | J65: 20 h | K65: 1 | L65: 62e6daae-1990-4ffa-8026-1cbbac1f0214
C66: 0049493-35.2021.8.16.6000 | D66: Estudante | E66: Altos Estudos em Audiências de Custódia | G66: 2022 | H66: 44343 | I66: 44344 | J66: 3 h | L66: 61df6c39-ac18-43f5-b9a3-b522ac1f0214
C67: 0030036-51.2020.8.16.6000 | D67: Estudante | E67: Tríade da Felicidade | G67: 2022 | H67: AUTOINSTRUCIONAL | I67: AUTOINSTRUCIONAL | J67: 20 h | L67: 63402d12-7164-44e5-8ce7-de41ac1f0214
C68: 0080451-38.2020.8.16.6000 | D68: Estudante | E68: Lei de Introdução às Normas do Direito Brasileiro | G68: 2022 | H68: AUTOINSTRUCIONAL | I68: AUTOINSTRUCIONAL | J68: 8 h | L68: 62ca22cc-7e68-423f-a4e8-d2f0ac1f0214
C69: 0016082-98.2021.8.16.6000 | D69: Estudante | E69: Gestão de Conflitos e Técnicas de Negociação | G69: 2022 | H69: AUTOINSTRUCIONAL | I69: AUTOINSTRUCIONAL | J69: 20 h | L69: 62ff855a-0e90-4728-b409-901cac1f0214
C70: 0008434-96.2023.8.16.6000 | D70: Estudante | E70: Formação de Tutores no Contexto da Magistratura - 3ª Edição | F70: 084/2021 | G70: 2023 | H70: 44994 | I70: 45035 | J70: 40 h | K70: 1 | L70: 644170df-1760-4165-88e5-504cac1f0214
C71: 0054248-34.2023.8.16.6000 | D71: Estudante | E71: Instruções BNMP | F71: não | G71: 2023 | H71: 45082 | I71: 45082 | J71: 4 h | K71: 1 | L71: 64a86b04-6e18-43fc-8919-69cfac1f0214
C72: 0037697-42.2024.8.16.6000 | D72: Estudante | E72: Curso de Aperfeiçoamento para Magistrados e Magistradas em Audiências Concentradas na Jurisdição da Infância e da Juventude e Inspeções em Estabelecimentos Socioeducativos | F72: 102/2024 | G72: 2024 | H72: 45414 | I72: 45453 | J72: 40 h | K72: 0.98 | L72: 666b2259-ede8-43ee-baea-0647ac1f0214
D75: RENATA MATTOS FIDALGO
C76: SEI | D76: FUNÇÃO OCUPADA | E76: Nome do Curso | F76: Portaria ENFAM | G76: Ano do curso | H76: Data de início | I76: Data de término | J76: Carga-horária | K76: Aproveitamento | L76: Código do certificado
C77: 0054248-34.2023.8.16.6000 | D77: Estudante | E77: Instruções do BNMP 2.0 | F77: não | G77: 2023 | H77: 45082 | I77: 45082 | J77: 4 h | K77: 1 | L77: 64a86a62-bdd0-417f-9980-69cfac1f0214
A78: sei de solicitação | B78: NOME | C78: 0052563-89.2023.8.16.6000 | D78: Estudante | E78: II Fórum Paranaense de Violência Doméstica e Familiar contra a Mulher (FOVID/PR) | F78: não | G78: 2023 | H78: 45077 | I78: 45079 | J78: 23 h | K78: 1 | L78: 6480cec3-3210-4da6-95ed-6752ac1f0214
B79: RENATA MATTOS FIDALGO | C79: 0060586-87.2024.8.16.6000 | D79: Estudante | E79: DESAFIOS ATUAIS DO TRIBUNAL DO JÚRI | G79: 2024 | H79: 45415 | I79: 45415 | J79: 2 h | K79: - | L79: 665fa157-04d8-4a83-9baf-03b8ac1f0214
C80: 0037697-42.2024.8.16.6000 | D80: Estudante | E80: Curso de Aperfeiçoamento para Magistrados e Magistradas em Audiências Concentradas na Jurisdição da Infância e da Juventude e Inspeções em Estabelecimentos Socioeducativos | F80: 102/2024 | G80: 2024 | H80: 45414 | I80: 45453 | J80: 40 h | K80: 1 | L80: 66703a2e-f7ac-4d11-b792-1928ac1f0214
C81: 0012839-10.2025.8.16.6000 | D81: Estudante | E81: Lançamento do Programa Paraná-Lilás, Selo CEVID/TJPR e Concurso de Redação | G81: 2025 | H81: 45728 | I81: 45728 | J81: 2 h | L81: 67d32dd1-fe18-4a82-9781-d859ac1f0214
D84: FELIPE WOLLERTT DE FRANÇA
C85: SEI | D85: FUNÇÃO OCUPADA | E85: Nome do Curso | F85: Portaria ENFAM | G85: Ano do curso | H85: Data de início | I85: Data de término | J85: Carga-horária | K85: Aproveitamento | L85: Código do certificado
C86: 0054248-34.2023.8.16.6000 | D86: Estudante | E86: Instruções BNMP | F86: não | G86: 2023 | H86: 45082 | I86: 45082 | J86: 4 h | K86: 1 | L86: 64a86b15-3e00-4204-a96b-69cfac1f0214
C87: 0079751-57.2023.8.16.6000 | D87: Estudante | E87: Curso Formação de Formadores - Desenvolvimento Docente N1M1 | F87: 302/2021 | G87: 2023 | H87: 45141 | I87: 45166 | J87: 26 h | K87: 1 | L87: 65009b51-a290-4193-a63e-0622ac1f0214
C88: 0099801-07.2023.8.16.6000 | D88: Estudante | E88: Psicologia do Testemunho e Tomada de Decisão | F88: 214/2023 | G88: 2023 | H88: 45210 | I88: 45243 | J88: 30 h | K88: 0.85 | L88: 655bc24a-e194-4478-9d99-0611ac1f0214
C89: 0130508-55.2023.8.16.6000 | D89: Estudante | E89: Formação de Formadores – Desenvolvimento Docente – N1 M2 | F89: 105/2022 | G89: 2023 | H89: 45236 | I89: 45265 | J89: 40 H | K89: 1 | L89: 656e9575-cc60-491d-8862-c7eaac1f0214
C90: 0075223-43.2024.8.16.6000 | D90: Estudante | E90: Formação de Formadores - Desenvolvimento Docente - Nível 1 Módulo 3" (2ª edição) | F90: 324/2022 | G90: 2024 | H90: 45467 | I90: 45468 | J90: 16 h | K90: 1 | L90: 667dd548-9fdc-4d71-b951-ac5dac1f0214
C91: 0107304-45.2024.8.16.6000 | D91: Estudante | E91: A estrutura lógica das decisões em matéria penal - O método alemão de resolução de casos (Gutachtenstil) | G91: 2024 | H91: 45530 | I91: 45530 | J91: 5 h | K91: - | L91: 66d5ebd6-0088-4d8c-8cf8-d551ac1f0214
C92: 0067759-65.2024.8.16.6000 | D92: Estudante | E92: Ciclo de Workshops denominado: Campanha de Adoção Microsoft Office 365 - TJPR | G92: 2024 | H92: 45525 | I92: 45525 | J92: 2 h | L92: 674a1cd1-0c9c-474a-a4fc-ff05ac1f0214
D96: FERNANDO RAMON MACHADO DE ANDRADE
C97: SEI | D97: FUNÇÃO OCUPADA | E97: Nome do Curso | F97: Portaria ENFAM | G97: Ano do curso | H97: Data de início | I97: Data de término | J97: Carga-horária | K97: Aproveitamento | L97: Código do certificado
C98: 0033497-60.2022.8.16.6000 | D98: Estudante | E98: Gestão Cartorária | F98: 7/2022 | G98: 2022 | H98: 27/04/2022 | I98: 44718 | J98: 40 h | K98: 1 | L98: 629e1e66-7530-460b-839a-012dac1f0214
A99: sei de solicitação | B99: NOME | C99: 0039846-79.2022.8.16.6000 | D99: Estudante | E99: Gestão de Pessoas | F99: 96/2021 | G99: 2022 | H99: 02/06/2022 | I99: 44753 | J99: 40 h | K99: 1 | L99: 62d16689-4988-4a10-a2b7-0eebac1f0214
B100: FERNANDO RAMON MACHADO DE ANDRADE | C100: 0091733-39.2021.8.16.6000 | D100: Estudante | E100: IV Encontro de Magistrados e Magistrados atuantes na Jurisdição de Infância e Juventude | F100: 106/2022 | G100: 2022 | H100: 44707 | I100: 44715 | J100: 22 h | K100: 1 | L100: 629e1ce9-729c-4cb5-8755-fbb1ac1f0214
C101: 0101171-55.2022.8.16.6000 | D101: Estudante | E101: Demandas Repetitivas e os Grandes Litigantes: Possíveis Caminhos para a Efetividade do Sistema de Justiça Brasileiro | F101: 006/2022 | G101: 2022 | H101: 44840 | I101: 44879 | J101: 40 h | K101: 1 | L101: 63769236-8f78-4889-b7ee-c3bbac1f0214
C102: 0024045-89.2023.8.16.6000 | D102: Estudante | E102: Judicialização da Saúde Pública - Fundamentos e Práticas para a Atuação Judicial | F102: 146/2022 | G102: 2023 | H102: 45029 | I102: 45068 | J102: 40 h | K102: 1 | L102: 646e666c-79d0-4866-b841-2890ac1f0214
C103: 0054248-34.2023.8.16.6000 | D103: Estudante | E103: Instruções do BNMP 2.0 | F103: não | G103: 2023 | H103: 45082 | I103: 45082 | J103: 4 h | K103: 1 | L103: 64a86a0b-48d4-4a9b-89cd-69cfac1f0214
C104: 0079751-57.2023.8.16.6000 | D104: Estudante | E104: Curso Formação de Formadores - Desenvolvimento Docente N1M1 | F104: 302/2021 | G104: 2023 | H104: 45141 | I104: 45166 | J104: 26 h | K104: 1 | L104: 64f0d3f9-e040-49ae-a816-064bac1f0214
C105: 0130508-55.2023.8.16.6000 | D105: Estudante | E105: Formação de Formadores – Desenvolvimento Docente – N1 M2 | F105: 105/2022 | G105: 2023 | H105: 45236 | I105: 45265 | J105: 40 H | K105: 1 | L105: 65736b16-b258-4614-a0b8-0659ac1f0214
C106: 0075223-43.2024.8.16.6000 | D106: Estudante | E106: Formação de Formadores - Desenvolvimento Docente - Nível 1 Módulo 3" (2ª edição) | F106: 324/2022 | G106: 2024 | H106: 45467 | I106: 45468 | J106: 16 h | K106: 1 | L106: 667e460f-8670-4a40-928f-9cbbac1f0214
C107: 0128335-24.2024.8.16.6000 | D107: Estudante | E107: 3ª Edição do Curso de Aperfeiçoamento para Magistradas e Magistrados "Gestão e Produtividade no 1º grau de jurisdição: Projudi e outras ferramentas" | G107: 2024 | H107: 45561 | I107: 45600 | J107: 40 h | K107: 1 | L107: 672bbf54-5974-4698-9379-fef6ac1f0214
C108: 0012839-10.2025.8.16.6000 | D108: Estudante | E108: Lançamento do Programa Paraná-Lilás, Selo CEVID/TJPR e Concurso de Redação | G108: 2025 | H108: 45728 | I108: 45728 | J108: 2 h | L108: 67d32e6e-f978-4718-bebe-d859ac1f0214
D110: RAQUEL NEVES ALEXANDRE
C111: SEI | D111: FUNÇÃO OCUPADA | E111: Nome do Curso | F111: Portaria ENFAM | G111: Ano do curso | H111: Data de início | I111: Data de término | J111: Carga-horária | K111: Aproveitamento | L111: Código do certificado
C112: 0089129-71.2022.8.16.6000 | D112: Estudante | E112: O Protocolo para Julgamento com a Perspectiva de Gênero | F112: 157/2022 | G112: 2022 | H112: 44770 | I112: 44801 | J112: 26 h | K112: 1 | L112: 630f9e26-d2c4-4632-bd68-1b22ac1f0214
C113: 0108225-09.2021.8.16.6000 | D113: Estudante | E113: Curso de Introdução à Justiça Restaurativa | G113: 2022 | H113: AUTOINSTRUCIONAL | I113: AUTOINSTRUCIONAL | J113: 20 h | K113: 0.875 | L113: 62c6e4ef-db64-42af-ad15-f519ac1f0214
A114: sei de solicitação | B114: NOME | C114: 0054248-34.2023.8.16.6000 | D114: Estudante | E114: Instruções BNMP | F114: não | G114: 2023 | H114: 45082 | I114: 45082 | J114: 4 h | K114: 1 | L114: 64a86a06-1be8-426d-b607-69cfac1f0214
B115: RAQUEL NEVES ALEXANDRE | C115: 0052563-89.2023.8.16.6000 | D115: Estudante | E115: II Fórum Paranaense de Violência Doméstica e Familiar contra a Mulher (FOVID/PR) | F115: não | G115: 2023 | H115: 45077 | I115: 45079 | J115: 23 h | K115: 1 | L115: 6480cedc-b74c-441b-a525-6752ac1f0214
C116: 0101194-30.2024.8.16.6000 | D116: Estudante | E116: Análise probatória em processos judiciais de abuso sexual infantojuvenil | F116: 218/2024 | G116: 2024 | H116: 45526 | I116: 45565 | J116: 40 H | K116: 0.96 | L116: 67197e83-5c20-4e4b-ac81-2270ac1f0214
C117: 0128335-24.2024.8.16.6000 | D117: Estudante | E117: 3ª Edição do Curso de Aperfeiçoamento para Magistradas e Magistrados "Gestão e Produtividade no 1º grau de jurisdição: Projudi e outras ferramentas" | G117: 2024 | H117: 45561 | I117: 45600 | J117: 40 h | K117: 1 | L117: 672bbf53-7c48-4fb5-ac43-fef6ac1f0214
C118: 0132966-11.2024.8.16.6000 | D118: Estudante | E118: Atuação do Juiz Corregedor no Foro Extrajudicial | F118: 276/2024 | G118: 2024 | H118: 45603 | I118: 45635 | J118: 30 h | K118: 0.95 | L118: 6761ac61-5814-42eb-a844-27e4ac1f0214
C119: 0012839-10.2025.8.16.6000 | D119: Estudante | E119: Lançamento do Programa Paraná-Lilás, Selo CEVID/TJPR e Concurso de Redação | G119: 2025 | H119: 45728 | I119: 45728 | J119: 2 h | L119: 67d32df7-471c-4137-ad1d-d859ac1f0214

Sheet 0010491-19.2025.8.16.6000
A1: Período avaliativo: 24 (vinte e quatro) meses que antecederam a publicação do edital | B1: dezembro/2022 a 02/04/2025
D3: LEONARDO MARCIO LAUREANO
A4: sei de solicitação | B4: NOME | C4: SEI | D4: FUNÇÃO OCUPADA | E4: Nome do Curso | F4: Portaria ENFAM | G4: Ano do curso | H4: Data de início | I4: Data de término | J4: Carga-horária | K4: Aproveitamento | L4: Código do certificado
A5: 0022329-56.2025.8.16.6000 | B5: LEONARDO MARCIO LAUREANO | C5: 0072085-73.2021.8.16.6000 | D5: Estudante | E5: A Violência Doméstica, suas relações com ações cíveis em matéria de família e o atendimento humanizado | G5: 2022 | H5: AUTOINSTRUCIONAL | I5: AUTOINSTRUCIONAL | J5: 4 h | L5: 6323a58d-a0b4-4a36-a321-bf31ac1f0214
A6: 0022329-56.2025.8.16.6000 | B6: LEONARDO MARCIO LAUREANO | C6: 0014757-88.2021.8.16.6000 | D6: Estudante | E6: Curso Formação de Gestores: Liderança, Gestão e Indicadores de Desempenho | G6: 2023 | H6: AUTOINSTRUCIONAL | I6: AUTOINSTRUCIONAL | J6: 20 h | K6: 1 | L6: 6422621a-1be0-4ebf-a1e7-761dac1f0214
A7: 0022329-56.2025.8.16.6000 | B7: LEONARDO MARCIO LAUREANO | C7: 0020225-67.2020.8.16.6000 | D7: Estudante | E7: Sindicância e Processo Administrativo Disciplinar: fundamentos legais e administrativos | G7: 2022 | H7: AUTOINSTRUCIONAL | I7: AUTOINSTRUCIONAL | J7: 16 h | K7: 1 | L7: 6414bffa-7d78-406b-8fe4-975fac1f0214
A8: 0022329-56.2025.8.16.6000 | B8: LEONARDO MARCIO LAUREANO | C8: 0054248-34.2023.8.16.6000 | D8: Estudante | E8: Instruções BNMP | F8: não | G8: 2023 | H8: 45082 | I8: 45082 | J8: 4 h | K8: 1 | L8: 64a86a8c-fe3c-40c3-a8a7-69cfac1f0214
A9: 0022329-56.2025.8.16.6000 | B9: LEONARDO MARCIO LAUREANO | C9: 0037697-42.2024.8.16.6000 | D9: Estudante | E9: Curso de Aperfeiçoamento para Magistrados e Magistradas em Audiências Concentradas na Jurisdição da Infância e da Juventude e Inspeções em Estabelecimentos Socioeducativos | F9: 102/2024 | G9: 2024 | H9: 45414 | I9: 45453 | J9: 40 h | K9: 1 | L9: 666a16b6-0984-45f0-919c-061fac1f0214
A10: 0022329-56.2025.8.16.6000 | B10: LEONARDO MARCIO LAUREANO | C10: 0158165-69.2023.8.16.6000 | D10: Estudante | E10: III Fórum Paranaense de Violência Doméstica e Familiar contra a Mulher (FOVID/PR). | G10: 2024 | H10: 45462 | I10: 45464 | J10: 17 h | K10: 1 | L10: 667b37b6-719c-413e-b268-9c67ac1f0214
A11: 0022329-56.2025.8.16.6000 | B11: LEONARDO MARCIO LAUREANO | C11: 0048036-60.2024.8.16.6000 | D11: Estudante | E11: Construção da Decisão Judicial | F11: 98/2023 | G11: 2024 | H11: 45456 | I11: 45488 | J11: 30 h | K11: 1 | L11: 6698bb4f-116c-4978-bcd4-9c73ac1f0214
A12: 0022329-56.2025.8.16.6000 | B12: LEONARDO MARCIO LAUREANO | C12: 0059503-36.2024.8.16.6000 | D12: Estudante | E12: Justiça Restaurativa: aspectos teóricos e práticos no contexto da magistratura | F12: 175/2024 | G12: 2024 | H12: 45512 | I12: 45548 | J12: 40 h | K12: 1 | L12: 66eadbf0-348c-4855-82e4-9c89ac1f0214
A13: 0022329-56.2025.8.16.6000 | B13: LEONARDO MARCIO LAUREANO | C13: 0087271-34.2024.8.16.6000 | D13: Estudante | E13: Curso de Aperfeiçoamento para Magistradas e Magistrados sobre a Moderna Teoria do Conflito, Jurisdição, Gerenciamento do Processo e Consensualidade. | F13: 263/2023 | G13: 2024 | H13: 45512 | I13: 45544 | J13: 40h | K13: 1 | L13: 66e0c22d-9108-45a2-9464-9c65ac1f0214
A14: 0022329-56.2025.8.16.6000 | B14: LEONARDO MARCIO LAUREANO | C14: 0127169-25.2022.8.16.6000 | D14: Estudante | E14: Gestão por Competências na Administração Pública | G14: 2024 | H14: AUTOINSTRUCIONAL | I14: AUTOINSTRUCIONAL | J14: 20 h | K14: 1 | L14: 66bd6711-5d1c-4e06-b143-9c6aac1f0214
A15: 0022329-56.2025.8.16.6000 | B15: LEONARDO MARCIO LAUREANO | C15: 0095105-59.2022.8.16.6000 | D15: Estudante | E15: Gerenciamento de Riscos no Poder Judiciário do Estado do Paraná | G15: 2024 | H15: AUTOINSTRUCIONAL | I15: AUTOINSTRUCIONAL | J15: 13 h | K15: 1 | L15: 66be54be-79b8-4ee2-80e6-f33eac1f0214
A16: 0022329-56.2025.8.16.6000 | B16: LEONARDO MARCIO LAUREANO | C16: 0064934-61.2018.8.16.6000 | D16: Estudante | E16: Gestão por Competências | G16: 2024 | H16: AUTOINSTRUCIONAL | I16: AUTOINSTRUCIONAL | J16: 10 h | K16: 1 | L16: 66b2784e-92fc-4647-b7ef-7866ac1f0214
A17: 0022329-56.2025.8.16.6000 | B17: LEONARDO MARCIO LAUREANO | C17: 0128335-24.2024.8.16.6000 | D17: Estudante | E17: 3ª Edição do Curso de Aperfeiçoamento para Magistradas e Magistrados "Gestão e Produtividade no 1º grau de jurisdição: Projudi e outras ferramentas" | G17: 2024 | H17: 45561 | I17: 45600 | J17: 40 h | K17: 1 | L17: 672bbf59-78e0-402a-95fa-fef6ac1f0214
A18: 0022329-56.2025.8.16.6000 | B18: LEONARDO MARCIO LAUREANO | C18: 0107063-71.2024.8.16.6000 | D18: Estudante | E18: Curso de Formação de Formadores Nível 2 “Formação de Tutores no Contexto da Magistratura | F18: 084/2021 | G18: 2024 | H18: 45561 | I18: 45600 | J18: 40 h | K18: 1 | L18: 672a7d3e-ee60-4909-a8ed-febbac1f0214
A19: 0022329-56.2025.8.16.6000 | B19: LEONARDO MARCIO LAUREANO | C19: 0115386-65.2024.8.16.6000 | D19: Estudante | E19: I Congresso de Inovação em Inteligência Artificial no Judiciário | G19: 2025 | H19: 45672 | I19: 45674 | J19: 10 | L19: 6792ba66-58d0-46a2-b5e4-2812ac1f0214
A20: 0022329-56.2025.8.16.6000 | B20: LEONARDO MARCIO LAUREANO | C20: 0012839-10.2025.8.16.6000 | D20: Estudante | E20: Lançamento do Programa Paraná-Lilás, Selo CEVID/TJPR e Concurso de Redação | G20: 2025 | H20: 45728 | I20: 45728 | J20: 2 h | L20: 67d32da8-5c98-4cf6-9a2b-d859ac1f0214
C21: 0033437-19.2024.8.16.6001 | D21: Estudante | E21: VI Encontro de Magistrados da Infância e Juventude | F21: 23/2025 | G21: 2025 | H21: 45742 | I21: 45751 | J21: 23 h | L21: 67f43802-d2f0-45a0-ab27-cf0dac1f0214
D25: JOSÉ VALDIR HALUCH JUNIOR
C26: SEI | D26: FUNÇÃO OCUPADA | E26: Nome do Curso | F26: Portaria ENFAM | G26: Ano do curso | H26: Data de início | I26: Data de término | J26: Carga-horária | K26: Aproveitamento | L26: Código do certificado
A27: sei de solicitação | B27: NOME | C27: 0049493-35.2021.8.16.6000 | D27: Estudante | E27: Altos Estudos em Audiências de Custódia | G27: 2022 | H27: 44343 | I27: 44344 | J27: 3 h | K27: - | L27: 61d1f085-5538-4fad-afe0-f3e1ac1f0214
B28: JOSÉ VALDIR HALUCH JUNIOR | C28: 0008434-96.2023.8.16.6000 | D28: Estudante | E28: Formação de Tutores no Contexto da Magistratura - 3ª Edição | F28: 084/2021 | G28: 2023 | H28: 44994 | I28: 45035 | J28: 40 h | K28: 0.96 | L28: 64417cd9-1934-4180-8397-6ed0ac1f0214
C29: 0024045-89.2023.8.16.6000 | D29: Estudante | E29: Judicialização da Saúde Pública - Fundamentos e Práticas para a Atuação Judicial | F29: 146/2022 | G29: 2023 | H29: 45029 | I29: 45068 | J29: 40 h | K29: 1 | L29: 646e0c90-db70-4615-89be-3d27ac1f0214
C30: 0060586-87.2024.8.16.6000 | D30: Estudante | E30: DESAFIOS ATUAIS DO TRIBUNAL DO JÚRI | G30: 2024 | H30: 45415 | I30: 45415 | J30: 2 h | K30: - | L30: 665fa158-31b4-4d33-9b6f-03b8ac1f0214
D32: ELISA SABINO DE AZEVEDO DUARTE SILVA
C33: SEI | D33: FUNÇÃO OCUPADA | E33: Nome do Curso | F33: Portaria ENFAM | G33: Ano do curso | H33: Data de início | I33: Data de término | J33: Carga-horária | K33: Aproveitamento | L33: Código do certificado
